Workbook
Name UPDATE: 'Data Sheet'!$E$1

Sheet Financials>

Sheet HistoricalFS
B2: ="Historical Financial Statement - "&'Data Sheet'!B1 -> Historical Financial Statement - INFOSYS LTD
B3: Years | C3: ='Data Sheet'!B16 -> 42460 | D3: ='Data Sheet'!C16 -> 42825 | E3: ='Data Sheet'!D16 -> 43190 | F3: ='Data Sheet'!E16 -> 43555 | G3: ='Data Sheet'!F16 -> 43921 | H3: ='Data Sheet'!G16 -> 44286 | I3: ='Data Sheet'!H16 -> 44651 | J3: ='Data Sheet'!I16 -> 45016 | ... L3: ='Data Sheet'!K16 -> 45747
A5: # | B5: Income Statement
B6: Sales | C6: =IFERROR('Data Sheet'!B17,0) -> 62441 | D6: =IFERROR('Data Sheet'!C17,0) -> 68484 | E6: =IFERROR('Data Sheet'!D17,0) -> 70522 | F6: =IFERROR('Data Sheet'!E17,0) -> 82675 | G6: =IFERROR('Data Sheet'!F17,0) -> 90791 | H6: =IFERROR('Data Sheet'!G17,0) -> 100472 | I6: =IFERROR('Data Sheet'!H17,0) -> 121641 | J6: =IFERROR('Data Sheet'!I17,0) -> 146767 | ... L6: =IFERROR('Data Sheet'!K17,0) -> 162990
B7: Sales Growth | C7: - | D7: =D6/C6-1 -> 0.09677936 | E7: =E6/D6-1 -> 0.029758776 | F7: =F6/E6-1 -> 0.1723292 | G7: =G6/F6-1 -> 0.098167523 | H7: =H6/G6-1 -> 0.10662951 | I7: =I6/H6-1 -> 0.21069552 | J7: =J6/I6-1 -> 0.20655864 | K7: =K6/J6-1 -> 0.047033734 | L7: =L6/K6-1 -> 0.060649444
B9: COGS | C9: {=IFERROR(SUM('Data Sheet'!B20:B22-1*'Data Sheet'!B19),0)} -> 40492 | D9: {=IFERROR(SUM('Data Sheet'!C20:C22-1*'Data Sheet'!C19),0)} -> 44609 | E9: {=IFERROR(SUM('Data Sheet'!D20:D22-1*'Data Sheet'!D19),0)} -> 46395 | F9: {=IFERROR(SUM('Data Sheet'!E20:E22-1*'Data Sheet'!E19),0)} -> 55446 | G9: {=IFERROR(SUM('Data Sheet'!F20:F22-1*'Data Sheet'!F19),0)} -> 62210 | H9: {=IFERROR(SUM('Data Sheet'!G20:G22-1*'Data Sheet'!G19),0)} -> 68490 | I9: {=IFERROR(SUM('Data Sheet'!H20:H22-1*'Data Sheet'!H19),0)} -> 84819 | J9: {=IFERROR(SUM('Data Sheet'!I20:I22-1*'Data Sheet'!I19),0)} -> 104880 | ... L9: {=IFERROR(SUM('Data Sheet'!K20:K22-1*'Data Sheet'!K19),0)} -> 116585
B10: COGS % Sales | C10: - | D10: =D9/C9-1 -> 0.1016744 | E10: =E9/D9-1 -> 0.040036764 | F10: =F9/E9-1 -> 0.19508568 | G10: =G9/F9-1 -> 0.12199257 | H10: =H9/G9-1 -> 0.1009484 | I10: =I9/H9-1 -> 0.23841437 | J10: =J9/I9-1 -> 0.2365154 | K10: =K9/J9-1 -> 0.049103738 | L10: =L9/K9-1 -> 0.059574661
B12: Gross Profit | C12: =IFERROR(C6-C9,0) -> 21949 | D12: =IFERROR(D6-D9,0) -> 23875 | E12: =IFERROR(E6-E9,0) -> 24127 | F12: =IFERROR(F6-F9,0) -> 27229 | G12: =IFERROR(G6-G9,0) -> 28581 | H12: =IFERROR(H6-H9,0) -> 31982 | I12: =IFERROR(I6-I9,0) -> 36822 | J12: =IFERROR(J6-J9,0) -> 41887 | ... L12: =IFERROR(L6-L9,0) -> 46405
B13: Gross Profit Margins | C13: =C12/C6 -> 0.35151583 | D13: =D12/D6 -> 0.34862158 | E13: =E12/E6 -> 0.34212019 | F13: =F12/F6 -> 0.32934986 | G13: =G12/G6 -> 0.31479993 | H13: =H12/H6 -> 0.31831754 | I13: =I12/I6 -> 0.30271043 | J13: =J12/J6 -> 0.28539794 | ... L13: =L12/L6 -> 0.28471072
B15: Selling & General Expenses | C15: =IFERROR(SUM('Data Sheet'!B23:B24),0) -> 4870 | D15: =IFERROR(SUM('Data Sheet'!C23:C24),0) -> 5271 | E15: =IFERROR(SUM('Data Sheet'!D23:D24),0) -> 5305 | F15: =IFERROR(SUM('Data Sheet'!E23:E24),0) -> 7059 | G15: =IFERROR(SUM('Data Sheet'!F23:F24),0) -> 6314 | H15: =IFERROR(SUM('Data Sheet'!G23:G24),0) -> 4093 | I15: =IFERROR(SUM('Data Sheet'!H23:H24),0) -> 5331 | J15: =IFERROR(SUM('Data Sheet'!I23:I24),0) -> 6757 | ... L15: =IFERROR(SUM('Data Sheet'!K23:K24),0) -> 7169
B16: S&G Expenses % Sales | C16: =C15/C6 -> 0.077993626 | D16: =D15/D6 -> 0.076966883 | E16: =E15/E6 -> 0.075224753 | F16: =F15/F6 -> 0.085382522 | G16: =G15/G6 -> 0.069544338 | H16: =H15/H6 -> 0.040737718 | I16: =I15/I6 -> 0.043825684 | J16: =J15/J6 -> 0.04603896 | ... L16: =L15/L6 -> 0.043984294
B18: EBITDA | C18: =IFERROR(C12-C15,0) -> 17079 | D18: =IFERROR(D12-D15,0) -> 18604 | E18: =IFERROR(E12-E15,0) -> 18822 | F18: =IFERROR(F12-F15,0) -> 20170 | G18: =IFERROR(G12-G15,0) -> 22267 | H18: =IFERROR(H12-H15,0) -> 27889 | I18: =IFERROR(I12-I15,0) -> 31491 | J18: =IFERROR(J12-J15,0) -> 35130 | ... L18: =IFERROR(L12-L15,0) -> 39236
B19: EBITDA Margins | C19: =IFERROR(C18/C6,0) -> 0.2735222 | D19: =IFERROR(D18/D6,0) -> 0.27165469 | E19: =IFERROR(E18/E6,0) -> 0.26689544 | F19: =IFERROR(F18/F6,0) -> 0.24396734 | G19: =IFERROR(G18/G6,0) -> 0.24525559 | H19: =IFERROR(H18/H6,0) -> 0.27757982 | I19: =IFERROR(I18/I6,0) -> 0.25888475 | J19: =IFERROR(J18/J6,0) -> 0.23935898 | ... L19: =IFERROR(L18/L6,0) -> 0.24072642
B21: Interest | C21: =IFERROR('Data Sheet'!B27,0) -> 0 | D21: =IFERROR('Data Sheet'!C27,0) -> 0 | E21: =IFERROR('Data Sheet'!D27,0) -> 0 | F21: =IFERROR('Data Sheet'!E27,0) -> 0 | G21: =IFERROR('Data Sheet'!F27,0) -> 170 | H21: =IFERROR('Data Sheet'!G27,0) -> 195 | I21: =IFERROR('Data Sheet'!H27,0) -> 200 | J21: =IFERROR('Data Sheet'!I27,0) -> 284 | ... L21: =IFERROR('Data Sheet'!K27,0) -> 416
B22: Interest % Sales | C22: =IFERROR(C21/C6,0) -> 0 | D22: =IFERROR(D21/D6,0) -> 0 | E22: =IFERROR(E21/E6,0) -> 0 | F22: =IFERROR(F21/F6,0) -> 0 | G22: =IFERROR(G21/G6,0) -> 0.0018724323 | H22: =IFERROR(H21/H6,0) -> 0.0019408392 | I22: =IFERROR(I21/I6,0) -> 0.0016441825 | J22: =IFERROR(J21/J6,0) -> 0.0019350399 | ... L22: =IFERROR(L21/L6,0) -> 0.0025523038
B24: Depreciation | C24: =IFERROR('Data Sheet'!B26,0) -> 1459 | D24: =IFERROR('Data Sheet'!C26,0) -> 1703 | E24: =IFERROR('Data Sheet'!D26,0) -> 1863 | F24: =IFERROR('Data Sheet'!E26,0) -> 2011 | G24: =IFERROR('Data Sheet'!F26,0) -> 2893 | H24: =IFERROR('Data Sheet'!G26,0) -> 3267 | I24: =IFERROR('Data Sheet'!H26,0) -> 3476 | J24: =IFERROR('Data Sheet'!I26,0) -> 4225 | ... L24: =IFERROR('Data Sheet'!K26,0) -> 4812
B25: Depreciation % Sales | C25: =IFERROR(C24/C6,0) -> 0.023366058 | D25: =IFERROR(D24/D6,0) -> 0.024867122 | E25: =IFERROR(E24/E6,0) -> 0.026417288 | F25: =IFERROR(F24/F6,0) -> 0.024324161 | G25: =IFERROR(G24/G6,0) -> 0.031864392 | H25: =IFERROR(H24/H6,0) -> 0.032516522 | I25: =IFERROR(I24/I6,0) -> 0.028575891 | J25: =IFERROR(J24/J6,0) -> 0.028787125 | ... L25: =IFERROR(L24/L6,0) -> 0.029523284
B27: EBT | C27: =IFERROR(C18-SUM(C24,C21),0) -> 15620 | D27: =IFERROR(D18-SUM(D24,D21),0) -> 16901 | E27: =IFERROR(E18-SUM(E24,E21),0) -> 16959 | F27: =IFERROR(F18-SUM(F24,F21),0) -> 18159 | G27: =IFERROR(G18-SUM(G24,G21),0) -> 19204 | H27: =IFERROR(H18-SUM(H24,H21),0) -> 24427 | I27: =IFERROR(I18-SUM(I24,I21),0) -> 27815 | J27: =IFERROR(J18-SUM(J24,J21),0) -> 30621 | ... L27: =IFERROR(L18-SUM(L24,L21),0) -> 34008
B28: EBT % Sales | C28: =IFERROR(C27/C6,0) -> 0.25015615 | D28: =IFERROR(D27/D6,0) -> 0.24678757 | E28: =IFERROR(E27/E6,0) -> 0.24047815 | F28: =IFERROR(F27/F6,0) -> 0.21964318 | G28: =IFERROR(G27/G6,0) -> 0.21151876 | H28: =IFERROR(H27/H6,0) -> 0.24312246 | I28: =IFERROR(I27/I6,0) -> 0.22866468 | J28: =IFERROR(J27/J6,0) -> 0.20863682 | ... L28: =IFERROR(L27/L6,0) -> 0.20865084
B30: Tax | C30: =IFERROR('Data Sheet'!B29,0) -> 5251 | D30: =IFERROR('Data Sheet'!C29,0) -> 5598 | E30: =IFERROR('Data Sheet'!D29,0) -> 4241 | F30: =IFERROR('Data Sheet'!E29,0) -> 5631 | G30: =IFERROR('Data Sheet'!F29,0) -> 5368 | H30: =IFERROR('Data Sheet'!G29,0) -> 7205 | I30: =IFERROR('Data Sheet'!H29,0) -> 7964 | J30: =IFERROR('Data Sheet'!I29,0) -> 9214 | ... L30: =IFERROR('Data Sheet'!K29,0) -> 10858
B31: Effective Tax Rate | C31: =IFERROR(C30/C27,0) -> 0.33617157 | D31: =IFERROR(D30/D27,0) -> 0.331223 | E31: =IFERROR(E30/E27,0) -> 0.25007371 | F31: =IFERROR(F30/F27,0) -> 0.31009417 | G31: =IFERROR(G30/G27,0) -> 0.2795251 | H31: =IFERROR(H30/H27,0) -> 0.29496049 | I31: =IFERROR(I30/I27,0) -> 0.28632033 | J31: =IFERROR(J30/J27,0) -> 0.30090461 | ... L31: =IFERROR(L30/L27,0) -> 0.31927782
B33: Net Profit | C33: =IFERROR(C27-C30,0) -> 10369 | D33: =IFERROR(D27-D30,0) -> 11303 | E33: =IFERROR(E27-E30,0) -> 12718 | F33: =IFERROR(F27-F30,0) -> 12528 | G33: =IFERROR(G27-G30,0) -> 13836 | H33: =IFERROR(H27-H30,0) -> 17222 | I33: =IFERROR(I27-I30,0) -> 19851 | J33: =IFERROR(J27-J30,0) -> 21407 | ... L33: =IFERROR(L27-L30,0) -> 23150
B34: Net Margins | C34: =IFERROR(C33/C6,0) -> 0.16606076 | D34: =IFERROR(D33/D6,0) -> 0.16504585 | E34: =IFERROR(E33/E6,0) -> 0.18034089 | F34: =IFERROR(F33/F6,0) -> 0.15153311 | G34: =IFERROR(G33/G6,0) -> 0.15239396 | H34: =IFERROR(H33/H6,0) -> 0.17141094 | I34: =IFERROR(I33/I6,0) -> 0.16319333 | J34: =IFERROR(J33/J6,0) -> 0.14585704 | ... L34: =IFERROR(L33/L6,0) -> 0.14203325
B36: No. of Equity Shares | C36: =IFERROR('Data Sheet'!B95,0) -> 459.39 | D36: =IFERROR('Data Sheet'!C95,0) -> 459.39 | E36: =IFERROR('Data Sheet'!D95,0) -> 436.82 | F36: =IFERROR('Data Sheet'!E95,0) -> 436.89 | G36: =IFERROR('Data Sheet'!F95,0) -> 425.9 | H36: =IFERROR('Data Sheet'!G95,0) -> 426.07 | I36: =IFERROR('Data Sheet'!H95,0) -> 420.67 | J36: =IFERROR('Data Sheet'!I95,0) -> 414.86 | ... L36: =IFERROR('Data Sheet'!K95,0) -> 415.33
B38: EPS | C38: =IFERROR(C33/C36,0) -> 22.571236 | D38: =IFERROR(D33/D36,0) -> 24.604367 | E38: =IFERROR(E33/E36,0) -> 29.114967 | F38: =IFERROR(F33/F36,0) -> 28.67541 | G38: =IFERROR(G33/G36,0) -> 32.486499 | H38: =IFERROR(H33/H36,0) -> 40.420588 | I38: =IFERROR(I33/I36,0) -> 47.189008 | J38: =IFERROR(J33/J36,0) -> 51.60054 | ... L38: =IFERROR(L33/L36,0) -> 55.73881
B39: EPS Growth % | D39: =IFERROR(D38/C38-1,0) -> 0.090076189 | E39: =IFERROR(E38/D38-1,0) -> 0.18332521 | F39: =IFERROR(F38/E38-1,0) -> -0.015097286 | G39: =IFERROR(G38/F38-1,0) -> 0.13290442 | H39: =IFERROR(H38/G38-1,0) -> 0.24422727 | I39: =IFERROR(I38/H38-1,0) -> 0.16744981 | J39: =IFERROR(J38/I38-1,0) -> 0.093486431 | K39: =IFERROR(K38/J38-1,0) -> 0.0055153183 | L39: =IFERROR(L38/K38-1,0) -> 0.074273236
B41: Divident Per Share | C41: =IFERROR('Data Sheet'!B31/HistoricalFS!C36,0) -> 12.077755 | D41: =IFERROR('Data Sheet'!C31/HistoricalFS!D36,0) -> 12.824833 | E41: =IFERROR('Data Sheet'!D31/HistoricalFS!E36,0) -> 21.669337 | F41: =IFERROR('Data Sheet'!E31/HistoricalFS!F36,0) -> 21.109433 | G41: =IFERROR('Data Sheet'!F31/HistoricalFS!G36,0) -> 17.438366 | H41: =IFERROR('Data Sheet'!G31/HistoricalFS!H36,0) -> 26.91952 | I41: =IFERROR('Data Sheet'!H31/HistoricalFS!I36,0) -> 30.92115 | J41: =IFERROR('Data Sheet'!I31/HistoricalFS!J36,0) -> 33.913127 | ... L41: =IFERROR('Data Sheet'!K31/HistoricalFS!L36,0) -> 42.924422
B42: Divident Payout Ratio | C42: =IFERROR(C41/C38,0) -> 0.53509499 | D42: =IFERROR(D41/D38,0) -> 0.52124215 | E42: =IFERROR(E41/E38,0) -> 0.74426797 | F42: =IFERROR(F41/F38,0) -> 0.73615102 | G42: =IFERROR(G41/G38,0) -> 0.53678809 | H42: =IFERROR(H41/H38,0) -> 0.66598537 | I42: =IFERROR(I41/I38,0) -> 0.6552617 | J42: =IFERROR(J41/J38,0) -> 0.65722427 | ... L42: =IFERROR(L41/L38,0) -> 0.77009935
B44: Retained Earnings | C44: =IFERROR(IF(C38>C41,1-C42,0),0) -> 0.46490501 | D44: =IFERROR(IF(D38>D41,1-D42,0),0) -> 0.47875785 | E44: =IFERROR(IF(E38>E41,1-E42,0),0) -> 0.25573203 | F44: =IFERROR(IF(F38>F41,1-F42,0),0) -> 0.26384898 | G44: =IFERROR(IF(G38>G41,1-G42,0),0) -> 0.46321191 | H44: =IFERROR(IF(H38>H41,1-H42,0),0) -> 0.33401463 | I44: =IFERROR(IF(I38>I41,1-I42,0),0) -> 0.3447383 | J44: =IFERROR(IF(J38>J41,1-J42,0),0) -> 0.34277573 | ... L44: =IFERROR(IF(L38>L41,1-L42,0),0) -> 0.22990065
A46: # | B46: Balance Sheet
B47: Equity Share Capital | C47: =IFERROR('Data Sheet'!B57,0) -> 1144 | D47: =IFERROR('Data Sheet'!C57,0) -> 1144 | E47: =IFERROR('Data Sheet'!D57,0) -> 1088 | F47: =IFERROR('Data Sheet'!E57,0) -> 2170 | G47: =IFERROR('Data Sheet'!F57,0) -> 2122 | H47: =IFERROR('Data Sheet'!G57,0) -> 2124 | I47: =IFERROR('Data Sheet'!H57,0) -> 2098 | J47: =IFERROR('Data Sheet'!I57,0) -> 2069 | ... L47: =IFERROR('Data Sheet'!K57,0) -> 2073
B48: Reserves | C48: =IFERROR('Data Sheet'!B58,0) -> 60600 | D48: =IFERROR('Data Sheet'!C58,0) -> 67838 | E48: =IFERROR('Data Sheet'!D58,0) -> 63835 | F48: =IFERROR('Data Sheet'!E58,0) -> 62778 | G48: =IFERROR('Data Sheet'!F58,0) -> 63328 | H48: =IFERROR('Data Sheet'!G58,0) -> 74227 | I48: =IFERROR('Data Sheet'!H58,0) -> 73252 | J48: =IFERROR('Data Sheet'!I58,0) -> 73338 | ... L48: =IFERROR('Data Sheet'!K58,0) -> 93745
B49: Borrowings | C49: =IFERROR('Data Sheet'!B59,0) -> 0 | D49: =IFERROR('Data Sheet'!C59,0) -> 0 | E49: =IFERROR('Data Sheet'!D59,0) -> 0 | F49: =IFERROR('Data Sheet'!E59,0) -> 0 | G49: =IFERROR('Data Sheet'!F59,0) -> 4633 | H49: =IFERROR('Data Sheet'!G59,0) -> 5325 | I49: =IFERROR('Data Sheet'!H59,0) -> 5474 | J49: =IFERROR('Data Sheet'!I59,0) -> 8299 | ... L49: =IFERROR('Data Sheet'!K59,0) -> 8227
B50: Other Liabilities | C50: =IFERROR('Data Sheet'!B60,0) -> 13354 | D50: =IFERROR('Data Sheet'!C60,0) -> 14166 | E50: =IFERROR('Data Sheet'!D60,0) -> 14426 | F50: =IFERROR('Data Sheet'!E60,0) -> 19118 | G50: =IFERROR('Data Sheet'!F60,0) -> 21717 | H50: =IFERROR('Data Sheet'!G60,0) -> 25835 | I50: =IFERROR('Data Sheet'!H60,0) -> 35905 | J50: =IFERROR('Data Sheet'!I60,0) -> 40890 | ... L50: =IFERROR('Data Sheet'!K60,0) -> 43750
B51: Total Liabilities | C51: =IFERROR('Data Sheet'!B61,0) -> 75098 | D51: =IFERROR('Data Sheet'!C61,0) -> 83148 | E51: =IFERROR('Data Sheet'!D61,0) -> 79349 | F51: =IFERROR('Data Sheet'!E61,0) -> 84066 | G51: =IFERROR('Data Sheet'!F61,0) -> 91800 | H51: =IFERROR('Data Sheet'!G61,0) -> 107511 | I51: =IFERROR('Data Sheet'!H61,0) -> 116729 | J51: =IFERROR('Data Sheet'!I61,0) -> 124596 | ... L51: =IFERROR('Data Sheet'!K61,0) -> 147795
B53: Fixed Assets Net Block | C53: =IFERROR('Data Sheet'!B62,0) -> 13386 | D53: =IFERROR('Data Sheet'!C62,0) -> 14179 | E53: =IFERROR('Data Sheet'!D62,0) -> 12574 | F53: =IFERROR('Data Sheet'!E62,0) -> 15710 | G53: =IFERROR('Data Sheet'!F62,0) -> 23789 | H53: =IFERROR('Data Sheet'!G62,0) -> 25505 | I53: =IFERROR('Data Sheet'!H62,0) -> 25800 | J53: =IFERROR('Data Sheet'!I62,0) -> 29225 | ... L53: =IFERROR('Data Sheet'!K62,0) -> 30961
B54: Capital Work in Progress | C54: =IFERROR('Data Sheet'!B63,0) -> 960 | D54: =IFERROR('Data Sheet'!C63,0) -> 1365 | E54: =IFERROR('Data Sheet'!D63,0) -> 1606 | F54: =IFERROR('Data Sheet'!E63,0) -> 1388 | G54: =IFERROR('Data Sheet'!F63,0) -> 954 | H54: =IFERROR('Data Sheet'!G63,0) -> 922 | I54: =IFERROR('Data Sheet'!H63,0) -> 416 | J54: =IFERROR('Data Sheet'!I63,0) -> 288 | ... L54: =IFERROR('Data Sheet'!K63,0) -> 814
B55: Investments | C55: =IFERROR('Data Sheet'!B64,0) -> 1892 | D55: =IFERROR('Data Sheet'!C64,0) -> 16423 | E55: =IFERROR('Data Sheet'!D64,0) -> 12163 | F55: =IFERROR('Data Sheet'!E64,0) -> 11261 | G55: =IFERROR('Data Sheet'!F64,0) -> 8792 | H55: =IFERROR('Data Sheet'!G64,0) -> 14205 | I55: =IFERROR('Data Sheet'!H64,0) -> 20324 | J55: =IFERROR('Data Sheet'!I64,0) -> 19478 | ... L55: =IFERROR('Data Sheet'!K64,0) -> 23541
B56: Other Assets | C56: =IFERROR('Data Sheet'!B65-SUM('Data Sheet'!B67:B69),0) -> 14833 | D56: =IFERROR('Data Sheet'!C65-SUM('Data Sheet'!C67:C69),0) -> 16234 | E56: =IFERROR('Data Sheet'!D65-SUM('Data Sheet'!D67:D69),0) -> 20046 | F56: =IFERROR('Data Sheet'!E65-SUM('Data Sheet'!E67:E69),0) -> 21312 | G56: =IFERROR('Data Sheet'!F65-SUM('Data Sheet'!F67:F69),0) -> 21129 | H56: =IFERROR('Data Sheet'!G65-SUM('Data Sheet'!G67:G69),0) -> 22871 | I56: =IFERROR('Data Sheet'!H65-SUM('Data Sheet'!H67:H69),0) -> 30019 | J56: =IFERROR('Data Sheet'!I65-SUM('Data Sheet'!I67:I69),0) -> 38008 | ... L56: =IFERROR('Data Sheet'!K65-SUM('Data Sheet'!K67:K69),0) -> 36866
B57: Total Non Current Assets | C57: =IFERROR(SUM(C53:C56),0) -> 31071 | D57: =IFERROR(SUM(D53:D56),0) -> 48201 | E57: =IFERROR(SUM(E53:E56),0) -> 46389 | F57: =IFERROR(SUM(F53:F56),0) -> 49671 | G57: =IFERROR(SUM(G53:G56),0) -> 54664 | H57: =IFERROR(SUM(H53:H56),0) -> 63503 | I57: =IFERROR(SUM(I53:I56),0) -> 76559 | J57: =IFERROR(SUM(J53:J56),0) -> 86999 | ... L57: =IFERROR(SUM(L53:L56),0) -> 92182
B59: Receivables | C59: =IFERROR('Data Sheet'!B67,0) -> 11330 | D59: =IFERROR('Data Sheet'!C67,0) -> 12322 | E59: =IFERROR('Data Sheet'!D67,0) -> 13142 | F59: =IFERROR('Data Sheet'!E67,0) -> 14827 | G59: =IFERROR('Data Sheet'!F67,0) -> 18487 | H59: =IFERROR('Data Sheet'!G67,0) -> 19294 | I59: =IFERROR('Data Sheet'!H67,0) -> 22698 | J59: =IFERROR('Data Sheet'!I67,0) -> 25424 | ... L59: =IFERROR('Data Sheet'!K67,0) -> 31158
B60: Inventory | C60: =IFERROR('Data Sheet'!B68,0) -> 0 | D60: =IFERROR('Data Sheet'!C68,0) -> 0 | E60: =IFERROR('Data Sheet'!D68,0) -> 0 | F60: =IFERROR('Data Sheet'!E68,0) -> 0 | G60: =IFERROR('Data Sheet'!F68,0) -> 0 | H60: =IFERROR('Data Sheet'!G68,0) -> 0 | I60: =IFERROR('Data Sheet'!H68,0) -> 0 | J60: =IFERROR('Data Sheet'!I68,0) -> 0 | ... L60: =IFERROR('Data Sheet'!K68,0) -> 0
B61: Cash & Bank | C61: =IFERROR('Data Sheet'!B69,0) -> 32697 | D61: =IFERROR('Data Sheet'!C69,0) -> 22625 | E61: =IFERROR('Data Sheet'!D69,0) -> 19818 | F61: =IFERROR('Data Sheet'!E69,0) -> 19568 | G61: =IFERROR('Data Sheet'!F69,0) -> 18649 | H61: =IFERROR('Data Sheet'!G69,0) -> 24714 | I61: =IFERROR('Data Sheet'!H69,0) -> 17472 | J61: =IFERROR('Data Sheet'!I69,0) -> 12173 | ... L61: =IFERROR('Data Sheet'!K69,0) -> 24455
B62: Total Current Assets | C62: =IFERROR(SUM(C59:C61),0) -> 44027 | D62: =IFERROR(SUM(D59:D61),0) -> 34947 | E62: =IFERROR(SUM(E59:E61),0) -> 32960 | F62: =IFERROR(SUM(F59:F61),0) -> 34395 | G62: =IFERROR(SUM(G59:G61),0) -> 37136 | H62: =IFERROR(SUM(H59:H61),0) -> 44008 | I62: =IFERROR(SUM(I59:I61),0) -> 40170 | J62: =IFERROR(SUM(J59:J61),0) -> 37597 | ... L62: =IFERROR(SUM(L59:L61),0) -> 55613
B64: Total Assets | C64: =IFERROR(SUM(C62,C57),0) -> 75098 | D64: =IFERROR(SUM(D62,D57),0) -> 83148 | E64: =IFERROR(SUM(E62,E57),0) -> 79349 | F64: =IFERROR(SUM(F62,F57),0) -> 84066 | G64: =IFERROR(SUM(G62,G57),0) -> 91800 | H64: =IFERROR(SUM(H62,H57),0) -> 107511 | I64: =IFERROR(SUM(I62,I57),0) -> 116729 | J64: =IFERROR(SUM(J62,J57),0) -> 124596 | ... L64: =IFERROR(SUM(L62,L57),0) -> 147795
B66: Check | C66: =C64=C51 -> TRUE | D66: =D64=D51 -> TRUE | E66: =E64=E51 -> TRUE | F66: =F64=F51 -> TRUE | G66: =G64=G51 -> TRUE | H66: =H64=H51 -> TRUE | I66: =I64=I51 -> TRUE | J66: =J64=J51 -> TRUE | ... L66: =L64=L51 -> TRUE
A68: # | B68: Cash Flow Statement
B69: Operating Activities
B70: Profit from operations | C70: =IFERROR('Cash Flow Data'!E5,0) -> 17839 | D70: =IFERROR('Cash Flow Data'!F5,0) -> 19340 | E70: =IFERROR('Cash Flow Data'!G5,0) -> 19963 | F70: =IFERROR('Cash Flow Data'!H5,0) -> 22126 | G70: =IFERROR('Cash Flow Data'!I5,0) -> 23920 | H70: =IFERROR('Cash Flow Data'!J5,0) -> 28845 | I70: =IFERROR('Cash Flow Data'!K5,0) -> 32921 | J70: =IFERROR('Cash Flow Data'!L5,0) -> 37605 | ... L70: =IFERROR('Cash Flow Data'!N5,0) -> 41591
B71: Receivables | C71: =IFERROR('Cash Flow Data'!E6,0) -> -1654 | D71: =IFERROR('Cash Flow Data'!F6,0) -> -1743 | E71: =IFERROR('Cash Flow Data'!G6,0) -> -1523 | F71: =IFERROR('Cash Flow Data'!H6,0) -> -2881 | G71: =IFERROR('Cash Flow Data'!I6,0) -> -3861 | H71: =IFERROR('Cash Flow Data'!J6,0) -> -1835 | I71: =IFERROR('Cash Flow Data'!K6,0) -> -7937 | J71: =IFERROR('Cash Flow Data'!L6,0) -> -7076 | ... L71: =IFERROR('Cash Flow Data'!N6,0) -> -1769
B72: Payables | C72: =IFERROR('Cash Flow Data'!E7,0) -> 242 | D72: =IFERROR('Cash Flow Data'!F7,0) -> -19 | E72: =IFERROR('Cash Flow Data'!G7,0) -> 328 | F72: =IFERROR('Cash Flow Data'!H7,0) -> 916 | G72: =IFERROR('Cash Flow Data'!I7,0) -> -373 | H72: =IFERROR('Cash Flow Data'!J7,0) -> -245 | I72: =IFERROR('Cash Flow Data'!K7,0) -> 1489 | J72: =IFERROR('Cash Flow Data'!L7,0) -> -279 | ... L72: =IFERROR('Cash Flow Data'!N7,0) -> 176
B73: Loans Advances | C73: =IFERROR('Cash Flow Data'!E8,0) -> -1134 | D73: =IFERROR('Cash Flow Data'!F8,0) -> 0 | E73: =IFERROR('Cash Flow Data'!G8,0) -> 0 | F73: =IFERROR('Cash Flow Data'!H8,0) -> 0 | G73: =IFERROR('Cash Flow Data'!I8,0) -> 0 | H73: =IFERROR('Cash Flow Data'!J8,0) -> -534 | I73: =IFERROR('Cash Flow Data'!K8,0) -> -1914 | J73: =IFERROR('Cash Flow Data'!L8,0) -> -3108 | ... L73: =IFERROR('Cash Flow Data'!N8,0) -> -1024
B74: Other WC items | C74: =IFERROR('Cash Flow Data'!E9,0) -> 600 | D74: =IFERROR('Cash Flow Data'!F9,0) -> -394 | E74: =IFERROR('Cash Flow Data'!G9,0) -> 1279 | F74: =IFERROR('Cash Flow Data'!H9,0) -> 1512 | G74: =IFERROR('Cash Flow Data'!I9,0) -> 1867 | H74: =IFERROR('Cash Flow Data'!J9,0) -> 3382 | I74: =IFERROR('Cash Flow Data'!K9,0) -> 6938 | J74: =IFERROR('Cash Flow Data'!L9,0) -> 4119 | ... L74: =IFERROR('Cash Flow Data'!N9,0) -> 2322
B75: Working capital changes | C75: =IFERROR('Cash Flow Data'!E10,0) -> -1946 | D75: =IFERROR('Cash Flow Data'!F10,0) -> -2156 | E75: =IFERROR('Cash Flow Data'!G10,0) -> 84 | F75: =IFERROR('Cash Flow Data'!H10,0) -> -453 | G75: =IFERROR('Cash Flow Data'!I10,0) -> -2367 | H75: =IFERROR('Cash Flow Data'!J10,0) -> 768 | I75: =IFERROR('Cash Flow Data'!K10,0) -> -1424 | J75: =IFERROR('Cash Flow Data'!L10,0) -> -6344 | ... L75: =IFERROR('Cash Flow Data'!N10,0) -> -295
B76: Direct taxes | C76: =IFERROR('Cash Flow Data'!E11,0) -> -5865 | D76: =IFERROR('Cash Flow Data'!F11,0) -> -5653 | E76: =IFERROR('Cash Flow Data'!G11,0) -> -6829 | F76: =IFERROR('Cash Flow Data'!H11,0) -> -6832 | G76: =IFERROR('Cash Flow Data'!I11,0) -> -4550 | H76: =IFERROR('Cash Flow Data'!J11,0) -> -6389 | I76: =IFERROR('Cash Flow Data'!K11,0) -> -7612 | J76: =IFERROR('Cash Flow Data'!L11,0) -> -8794 | ... L76: =IFERROR('Cash Flow Data'!N11,0) -> -5602
B77: Cash From Operating Activities | C77: =IFERROR(SUM(C70:C76),0) -> 8082 | D77: =IFERROR(SUM(D70:D76),0) -> 9375 | E77: =IFERROR(SUM(E70:E76),0) -> 13302 | F77: =IFERROR(SUM(F70:F76),0) -> 14388 | G77: =IFERROR(SUM(G70:G76),0) -> 14636 | H77: =IFERROR(SUM(H70:H76),0) -> 23992 | I77: =IFERROR(SUM(I70:I76),0) -> 22461 | J77: =IFERROR(SUM(J70:J76),0) -> 16123 | ... L77: =IFERROR(SUM(L70:L76),0) -> 35399
B79: Investing Activities
B80: Fixed assets purchased | C80: =IFERROR('Cash Flow Data'!E13,0) -> -2723 | D80: =IFERROR('Cash Flow Data'!F13,0) -> -2760 | E80: =IFERROR('Cash Flow Data'!G13,0) -> -1998 | F80: =IFERROR('Cash Flow Data'!H13,0) -> -2445 | G80: =IFERROR('Cash Flow Data'!I13,0) -> -3307 | H80: =IFERROR('Cash Flow Data'!J13,0) -> -2107 | I80: =IFERROR('Cash Flow Data'!K13,0) -> -2161 | J80: =IFERROR('Cash Flow Data'!L13,0) -> -2579 | ... L80: =IFERROR('Cash Flow Data'!N13,0) -> -2237
B81: Fixed assets sold | C81: =IFERROR('Cash Flow Data'!E14,0) -> 0 | D81: =IFERROR('Cash Flow Data'!F14,0) -> 0 | E81: =IFERROR('Cash Flow Data'!G14,0) -> 0 | F81: =IFERROR('Cash Flow Data'!H14,0) -> 0 | G81: =IFERROR('Cash Flow Data'!I14,0) -> 0 | H81: =IFERROR('Cash Flow Data'!J14,0) -> 0 | I81: =IFERROR('Cash Flow Data'!K14,0) -> 0 | J81: =IFERROR('Cash Flow Data'!L14,0) -> 0 | ... L81: =IFERROR('Cash Flow Data'!N14,0) -> 0
B82: Investments purchased | C82: =IFERROR('Cash Flow Data'!E15,0) -> -24577 | D82: =IFERROR('Cash Flow Data'!F15,0) -> -66410 | E82: =IFERROR('Cash Flow Data'!G15,0) -> -69159 | F82: =IFERROR('Cash Flow Data'!H15,0) -> -79410 | G82: =IFERROR('Cash Flow Data'!I15,0) -> -37482 | H82: =IFERROR('Cash Flow Data'!J15,0) -> -46738 | I82: =IFERROR('Cash Flow Data'!K15,0) -> -59951 | J82: =IFERROR('Cash Flow Data'!L15,0) -> -75800 | ... L82: =IFERROR('Cash Flow Data'!N15,0) -> -82753
B83: Investments sold | C83: =IFERROR('Cash Flow Data'!E16,0) -> 24980 | D83: =IFERROR('Cash Flow Data'!F16,0) -> 52048 | E83: =IFERROR('Cash Flow Data'!G16,0) -> 74003 | F83: =IFERROR('Cash Flow Data'!H16,0) -> 78098 | G83: =IFERROR('Cash Flow Data'!I16,0) -> 38861 | H83: =IFERROR('Cash Flow Data'!J16,0) -> 40381 | I83: =IFERROR('Cash Flow Data'!K16,0) -> 57356 | J83: =IFERROR('Cash Flow Data'!L16,0) -> 76722 | ... L83: =IFERROR('Cash Flow Data'!N16,0) -> 84888
B84: Interest received | C84: =IFERROR('Cash Flow Data'!E17,0) -> 2383 | D84: =IFERROR('Cash Flow Data'!F17,0) -> 0 | E84: =IFERROR('Cash Flow Data'!G17,0) -> 0 | F84: =IFERROR('Cash Flow Data'!H17,0) -> 0 | G84: =IFERROR('Cash Flow Data'!I17,0) -> 0 | H84: =IFERROR('Cash Flow Data'!J17,0) -> 0 | I84: =IFERROR('Cash Flow Data'!K17,0) -> 0 | J84: =IFERROR('Cash Flow Data'!L17,0) -> 0 | ... L84: =IFERROR('Cash Flow Data'!N17,0) -> 0
B85: Dividends received | C85: =IFERROR('Cash Flow Data'!E18,0) -> 0 | D85: =IFERROR('Cash Flow Data'!F18,0) -> 2753 | E85: =IFERROR('Cash Flow Data'!G18,0) -> 1768 | F85: =IFERROR('Cash Flow Data'!H18,0) -> 1557 | G85: =IFERROR('Cash Flow Data'!I18,0) -> 1929 | H85: =IFERROR('Cash Flow Data'!J18,0) -> 1418 | I85: =IFERROR('Cash Flow Data'!K18,0) -> 1898 | J85: =IFERROR('Cash Flow Data'!L18,0) -> 1525 | ... L85: =IFERROR('Cash Flow Data'!N18,0) -> 2040
B86: Acquisition of companies | C86: =IFERROR('Cash Flow Data'!E19,0) -> -747 | D86: =IFERROR('Cash Flow Data'!F19,0) -> 0 | E86: =IFERROR('Cash Flow Data'!G19,0) -> 0 | F86: =IFERROR('Cash Flow Data'!H19,0) -> 0 | G86: =IFERROR('Cash Flow Data'!I19,0) -> 0 | H86: =IFERROR('Cash Flow Data'!J19,0) -> 0 | I86: =IFERROR('Cash Flow Data'!K19,0) -> 0 | J86: =IFERROR('Cash Flow Data'!L19,0) -> 0 | ... L86: =IFERROR('Cash Flow Data'!N19,0) -> 0
B87: Inter corporate deposits | C87: =IFERROR('Cash Flow Data'!E20,0) -> -142 | D87: =IFERROR('Cash Flow Data'!F20,0) -> -164 | E87: =IFERROR('Cash Flow Data'!G20,0) -> -130 | F87: =IFERROR('Cash Flow Data'!H20,0) -> -24 | G87: =IFERROR('Cash Flow Data'!I20,0) -> -108 | H87: =IFERROR('Cash Flow Data'!J20,0) -> 0 | I87: =IFERROR('Cash Flow Data'!K20,0) -> 0 | J87: =IFERROR('Cash Flow Data'!L20,0) -> 0 | ... L87: =IFERROR('Cash Flow Data'!N20,0) -> 0
B88: Other investing items | C88: =IFERROR('Cash Flow Data'!E21,0) -> -59 | D88: =IFERROR('Cash Flow Data'!F21,0) -> -131 | E88: =IFERROR('Cash Flow Data'!G21,0) -> 49 | F88: =IFERROR('Cash Flow Data'!H21,0) -> 1592 | G88: =IFERROR('Cash Flow Data'!I21,0) -> -224 | H88: =IFERROR('Cash Flow Data'!J21,0) -> -327 | I88: =IFERROR('Cash Flow Data'!K21,0) -> -3627 | J88: =IFERROR('Cash Flow Data'!L21,0) -> -939 | ... L88: =IFERROR('Cash Flow Data'!N21,0) -> -3802
B89: Cash From Investing Activities | C89: =IFERROR(SUM(C80:C88),0) -> -885 | D89: =IFERROR(SUM(D80:D88),0) -> -14664 | E89: =IFERROR(SUM(E80:E88),0) -> 4533 | F89: =IFERROR(SUM(F80:F88),0) -> -632 | G89: =IFERROR(SUM(G80:G88),0) -> -331 | H89: =IFERROR(SUM(H80:H88),0) -> -7373 | I89: =IFERROR(SUM(I80:I88),0) -> -6485 | J89: =IFERROR(SUM(J80:J88),0) -> -1071 | ... L89: =IFERROR(SUM(L80:L88),0) -> -1864
B91: Financing Activities
B92: Proceeds from shares | C92: =IFERROR('Cash Flow Data'!E23,0) -> 0 | D92: =IFERROR('Cash Flow Data'!F23,0) -> 0 | E92: =IFERROR('Cash Flow Data'!G23,0) -> 5 | F92: =IFERROR('Cash Flow Data'!H23,0) -> 6 | G92: =IFERROR('Cash Flow Data'!I23,0) -> 6 | H92: =IFERROR('Cash Flow Data'!J23,0) -> 15 | I92: =IFERROR('Cash Flow Data'!K23,0) -> 21 | J92: =IFERROR('Cash Flow Data'!L23,0) -> 35 | ... L92: =IFERROR('Cash Flow Data'!N23,0) -> 6
B93: Repayment of borrowings | C93: =IFERROR('Cash Flow Data'!E24,0) -> 0 | D93: =IFERROR('Cash Flow Data'!F24,0) -> 0 | E93: =IFERROR('Cash Flow Data'!G24,0) -> 0 | F93: =IFERROR('Cash Flow Data'!H24,0) -> 0 | G93: =IFERROR('Cash Flow Data'!I24,0) -> 0 | H93: =IFERROR('Cash Flow Data'!J24,0) -> 0 | I93: =IFERROR('Cash Flow Data'!K24,0) -> 0 | J93: =IFERROR('Cash Flow Data'!L24,0) -> 0 | ... L93: =IFERROR('Cash Flow Data'!N24,0) -> -985
B94: Dividends paid | C94: =IFERROR('Cash Flow Data'!E25,0) -> -6813 | D94: =IFERROR('Cash Flow Data'!F25,0) -> -6939 | E94: =IFERROR('Cash Flow Data'!G25,0) -> -7464 | F94: =IFERROR('Cash Flow Data'!H25,0) -> -13705 | G94: =IFERROR('Cash Flow Data'!I25,0) -> -9548 | H94: =IFERROR('Cash Flow Data'!J25,0) -> -9137 | I94: =IFERROR('Cash Flow Data'!K25,0) -> -12731 | J94: =IFERROR('Cash Flow Data'!L25,0) -> -13653 | ... L94: =IFERROR('Cash Flow Data'!N25,0) -> -20289
B95: Financial liabilities | C95: =IFERROR('Cash Flow Data'!E26,0) -> 0 | D95: =IFERROR('Cash Flow Data'!F26,0) -> 0 | E95: =IFERROR('Cash Flow Data'!G26,0) -> 0 | F95: =IFERROR('Cash Flow Data'!H26,0) -> 0 | G95: =IFERROR('Cash Flow Data'!I26,0) -> -571 | H95: =IFERROR('Cash Flow Data'!J26,0) -> -698 | I95: =IFERROR('Cash Flow Data'!K26,0) -> -915 | J95: =IFERROR('Cash Flow Data'!L26,0) -> -1231 | ... L95: =IFERROR('Cash Flow Data'!N26,0) -> -2355
B96: Other financing items | C96: =IFERROR('Cash Flow Data'!E27,0) -> 0 | D96: =IFERROR('Cash Flow Data'!F27,0) -> 0 | E96: =IFERROR('Cash Flow Data'!G27,0) -> -13046 | F96: =IFERROR('Cash Flow Data'!H27,0) -> -813 | G96: =IFERROR('Cash Flow Data'!I27,0) -> -7478 | H96: =IFERROR('Cash Flow Data'!J27,0) -> 34 | I96: =IFERROR('Cash Flow Data'!K27,0) -> -11017 | J96: =IFERROR('Cash Flow Data'!L27,0) -> -11846 | ... L96: =IFERROR('Cash Flow Data'!N27,0) -> -538
B97: Cash From Financing Activities | C97: =IFERROR(SUM(C92:C96),0) -> -6813 | D97: =IFERROR(SUM(D92:D96),0) -> -6939 | E97: =IFERROR(SUM(E92:E96),0) -> -20505 | F97: =IFERROR(SUM(F92:F96),0) -> -14512 | G97: =IFERROR(SUM(G92:G96),0) -> -17591 | H97: =IFERROR(SUM(H92:H96),0) -> -9786 | I97: =IFERROR(SUM(I92:I96),0) -> -24642 | J97: =IFERROR(SUM(J92:J96),0) -> -26695 | ... L97: =IFERROR(SUM(L92:L96),0) -> -24161
B99: Net Cash Flow | C99: =IFERROR(SUM(C97,C89,C77),0) -> 384 | D99: =IFERROR(SUM(D97,D89,D77),0) -> -12228 | E99: =IFERROR(SUM(E97,E89,E77),0) -> -2670 | F99: =IFERROR(SUM(F97,F89,F77),0) -> -756 | G99: =IFERROR(SUM(G97,G89,G77),0) -> -3286 | H99: =IFERROR(SUM(H97,H89,H77),0) -> 6833 | I99: =IFERROR(SUM(I97,I89,I77),0) -> -8666 | J99: =IFERROR(SUM(J97,J89,J77),0) -> -11643 | ... L99: =IFERROR(SUM(L97,L89,L77),0) -> 9374

Sheet Ratio Analysis
B2: ="Ratio Analysis - "&'Data Sheet'!B1 -> Ratio Analysis - INFOSYS LTD
B3: Years | C3: ='Data Sheet'!B16 -> 42460 | D3: ='Data Sheet'!C16 -> 42825 | E3: ='Data Sheet'!D16 -> 43190 | F3: ='Data Sheet'!E16 -> 43555 | G3: ='Data Sheet'!F16 -> 43921 | H3: ='Data Sheet'!G16 -> 44286 | I3: ='Data Sheet'!H16 -> 44651 | J3: ='Data Sheet'!I16 -> 45016 | ... L3: ='Data Sheet'!K16 -> 45747 | M3: Trand | N3: Mean | O3: Median
B5: Sales Growth | C5: =IFERROR(HistoricalFS!C7,0) -> - | D5: =IFERROR(HistoricalFS!D7,0) -> 0.09677936 | E5: =IFERROR(HistoricalFS!E7,0) -> 0.029758776 | F5: =IFERROR(HistoricalFS!F7,0) -> 0.1723292 | G5: =IFERROR(HistoricalFS!G7,0) -> 0.098167523 | H5: =IFERROR(HistoricalFS!H7,0) -> 0.10662951 | I5: =IFERROR(HistoricalFS!I7,0) -> 0.21069552 | J5: =IFERROR(HistoricalFS!J7,0) -> 0.20655864 | ... L5: =IFERROR(HistoricalFS!L7,0) -> 0.060649444 | N5: =IFERROR(AVERAGE(D5:L5),0) -> 0.11428908 | O5: =IFERROR(MEDIAN(C5:L5),0) -> 0.098167523
B6: EBITDA Growth | D6: =IFERROR(HistoricalFS!D18/HistoricalFS!C18-1,0) -> 0.089290942 | E6: =IFERROR(HistoricalFS!E18/HistoricalFS!D18-1,0) -> 0.01171791 | F6: =IFERROR(HistoricalFS!F18/HistoricalFS!E18-1,0) -> 0.071618319 | G6: =IFERROR(HistoricalFS!G18/HistoricalFS!F18-1,0) -> 0.10396629 | H6: =IFERROR(HistoricalFS!H18/HistoricalFS!G18-1,0) -> 0.25248125 | I6: =IFERROR(HistoricalFS!I18/HistoricalFS!H18-1,0) -> 0.12915486 | J6: =IFERROR(HistoricalFS!J18/HistoricalFS!I18-1,0) -> 0.11555683 | K6: =IFERROR(HistoricalFS!K18/HistoricalFS!J18-1,0) -> 0.03686308 | L6: =IFERROR(HistoricalFS!L18/HistoricalFS!K18-1,0) -> 0.077172272 | N6: =IFERROR(AVERAGE(D6:L6),0) -> 0.098646861 | O6: =IFERROR(MEDIAN(C6:L6),0) -> 0.089290942
B7: EBIT Growth | D7: =IFERROR(HistoricalFS!D27/HistoricalFS!C27-1,0) -> 0.082010243 | E7: =IFERROR(HistoricalFS!E27/HistoricalFS!D27-1,0) -> 0.0034317496 | F7: =IFERROR(HistoricalFS!F27/HistoricalFS!E27-1,0) -> 0.070758889 | G7: =IFERROR(HistoricalFS!G27/HistoricalFS!F27-1,0) -> 0.057547222 | H7: =IFERROR(HistoricalFS!H27/HistoricalFS!G27-1,0) -> 0.27197459 | I7: =IFERROR(HistoricalFS!I27/HistoricalFS!H27-1,0) -> 0.13869898 | J7: =IFERROR(HistoricalFS!J27/HistoricalFS!I27-1,0) -> 0.10088082 | K7: =IFERROR(HistoricalFS!K27/HistoricalFS!J27-1,0) -> 0.021423206 | L7: =IFERROR(HistoricalFS!L27/HistoricalFS!K27-1,0) -> 0.087316558 | N7: =IFERROR(AVERAGE(D7:L7),0) -> 0.092671362 | O7: =IFERROR(MEDIAN(C7:L7),0) -> 0.082010243
B8: Net Profit Growth | D8: =IFERROR(HistoricalFS!D33/HistoricalFS!C33-1,0) -> 0.090076189 | E8: =IFERROR(HistoricalFS!E33/HistoricalFS!D33-1,0) -> 0.125188 | F8: =IFERROR(HistoricalFS!F33/HistoricalFS!E33-1,0) -> -0.014939456 | G8: =IFERROR(HistoricalFS!G33/HistoricalFS!F33-1,0) -> 0.10440613 | H8: =IFERROR(HistoricalFS!H33/HistoricalFS!G33-1,0) -> 0.24472391 | I8: =IFERROR(HistoricalFS!I33/HistoricalFS!H33-1,0) -> 0.15265358 | J8: =IFERROR(HistoricalFS!J33/HistoricalFS!I33-1,0) -> 0.078383961 | K8: =IFERROR(HistoricalFS!K33/HistoricalFS!J33-1,0) -> 0.0060727799 | L8: =IFERROR(HistoricalFS!L33/HistoricalFS!K33-1,0) -> 0.074894368 | N8: =IFERROR(AVERAGE(D8:L8),0) -> 0.095717718 | O8: =IFERROR(MEDIAN(C8:L8),0) -> 0.090076189
B9: Divident Growth | D9: =IFERROR(HistoricalFS!D41/HistoricalFS!C41-1,0) -> 0.06185567 | E9: =IFERROR(HistoricalFS!E41/HistoricalFS!D41-1,0) -> 0.68963897 | F9: =IFERROR(HistoricalFS!F41/HistoricalFS!E41-1,0) -> -0.02583858 | G9: =IFERROR(HistoricalFS!G41/HistoricalFS!F41-1,0) -> -0.17390646 | H9: =IFERROR(HistoricalFS!H41/HistoricalFS!G41-1,0) -> 0.54369512 | I9: =IFERROR(HistoricalFS!I41/HistoricalFS!H41-1,0) -> 0.14865158 | J9: =IFERROR(HistoricalFS!J41/HistoricalFS!I41-1,0) -> 0.096761529 | K9: =IFERROR(HistoricalFS!K41/HistoricalFS!J41-1,0) -> 0.35349861 | L9: =IFERROR(HistoricalFS!L41/HistoricalFS!K41-1,0) -> -0.064855345 | N9: =IFERROR(AVERAGE(D9:L9),0) -> 0.18105568 | O9: =IFERROR(MEDIAN(C9:L9),0) -> 0.096761529
B11: Gross Margin | C11: =IFERROR(HistoricalFS!C13,0) -> 0.35151583 | D11: =IFERROR(HistoricalFS!D13,0) -> 0.34862158 | E11: =IFERROR(HistoricalFS!E13,0) -> 0.34212019 | F11: =IFERROR(HistoricalFS!F13,0) -> 0.32934986 | G11: =IFERROR(HistoricalFS!G13,0) -> 0.31479993 | H11: =IFERROR(HistoricalFS!H13,0) -> 0.31831754 | I11: =IFERROR(HistoricalFS!I13,0) -> 0.30271043 | J11: =IFERROR(HistoricalFS!J13,0) -> 0.28539794 | ... L11: =IFERROR(HistoricalFS!L13,0) -> 0.28471072 | N11: =IFERROR(AVERAGE(C11:L11),0) -> 0.31615292 | O11: =IFERROR(MEDIAN(C11:L11),0) -> 0.31655873
B12: EBITDA Margin | C12: =IFERROR(HistoricalFS!C19,0) -> 0.2735222 | D12: =IFERROR(HistoricalFS!D19,0) -> 0.27165469 | E12: =IFERROR(HistoricalFS!E19,0) -> 0.26689544 | F12: =IFERROR(HistoricalFS!F19,0) -> 0.24396734 | G12: =IFERROR(HistoricalFS!G19,0) -> 0.24525559 | H12: =IFERROR(HistoricalFS!H19,0) -> 0.27757982 | I12: =IFERROR(HistoricalFS!I19,0) -> 0.25888475 | J12: =IFERROR(HistoricalFS!J19,0) -> 0.23935898 | ... L12: =IFERROR(HistoricalFS!L19,0) -> 0.24072642 | N12: =IFERROR(AVERAGE(C12:L12),0) -> 0.25548792 | O12: =IFERROR(MEDIAN(C12:L12),0) -> 0.25207017
B13: EBIT Margin | C13: =IFERROR((HistoricalFS!C18-HistoricalFS!C24)/HistoricalFS!C6,0) -> 0.25015615 | D13: =IFERROR((HistoricalFS!D18-HistoricalFS!D24)/HistoricalFS!D6,0) -> 0.24678757 | E13: =IFERROR((HistoricalFS!E18-HistoricalFS!E24)/HistoricalFS!E6,0) -> 0.24047815 | F13: =IFERROR((HistoricalFS!F18-HistoricalFS!F24)/HistoricalFS!F6,0) -> 0.21964318 | G13: =IFERROR((HistoricalFS!G18-HistoricalFS!G24)/HistoricalFS!G6,0) -> 0.2133912 | H13: =IFERROR((HistoricalFS!H18-HistoricalFS!H24)/HistoricalFS!H6,0) -> 0.2450633 | I13: =IFERROR((HistoricalFS!I18-HistoricalFS!I24)/HistoricalFS!I6,0) -> 0.23030886 | J13: =IFERROR((HistoricalFS!J18-HistoricalFS!J24)/HistoricalFS!J6,0) -> 0.21057186 | ... L13: =IFERROR((HistoricalFS!L18-HistoricalFS!L24)/HistoricalFS!L6,0) -> 0.21120314 | N13: =IFERROR(AVERAGE(C13:L13),0) -> 0.22741955 | O13: =IFERROR(MEDIAN(C13:L13),0) -> 0.22497602
B14: EBT Margin | C14: =IFERROR(HistoricalFS!C28,0) -> 0.25015615 | D14: =IFERROR(HistoricalFS!D28,0) -> 0.24678757 | E14: =IFERROR(HistoricalFS!E28,0) -> 0.24047815 | F14: =IFERROR(HistoricalFS!F28,0) -> 0.21964318 | G14: =IFERROR(HistoricalFS!G28,0) -> 0.21151876 | H14: =IFERROR(HistoricalFS!H28,0) -> 0.24312246 | I14: =IFERROR(HistoricalFS!I28,0) -> 0.22866468 | J14: =IFERROR(HistoricalFS!J28,0) -> 0.20863682 | ... L14: =IFERROR(HistoricalFS!L28,0) -> 0.20865084 | N14: =IFERROR(AVERAGE(C14:L14),0) -> 0.22611922 | O14: =IFERROR(MEDIAN(C14:L14),0) -> 0.22415393
B15: Net Profit Margin | C15: =IFERROR(HistoricalFS!C34,0) -> 0.16606076 | D15: =IFERROR(HistoricalFS!D34,0) -> 0.16504585 | E15: =IFERROR(HistoricalFS!E34,0) -> 0.18034089 | F15: =IFERROR(HistoricalFS!F34,0) -> 0.15153311 | G15: =IFERROR(HistoricalFS!G34,0) -> 0.15239396 | H15: =IFERROR(HistoricalFS!H34,0) -> 0.17141094 | I15: =IFERROR(HistoricalFS!I34,0) -> 0.16319333 | J15: =IFERROR(HistoricalFS!J34,0) -> 0.14585704 | ... L15: =IFERROR(HistoricalFS!L34,0) -> 0.14203325 | N15: =IFERROR(AVERAGE(C15:L15),0) -> 0.15780201 | O15: =IFERROR(MEDIAN(C15:L15),0) -> 0.15779365
B17: Sales Expenses % Sales | C17: =IFERROR(HistoricalFS!C16,0) -> 0.077993626 | D17: =IFERROR(HistoricalFS!D16,0) -> 0.076966883 | E17: =IFERROR(HistoricalFS!E16,0) -> 0.075224753 | F17: =IFERROR(HistoricalFS!F16,0) -> 0.085382522 | G17: =IFERROR(HistoricalFS!G16,0) -> 0.069544338 | H17: =IFERROR(HistoricalFS!H16,0) -> 0.040737718 | I17: =IFERROR(HistoricalFS!I16,0) -> 0.043825684 | J17: =IFERROR(HistoricalFS!J16,0) -> 0.04603896 | ... L17: =IFERROR(HistoricalFS!L16,0) -> 0.043984294 | N17: =IFERROR(AVERAGE(C17:L17),0) -> 0.060665004 | O17: =IFERROR(MEDIAN(C17:L17),0) -> 0.058247799
B18: Depreciation % Sales | C18: =IFERROR(HistoricalFS!C25,0) -> 0.023366058 | D18: =IFERROR(HistoricalFS!D25,0) -> 0.024867122 | E18: =IFERROR(HistoricalFS!E25,0) -> 0.026417288 | F18: =IFERROR(HistoricalFS!F25,0) -> 0.024324161 | G18: =IFERROR(HistoricalFS!G25,0) -> 0.031864392 | H18: =IFERROR(HistoricalFS!H25,0) -> 0.032516522 | I18: =IFERROR(HistoricalFS!I25,0) -> 0.028575891 | J18: =IFERROR(HistoricalFS!J25,0) -> 0.028787125 | ... L18: =IFERROR(HistoricalFS!L25,0) -> 0.029523284 | N18: =IFERROR(AVERAGE(C18:L18),0) -> 0.02806837 | O18: =IFERROR(MEDIAN(C18:L18),0) -> 0.028681508
B19: Operating Income % Sales | C19: =C13 -> 0.25015615 | D19: =D13 -> 0.24678757 | E19: =E13 -> 0.24047815 | F19: =F13 -> 0.21964318 | G19: =G13 -> 0.2133912 | H19: =H13 -> 0.2450633 | I19: =I13 -> 0.23030886 | J19: =J13 -> 0.21057186 | ... L19: =L13 -> 0.21120314 | N19: =IFERROR(AVERAGE(C19:L19),0) -> 0.22741955 | O19: =IFERROR(MEDIAN(C19:L19),0) -> 0.22497602
B21: Return on Capital Employed | C21: =IFERROR((HistoricalFS!C18-HistoricalFS!C24)/SUM(HistoricalFS!C47:C49),0) -> 0.25298005 | D21: =IFERROR((HistoricalFS!D18-HistoricalFS!D24)/SUM(HistoricalFS!D47:D49),0) -> 0.24500594 | E21: =IFERROR((HistoricalFS!E18-HistoricalFS!E24)/SUM(HistoricalFS!E47:E49),0) -> 0.26121713 | F21: =IFERROR((HistoricalFS!F18-HistoricalFS!F24)/SUM(HistoricalFS!F47:F49),0) -> 0.27959291 | G21: =IFERROR((HistoricalFS!G18-HistoricalFS!G24)/SUM(HistoricalFS!G47:G49),0) -> 0.27644365 | H21: =IFERROR((HistoricalFS!H18-HistoricalFS!H24)/SUM(HistoricalFS!H47:H49),0) -> 0.30145943 | I21: =IFERROR((HistoricalFS!I18-HistoricalFS!I24)/SUM(HistoricalFS!I47:I49),0) -> 0.34661734 | J21: =IFERROR((HistoricalFS!J18-HistoricalFS!J24)/SUM(HistoricalFS!J47:J49),0) -> 0.3692089 | ... L21: =IFERROR((HistoricalFS!L18-HistoricalFS!L24)/SUM(HistoricalFS!L47:L49),0) -> 0.33085684 | N21: =IFERROR(AVERAGE(C21:L21),0) -> 0.29924519 | O21: =IFERROR(MEDIAN(C21:L21),0) -> 0.29052617
B22: Retained Earnings % | C22: =IFERROR(HistoricalFS!C44,0) -> 0.46490501 | D22: =IFERROR(HistoricalFS!D44,0) -> 0.47875785 | E22: =IFERROR(HistoricalFS!E44,0) -> 0.25573203 | F22: =IFERROR(HistoricalFS!F44,0) -> 0.26384898 | G22: =IFERROR(HistoricalFS!G44,0) -> 0.46321191 | H22: =IFERROR(HistoricalFS!H44,0) -> 0.33401463 | I22: =IFERROR(HistoricalFS!I44,0) -> 0.3447383 | J22: =IFERROR(HistoricalFS!J44,0) -> 0.34277573 | ... L22: =IFERROR(HistoricalFS!L44,0) -> 0.22990065 | N22: =IFERROR(AVERAGE(C22:L22),0) -> 0.32932122 | O22: =IFERROR(MEDIAN(C22:L22),0) -> 0.33839518
B23: Return on Equity % | C23: =IFERROR(HistoricalFS!C33/SUM(HistoricalFS!C47:C48),0) -> 0.16793535 | D23: =IFERROR(HistoricalFS!D33/SUM(HistoricalFS!D47:D48),0) -> 0.16385434 | E23: =IFERROR(HistoricalFS!E33/SUM(HistoricalFS!E47:E48),0) -> 0.1958936 | F23: =IFERROR(HistoricalFS!F33/SUM(HistoricalFS!F47:F48),0) -> 0.19289278 | G23: =IFERROR(HistoricalFS!G33/SUM(HistoricalFS!G47:G48),0) -> 0.21139801 | H23: =IFERROR(HistoricalFS!H33/SUM(HistoricalFS!H47:H48),0) -> 0.22556352 | I23: =IFERROR(HistoricalFS!I33/SUM(HistoricalFS!I47:I48),0) -> 0.26345056 | J23: =IFERROR(HistoricalFS!J33/SUM(HistoricalFS!J47:J48),0) -> 0.28388611 | ... L23: =IFERROR(HistoricalFS!L33/SUM(HistoricalFS!L47:L48),0) -> 0.24160387 | N23: =IFERROR(AVERAGE(C23:L23),0) -> 0.21908946 | O23: =IFERROR(MEDIAN(C23:L23),0) -> 0.21848076
B24: Self Sustained Growth Rate | C24: =IFERROR(C22*C23,0) -> 0.078073983 | D24: =IFERROR(D22*D23,0) -> 0.078446551 | E24: =IFERROR(E22*E23,0) -> 0.050096268 | F24: =IFERROR(F22*F23,0) -> 0.050894562 | G24: =IFERROR(G22*G23,0) -> 0.097922078 | H24: =IFERROR(H22*H23,0) -> 0.075341515 | I24: =IFERROR(I22*I23,0) -> 0.0908215 | J24: =IFERROR(J22*J23,0) -> 0.097309268 | ... L24: =IFERROR(L22*L23,0) -> 0.055544887 | N24: =IFERROR(AVERAGE(C24:L24),0) -> 0.070263846 | O24: =IFERROR(MEDIAN(C24:L24),0) -> 0.076707749
B25: Interest Coverage Ratio | C25: =IFERROR((HistoricalFS!C18-HistoricalFS!C24)/HistoricalFS!C21,0) -> 0 | D25: =IFERROR((HistoricalFS!D18-HistoricalFS!D24)/HistoricalFS!D21,0) -> 0 | E25: =IFERROR((HistoricalFS!E18-HistoricalFS!E24)/HistoricalFS!E21,0) -> 0 | F25: =IFERROR((HistoricalFS!F18-HistoricalFS!F24)/HistoricalFS!F21,0) -> 0 | G25: =IFERROR((HistoricalFS!G18-HistoricalFS!G24)/HistoricalFS!G21,0) -> 113.96471 | H25: =IFERROR((HistoricalFS!H18-HistoricalFS!H24)/HistoricalFS!H21,0) -> 126.26667 | I25: =IFERROR((HistoricalFS!I18-HistoricalFS!I24)/HistoricalFS!I21,0) -> 140.075 | J25: =IFERROR((HistoricalFS!J18-HistoricalFS!J24)/HistoricalFS!J21,0) -> 108.82042 | ... L25: =IFERROR((HistoricalFS!L18-HistoricalFS!L24)/HistoricalFS!L21,0) -> 82.75 | N25: =IFERROR(AVERAGE(C25:L25),0) -> 63.94236 | O25: =IFERROR(MEDIAN(C25:L25),0) -> 75.148404
B27: Debtor Turnover Ratio | C27: =IFERROR(HistoricalFS!C6/HistoricalFS!C59,0) -> 5.5111209 | D27: =IFERROR(HistoricalFS!D6/HistoricalFS!D59,0) -> 5.557864 | E27: =IFERROR(HistoricalFS!E6/HistoricalFS!E59,0) -> 5.3661543 | F27: =IFERROR(HistoricalFS!F6/HistoricalFS!F59,0) -> 5.5759763 | G27: =IFERROR(HistoricalFS!G6/HistoricalFS!G59,0) -> 4.9110726 | H27: =IFERROR(HistoricalFS!H6/HistoricalFS!H59,0) -> 5.207422 | I27: =IFERROR(HistoricalFS!I6/HistoricalFS!I59,0) -> 5.3591065 | J27: =IFERROR(HistoricalFS!J6/HistoricalFS!J59,0) -> 5.7727738 | ... L27: =IFERROR(HistoricalFS!L6/HistoricalFS!L59,0) -> 5.2310803 | N27: =IFERROR(AVERAGE(C27:L27),0) -> 5.3582161 | O27: =IFERROR(MEDIAN(C27:L27),0) -> 5.3626304
B28: Creditor Turnover Ratio | C28: =IFERROR(HistoricalFS!C6/HistoricalFS!C50,0) -> 4.6758275 | D28: =IFERROR(HistoricalFS!D6/HistoricalFS!D50,0) -> 4.8343922 | E28: =IFERROR(HistoricalFS!E6/HistoricalFS!E50,0) -> 4.8885346 | F28: =IFERROR(HistoricalFS!F6/HistoricalFS!F50,0) -> 4.3244586 | G28: =IFERROR(HistoricalFS!G6/HistoricalFS!G50,0) -> 4.1806419 | H28: =IFERROR(HistoricalFS!H6/HistoricalFS!H50,0) -> 3.8889878 | I28: =IFERROR(HistoricalFS!I6/HistoricalFS!I50,0) -> 3.3878568 | J28: =IFERROR(HistoricalFS!J6/HistoricalFS!J50,0) -> 3.5893128 | ... L28: =IFERROR(HistoricalFS!L6/HistoricalFS!L50,0) -> 3.7254857 | N28: =IFERROR(AVERAGE(C28:L28),0) -> 4.1254089 | O28: =IFERROR(MEDIAN(C28:L28),0) -> 4.0348149
B29: Inventory Turnover Ratio | C29: =IFERROR(HistoricalFS!C6/HistoricalFS!C60,0) -> 0 | D29: =IFERROR(HistoricalFS!D6/HistoricalFS!D60,0) -> 0 | E29: =IFERROR(HistoricalFS!E6/HistoricalFS!E60,0) -> 0 | F29: =IFERROR(HistoricalFS!F6/HistoricalFS!F60,0) -> 0 | G29: =IFERROR(HistoricalFS!G6/HistoricalFS!G60,0) -> 0 | H29: =IFERROR(HistoricalFS!H6/HistoricalFS!H60,0) -> 0 | I29: =IFERROR(HistoricalFS!I6/HistoricalFS!I60,0) -> 0 | J29: =IFERROR(HistoricalFS!J6/HistoricalFS!J60,0) -> 0 | ... L29: =IFERROR(HistoricalFS!L6/HistoricalFS!L60,0) -> 0 | N29: =IFERROR(AVERAGE(C29:L29),0) -> 0 | O29: =IFERROR(MEDIAN(C29:L29),0) -> 0
B30: Fixed Assets Turnover | C30: =IFERROR(HistoricalFS!C6/HistoricalFS!C53,0) -> 4.6646496 | D30: =IFERROR(HistoricalFS!D6/HistoricalFS!D53,0) -> 4.8299598 | E30: =IFERROR(HistoricalFS!E6/HistoricalFS!E53,0) -> 5.6085573 | F30: =IFERROR(HistoricalFS!F6/HistoricalFS!F53,0) -> 5.2625716 | G30: =IFERROR(HistoricalFS!G6/HistoricalFS!G53,0) -> 3.8165118 | H30: =IFERROR(HistoricalFS!H6/HistoricalFS!H53,0) -> 3.939306 | I30: =IFERROR(HistoricalFS!I6/HistoricalFS!I53,0) -> 4.7147674 | J30: =IFERROR(HistoricalFS!J6/HistoricalFS!J53,0) -> 5.0219675 | ... L30: =IFERROR(HistoricalFS!L6/HistoricalFS!L53,0) -> 5.2643648 | N30: =IFERROR(AVERAGE(C30:L30),0) -> 4.8685975 | O30: =IFERROR(MEDIAN(C30:L30),0) -> 4.9259636
B31: Capital Turnover Ratio | C31: =IFERROR(HistoricalFS!C6/SUM(HistoricalFS!C47:C48),0) -> 1.0112885 | D31: =IFERROR(HistoricalFS!D6/SUM(HistoricalFS!D47:D48),0) -> 0.99278073 | E31: =IFERROR(HistoricalFS!E6/SUM(HistoricalFS!E47:E48),0) -> 1.0862406 | F31: =IFERROR(HistoricalFS!F6/SUM(HistoricalFS!F47:F48),0) -> 1.2729414 | G31: =IFERROR(HistoricalFS!G6/SUM(HistoricalFS!G47:G48),0) -> 1.3871811 | H31: =IFERROR(HistoricalFS!H6/SUM(HistoricalFS!H47:H48),0) -> 1.3159225 | I31: =IFERROR(HistoricalFS!I6/SUM(HistoricalFS!I47:I48),0) -> 1.6143464 | J31: =IFERROR(HistoricalFS!J6/SUM(HistoricalFS!J47:J48),0) -> 1.9463312 | ... L31: =IFERROR(HistoricalFS!L6/SUM(HistoricalFS!L47:L48),0) -> 1.7010374 | N31: =IFERROR(AVERAGE(C31:L31),0) -> 1.4072021 | O31: =IFERROR(MEDIAN(C31:L31),0) -> 1.3515518
B33: (in days)
B34: Debtor Days | C34: =IFERROR(365/C27,0) -> 66.229721 | D34: =IFERROR(365/D27,0) -> 65.672712 | E34: =IFERROR(365/E27,0) -> 68.018916 | F34: =IFERROR(365/F27,0) -> 65.459389 | G34: =IFERROR(365/G27,0) -> 74.321849 | H34: =IFERROR(365/H27,0) -> 70.092265 | I34: =IFERROR(365/I27,0) -> 68.108368 | J34: =IFERROR(365/J27,0) -> 63.227837 | ... L34: =IFERROR(365/L27,0) -> 69.775262 | N34: =IFERROR(AVERAGE(C34:L34),0) -> 68.262133 | O34: =IFERROR(MEDIAN(C34:L34),0) -> 68.063642
B35: Payable Days | C35: =IFERROR(365/C28,0) -> 78.06105 | D35: =IFERROR(365/D28,0) -> 75.500701 | E35: =IFERROR(365/E28,0) -> 74.664502 | F35: =IFERROR(365/F28,0) -> 84.403629 | G35: =IFERROR(365/G28,0) -> 87.307167 | H35: =IFERROR(365/H28,0) -> 93.854756 | I35: =IFERROR(365/I28,0) -> 107.73773 | J35: =IFERROR(365/J28,0) -> 101.69078 | ... L35: =IFERROR(365/L28,0) -> 97.973802 | N35: =IFERROR(AVERAGE(C35:L35),0) -> 89.830496 | O35: =IFERROR(MEDIAN(C35:L35),0) -> 90.580961
B36: Inventory Days | C36: =IFERROR(365/C29,0) -> 0 | D36: =IFERROR(365/D29,0) -> 0 | E36: =IFERROR(365/E29,0) -> 0 | F36: =IFERROR(365/F29,0) -> 0 | G36: =IFERROR(365/G29,0) -> 0 | H36: =IFERROR(365/H29,0) -> 0 | I36: =IFERROR(365/I29,0) -> 0 | J36: =IFERROR(365/J29,0) -> 0 | ... L36: =IFERROR(365/L29,0) -> 0 | N36: =IFERROR(AVERAGE(C36:L36),0) -> 0 | O36: =IFERROR(MEDIAN(C36:L36),0) -> 0
B37: Cash Conversion Cycle | C37: =IFERROR((SUM(C34,C36)-C35),0) -> -11.831329 | D37: =IFERROR((SUM(D34,D36)-D35),0) -> -9.827989 | E37: =IFERROR((SUM(E34,E36)-E35),0) -> -6.6455858 | F37: =IFERROR((SUM(F34,F36)-F35),0) -> -18.944239 | G37: =IFERROR((SUM(G34,G36)-G35),0) -> -12.985318 | H37: =IFERROR((SUM(H34,H36)-H35),0) -> -23.762491 | I37: =IFERROR((SUM(I34,I36)-I35),0) -> -39.62936 | J37: =IFERROR((SUM(J34,J36)-J35),0) -> -38.462938 | ... L37: =IFERROR((SUM(L34,L36)-L35),0) -> -28.19854 | N37: =IFERROR(AVERAGE(C37:L37),0) -> -21.568364 | O37: =IFERROR(MEDIAN(C37:L37),0) -> -21.353365
B39: CFO/Sales | C39: =IFERROR(HistoricalFS!C77/HistoricalFS!C6,0) -> 0.12943419 | D39: =IFERROR(HistoricalFS!D77/HistoricalFS!D6,0) -> 0.13689329 | E39: =IFERROR(HistoricalFS!E77/HistoricalFS!E6,0) -> 0.18862199 | F39: =IFERROR(HistoricalFS!F77/HistoricalFS!F6,0) -> 0.17403084 | G39: =IFERROR(HistoricalFS!G77/HistoricalFS!G6,0) -> 0.16120541 | H39: =IFERROR(HistoricalFS!H77/HistoricalFS!H6,0) -> 0.2387929 | I39: =IFERROR(HistoricalFS!I77/HistoricalFS!I6,0) -> 0.18464991 | J39: =IFERROR(HistoricalFS!J77/HistoricalFS!J6,0) -> 0.1098544 | ... L39: =IFERROR(HistoricalFS!L77/HistoricalFS!L6,0) -> 0.2171851 | N39: =IFERROR(AVERAGE(C39:L39),0) -> 0.167165 | O39: =IFERROR(MEDIAN(C39:L39),0) -> 0.16761812
B40: CFO/Total Assets | C40: =IFERROR(HistoricalFS!C77/HistoricalFS!C64,0) -> 0.10761938 | D40: =IFERROR(HistoricalFS!D77/HistoricalFS!D64,0) -> 0.11275076 | E40: =IFERROR(HistoricalFS!E77/HistoricalFS!E64,0) -> 0.16763916 | F40: =IFERROR(HistoricalFS!F77/HistoricalFS!F64,0) -> 0.17115124 | G40: =IFERROR(HistoricalFS!G77/HistoricalFS!G64,0) -> 0.15943355 | H40: =IFERROR(HistoricalFS!H77/HistoricalFS!H64,0) -> 0.22315856 | I40: =IFERROR(HistoricalFS!I77/HistoricalFS!I64,0) -> 0.19242005 | J40: =IFERROR(HistoricalFS!J77/HistoricalFS!J64,0) -> 0.12940223 | ... L40: =IFERROR(HistoricalFS!L77/HistoricalFS!L64,0) -> 0.23951419 | N40: =IFERROR(AVERAGE(C40:L40),0) -> 0.16496238 | O40: =IFERROR(MEDIAN(C40:L40),0) -> 0.16353636
B41: CFO/Total Debt | C41: =IFERROR(HistoricalFS!C77/HistoricalFS!C49,0) -> 0 | D41: =IFERROR(HistoricalFS!D77/HistoricalFS!D49,0) -> 0 | E41: =IFERROR(HistoricalFS!E77/HistoricalFS!E49,0) -> 0 | F41: =IFERROR(HistoricalFS!F77/HistoricalFS!F49,0) -> 0 | G41: =IFERROR(HistoricalFS!G77/HistoricalFS!G49,0) -> 3.1590762 | H41: =IFERROR(HistoricalFS!H77/HistoricalFS!H49,0) -> 4.5055399 | I41: =IFERROR(HistoricalFS!I77/HistoricalFS!I49,0) -> 4.1032152 | J41: =IFERROR(HistoricalFS!J77/HistoricalFS!J49,0) -> 1.9427642 | ... L41: =IFERROR(HistoricalFS!L77/HistoricalFS!L49,0) -> 4.3027835 | N41: =IFERROR(AVERAGE(C41:L41),0) -> 2.0421323 | O41: =IFERROR(MEDIAN(C41:L41),0) -> 2.1753539

Sheet Forecasting
B2: ='Data Sheet'!B1&" - "&'Data Sheet'!A17&" Forecasting " -> INFOSYS LTD - Sales Forecasting | H2: ='Data Sheet'!B1&" - "&HistoricalFS!B18&" Forecasting " -> INFOSYS LTD - EBITDA Forecasting | N2: ='Data Sheet'!B1&" - "&HistoricalFS!B38&" Forecasting " -> INFOSYS LTD - EPS Forecasting
B3: Year Weight | C3: Year | D3: Sales | E3: Sales Growth | H3: Year Weight | I3: Year | J3: Sales | K3: Sales Growth | N3: Year Weight | O3: Year | P3: Sales | Q3: Sales Growth
B4: 1 | C4: ='Data Sheet'!B16 -> 42460 | D4: {=TRANSPOSE('Data Sheet'!B17:K17)} -> 62441 | H4: 1 | I4: =C4 -> 42460 | J4: {=TRANSPOSE(HistoricalFS!C18:L18)} -> 17079 | N4: 1 | O4: =I4 -> 42460 | P4: {=TRANSPOSE(HistoricalFS!C38:L38)} -> 22.571236
B5: =B4+1 -> 2 | C5: =C4+365 -> 42825 | D5: 68484 | E5: =D5/D4-1 -> 0.09677936 | H5: =H4+1 -> 2 | I5: =I4+365 -> 42825 | J5: 18604 | K5: =J5/J4-1 -> 0.089290942 | N5: =N4+1 -> 2 | O5: =O4+365 -> 42825 | P5: 24.604367 | Q5: =P5/P4-1 -> 0.090076189
B6: =B5+1 -> 3 | C6: =C5+365 -> 43190 | D6: 70522 | E6: =D6/D5-1 -> 0.029758776 | H6: =H5+1 -> 3 | I6: =I5+365 -> 43190 | J6: 18822 | K6: =J6/J5-1 -> 0.01171791 | N6: =N5+1 -> 3 | O6: =O5+365 -> 43190 | P6: 29.114967 | Q6: =P6/P5-1 -> 0.18332521
B7: =B6+1 -> 4 | C7: =C6+365 -> 43555 | D7: 82675 | E7: =D7/D6-1 -> 0.1723292 | H7: =H6+1 -> 4 | I7: =I6+365 -> 43555 | J7: 20170 | K7: =J7/J6-1 -> 0.071618319 | N7: =N6+1 -> 4 | O7: =O6+365 -> 43555 | P7: 28.67541 | Q7: =P7/P6-1 -> -0.015097286
B8: =B7+1 -> 5 | C8: =C7+365 -> 43920 | D8: 90791 | E8: =D8/D7-1 -> 0.098167523 | H8: =H7+1 -> 5 | I8: =I7+365 -> 43920 | J8: 22267 | K8: =J8/J7-1 -> 0.10396629 | N8: =N7+1 -> 5 | O8: =O7+365 -> 43920 | P8: 32.486499 | Q8: =P8/P7-1 -> 0.13290442
B9: =B8+1 -> 6 | C9: =C8+365 -> 44285 | D9: 100472 | E9: =D9/D8-1 -> 0.10662951 | H9: =H8+1 -> 6 | I9: =I8+365 -> 44285 | J9: 27889 | K9: =J9/J8-1 -> 0.25248125 | N9: =N8+1 -> 6 | O9: =O8+365 -> 44285 | P9: 40.420588 | Q9: =P9/P8-1 -> 0.24422727
B10: =B9+1 -> 7 | C10: =C9+365 -> 44650 | D10: 121641 | E10: =D10/D9-1 -> 0.21069552 | H10: =H9+1 -> 7 | I10: =I9+365 -> 44650 | J10: 31491 | K10: =J10/J9-1 -> 0.12915486 | N10: =N9+1 -> 7 | O10: =O9+365 -> 44650 | P10: 47.189008 | Q10: =P10/P9-1 -> 0.16744981
B11: =B10+1 -> 8 | C11: =C10+365 -> 45015 | D11: 146767 | E11: =D11/D10-1 -> 0.20655864 | H11: =H10+1 -> 8 | I11: =I10+365 -> 45015 | J11: 35130 | K11: =J11/J10-1 -> 0.11555683 | N11: =N10+1 -> 8 | O11: =O10+365 -> 45015 | P11: 51.60054 | Q11: =P11/P10-1 -> 0.093486431
B12: =B11+1 -> 9 | C12: =C11+365 -> 45380 | D12: 153670 | E12: =D12/D11-1 -> 0.047033734 | H12: =H11+1 -> 9 | I12: =I11+365 -> 45380 | J12: 36425 | K12: =J12/J11-1 -> 0.03686308 | N12: =N11+1 -> 9 | O12: =O11+365 -> 45380 | P12: 51.885133 | Q12: =P12/P11-1 -> 0.0055153183
B13: =B12+1 -> 10 | C13: =C12+365 -> 45745 | D13: 162990 | E13: =D13/D12-1 -> 0.060649444 | H13: =H12+1 -> 10 | I13: =I12+365 -> 45745 | J13: 39236 | K13: =J13/J12-1 -> 0.077172272 | N13: =N12+1 -> 10 | O13: =O12+365 -> 45745 | P13: 55.73881 | Q13: =P13/P12-1 -> 0.074273236
B14: =B13+1 -> 11 | C14: =C13+365 -> 46110 | D14: =FORECAST(B14,$D$4:$D$13,$B$4:$B$13) -> 173013.53 | E14: =D14/D13-1 -> 0.061497842 | H14: =H13+1 -> 11 | I14: =I13+365 -> 46110 | J14: =FORECAST(H14,$J$4:$J$13,$H$4:$H$13) -> 41554.133 | K14: =J14/J13-1 -> 0.059081796 | N14: =N13+1 -> 11 | O14: =O13+365 -> 46110 | P14: =FORECAST(N14,$P$4:$P$13,$N$4:$N$13) -> 60.607865 | Q14: =P14/P13-1 -> 0.087354846
B15: =B14+1 -> 12 | C15: =C14+365 -> 46475 | D15: =FORECAST(B15,$D$4:$D$13,$B$4:$B$13) -> 185189.58 | E15: =D15/D14-1 -> 0.070376243 | H15: =H14+1 -> 12 | I15: =I14+365 -> 46475 | J15: =FORECAST(H15,$J$4:$J$13,$H$4:$H$13) -> 44252.83 | K15: =J15/J14-1 -> 0.064944128 | N15: =N14+1 -> 12 | O15: =O14+365 -> 46475 | P15: =FORECAST(N15,$P$4:$P$13,$N$4:$N$13) -> 64.640449 | Q15: =P15/P14-1 -> 0.066535647
B16: =B15+1 -> 13 | C16: =C15+365 -> 46840 | D16: =FORECAST(B16,$D$4:$D$13,$B$4:$B$13) -> 197365.62 | E16: =D16/D15-1 -> 0.06574907 | H16: =H15+1 -> 13 | I16: =I15+365 -> 46840 | J16: =FORECAST(H16,$J$4:$J$13,$H$4:$H$13) -> 46951.527 | K16: =J16/J15-1 -> 0.060983602 | N16: =N15+1 -> 13 | O16: =O15+365 -> 46840 | P16: =FORECAST(N16,$P$4:$P$13,$N$4:$N$13) -> 68.673032 | Q16: =P16/P15-1 -> 0.062384832
B17: =B16+1 -> 14 | C17: =C16+365 -> 47205 | D17: =FORECAST(B17,$D$4:$D$13,$B$4:$B$13) -> 209541.66 | E17: =D17/D16-1 -> 0.061692824 | H17: =H16+1 -> 14 | I17: =I16+365 -> 47205 | J17: =FORECAST(H17,$J$4:$J$13,$H$4:$H$13) -> 49650.224 | K17: =J17/J16-1 -> 0.057478364 | N17: =N16+1 -> 14 | O17: =O16+365 -> 47205 | P17: =FORECAST(N17,$P$4:$P$13,$N$4:$N$13) -> 72.705616 | Q17: =P17/P16-1 -> 0.058721501
B18: =B17+1 -> 15 | C18: =C17+365 -> 47570 | D18: =FORECAST(B18,$D$4:$D$13,$B$4:$B$13) -> 221717.7 | E18: =D18/D17-1 -> 0.058107979 | H18: =H17+1 -> 15 | I18: =I17+365 -> 47570 | J18: =FORECAST(H18,$J$4:$J$13,$H$4:$H$13) -> 52348.921 | K18: =J18/J17-1 -> 0.054354175 | N18: =N17+1 -> 15 | O18: =O17+365 -> 47570 | P18: =FORECAST(N18,$P$4:$P$13,$N$4:$N$13) -> 76.738199 | Q18: =P18/P17-1 -> 0.05546454
B22: Done by linear forecasting
B27: (Why we should not take these)
B28: Arthematic Growth | D28: =AVERAGE(E5:E13) -> 0.11428908
B29: Geometric Growth | D29: =_xlfn.RRI(B13,D4,D13) -> 0.10070037
B31: Standard Deviation | D31: =_xlfn.STDEV.S(E5:E13) -> 0.067405079

Sheet Common Size Statement
A2: # | B2: ="Common Size Income Statement"&" "&"- "&'Data Sheet'!$B$1 -> Common Size Income Statement - INFOSYS LTD
B4: Particulars | C4: ='Data Sheet'!B16 -> 42460 | D4: ='Data Sheet'!C16 -> 42825 | E4: ='Data Sheet'!D16 -> 43190 | F4: ='Data Sheet'!E16 -> 43555 | G4: ='Data Sheet'!F16 -> 43921 | H4: ='Data Sheet'!G16 -> 44286 | I4: ='Data Sheet'!H16 -> 44651 | J4: ='Data Sheet'!I16 -> 45016 | ... L4: ='Data Sheet'!K16 -> 45747
B6: ='Data Sheet'!A17 -> Sales | C6: ='Data Sheet'!B17/'Data Sheet'!B$17 -> 1 | D6: ='Data Sheet'!C17/'Data Sheet'!C$17 -> 1 | E6: ='Data Sheet'!D17/'Data Sheet'!D$17 -> 1 | F6: ='Data Sheet'!E17/'Data Sheet'!E$17 -> 1 | G6: ='Data Sheet'!F17/'Data Sheet'!F$17 -> 1 | H6: ='Data Sheet'!G17/'Data Sheet'!G$17 -> 1 | I6: ='Data Sheet'!H17/'Data Sheet'!H$17 -> 1 | J6: ='Data Sheet'!I17/'Data Sheet'!I$17 -> 1 | ... L6: ='Data Sheet'!K17/'Data Sheet'!K$17 -> 1
B7: ='Data Sheet'!A18 -> Raw Material Cost | C7: ='Data Sheet'!B18/'Data Sheet'!B$17 -> 0 | D7: ='Data Sheet'!C18/'Data Sheet'!C$17 -> 0 | E7: ='Data Sheet'!D18/'Data Sheet'!D$17 -> 0 | F7: ='Data Sheet'!E18/'Data Sheet'!E$17 -> 0 | G7: ='Data Sheet'!F18/'Data Sheet'!F$17 -> 0 | H7: ='Data Sheet'!G18/'Data Sheet'!G$17 -> 0 | I7: ='Data Sheet'!H18/'Data Sheet'!H$17 -> 0 | J7: ='Data Sheet'!I18/'Data Sheet'!I$17 -> 0 | ... L7: ='Data Sheet'!K18/'Data Sheet'!K$17 -> 0
B8: ='Data Sheet'!A19 -> Change in Inventory | C8: ='Data Sheet'!B19/'Data Sheet'!B$17 -> 0 | D8: ='Data Sheet'!C19/'Data Sheet'!C$17 -> 0 | E8: ='Data Sheet'!D19/'Data Sheet'!D$17 -> 0 | F8: ='Data Sheet'!E19/'Data Sheet'!E$17 -> 0 | G8: ='Data Sheet'!F19/'Data Sheet'!F$17 -> 0 | H8: ='Data Sheet'!G19/'Data Sheet'!G$17 -> 0 | I8: ='Data Sheet'!H19/'Data Sheet'!H$17 -> 0 | J8: ='Data Sheet'!I19/'Data Sheet'!I$17 -> 0 | ... L8: ='Data Sheet'!K19/'Data Sheet'!K$17 -> 0
B9: ='Data Sheet'!A20 -> Power and Fuel | C9: ='Data Sheet'!B20/'Data Sheet'!B$17 -> 0.0034752807 | D9: ='Data Sheet'!C20/'Data Sheet'!C$17 -> 0.0033292448 | E9: ='Data Sheet'!D20/'Data Sheet'!D$17 -> 0.0029352542 | F9: ='Data Sheet'!E20/'Data Sheet'!E$17 -> 0.0026731176 | G9: ='Data Sheet'!F20/'Data Sheet'!F$17 -> 0.0025222764 | H9: ='Data Sheet'!G20/'Data Sheet'!G$17 -> 0.0014232821 | I9: ='Data Sheet'!H20/'Data Sheet'!H$17 -> 0.0010851604 | J9: ='Data Sheet'!I20/'Data Sheet'!I$17 -> 0.0011991797 | ... L9: ='Data Sheet'!K20/'Data Sheet'!K$17 -> 0.0013620468
B10: ='Data Sheet'!A21 -> Other Mfr. Exp | C10: ='Data Sheet'!B21/'Data Sheet'!B$17 -> 0.093848593 | D10: ='Data Sheet'!C21/'Data Sheet'!C$17 -> 0.098008294 | E10: ='Data Sheet'!D21/'Data Sheet'!D$17 -> 0.10331528 | F10: ='Data Sheet'!E21/'Data Sheet'!E$17 -> 0.11977018 | G10: ='Data Sheet'!F21/'Data Sheet'!F$17 -> 0.12210461 | H10: ='Data Sheet'!G21/'Data Sheet'!G$17 -> 0.12739868 | I10: ='Data Sheet'!H21/'Data Sheet'!H$17 -> 0.17009068 | J10: ='Data Sheet'!I21/'Data Sheet'!I$17 -> 0.1794 | ... L10: ='Data Sheet'!K21/'Data Sheet'!K$17 -> 0.18648383
B11: ='Data Sheet'!A22 -> Employee Cost | C11: ='Data Sheet'!B22/'Data Sheet'!B$17 -> 0.5511603 | D11: ='Data Sheet'!C22/'Data Sheet'!C$17 -> 0.55004089 | E11: ='Data Sheet'!D22/'Data Sheet'!D$17 -> 0.55162928 | F11: ='Data Sheet'!E22/'Data Sheet'!E$17 -> 0.54820683 | G11: ='Data Sheet'!F22/'Data Sheet'!F$17 -> 0.56057318 | H11: ='Data Sheet'!G22/'Data Sheet'!G$17 -> 0.5528605 | I11: ='Data Sheet'!H22/'Data Sheet'!H$17 -> 0.52611373 | J11: ='Data Sheet'!I22/'Data Sheet'!I$17 -> 0.53400288 | ... L11: ='Data Sheet'!K22/'Data Sheet'!K$17 -> 0.5274434
B12: ='Data Sheet'!A23 -> Selling and admin | C12: ='Data Sheet'!B23/'Data Sheet'!B$17 -> 0.07112314 | D12: ='Data Sheet'!C23/'Data Sheet'!C$17 -> 0.066935343 | E12: ='Data Sheet'!D23/'Data Sheet'!D$17 -> 0.065015173 | F12: ='Data Sheet'!E23/'Data Sheet'!E$17 -> 0.067166616 | G12: ='Data Sheet'!F23/'Data Sheet'!F$17 -> 0.059201903 | H12: ='Data Sheet'!G23/'Data Sheet'!G$17 -> 0.031789951 | I12: ='Data Sheet'!H23/'Data Sheet'!H$17 -> 0.035391028 | J12: ='Data Sheet'!I23/'Data Sheet'!I$17 -> 0.03611166 | ... L12: ='Data Sheet'!K23/'Data Sheet'!K$17 -> 0.037051353
B13: ='Data Sheet'!A24 -> Other Expenses | C13: ='Data Sheet'!B24/'Data Sheet'!B$17 -> 0.0068704857 | D13: ='Data Sheet'!C24/'Data Sheet'!C$17 -> 0.01003154 | E13: ='Data Sheet'!D24/'Data Sheet'!D$17 -> 0.01020958 | F13: ='Data Sheet'!E24/'Data Sheet'!E$17 -> 0.018215906 | G13: ='Data Sheet'!F24/'Data Sheet'!F$17 -> 0.010342435 | H13: ='Data Sheet'!G24/'Data Sheet'!G$17 -> 0.0089477665 | I13: ='Data Sheet'!H24/'Data Sheet'!H$17 -> 0.0084346561 | J13: ='Data Sheet'!I24/'Data Sheet'!I$17 -> 0.0099272997 | ... L13: ='Data Sheet'!K24/'Data Sheet'!K$17 -> 0.0069329407
B14: ='Data Sheet'!A25 -> Other Income | C14: ='Data Sheet'!B25/'Data Sheet'!B$17 -> 0.049967169 | D14: ='Data Sheet'!C25/'Data Sheet'!C$17 -> 0.04453595 | E14: ='Data Sheet'!D25/'Data Sheet'!D$17 -> 0.046949888 | F14: ='Data Sheet'!E25/'Data Sheet'!E$17 -> 0.034859389 | G14: ='Data Sheet'!F25/'Data Sheet'!F$17 -> 0.030873104 | H14: ='Data Sheet'!G25/'Data Sheet'!G$17 -> 0.021906601 | I14: ='Data Sheet'!H25/'Data Sheet'!H$17 -> 0.018866994 | J14: ='Data Sheet'!I25/'Data Sheet'!I$17 -> 0.01840332 | ... L14: ='Data Sheet'!K25/'Data Sheet'!K$17 -> 0.022087245
B15: ='Data Sheet'!A26 -> Depreciation | C15: ='Data Sheet'!B26/'Data Sheet'!B$17 -> 0.023366058 | D15: ='Data Sheet'!C26/'Data Sheet'!C$17 -> 0.024867122 | E15: ='Data Sheet'!D26/'Data Sheet'!D$17 -> 0.026417288 | F15: ='Data Sheet'!E26/'Data Sheet'!E$17 -> 0.024324161 | G15: ='Data Sheet'!F26/'Data Sheet'!F$17 -> 0.031864392 | H15: ='Data Sheet'!G26/'Data Sheet'!G$17 -> 0.032516522 | I15: ='Data Sheet'!H26/'Data Sheet'!H$17 -> 0.028575891 | J15: ='Data Sheet'!I26/'Data Sheet'!I$17 -> 0.028787125 | ... L15: ='Data Sheet'!K26/'Data Sheet'!K$17 -> 0.029523284
B16: ='Data Sheet'!A27 -> Interest | C16: ='Data Sheet'!B27/'Data Sheet'!B$17 -> 0 | D16: ='Data Sheet'!C27/'Data Sheet'!C$17 -> 0 | E16: ='Data Sheet'!D27/'Data Sheet'!D$17 -> 0 | F16: ='Data Sheet'!E27/'Data Sheet'!E$17 -> 0 | G16: ='Data Sheet'!F27/'Data Sheet'!F$17 -> 0.0018724323 | H16: ='Data Sheet'!G27/'Data Sheet'!G$17 -> 0.0019408392 | I16: ='Data Sheet'!H27/'Data Sheet'!H$17 -> 0.0016441825 | J16: ='Data Sheet'!I27/'Data Sheet'!I$17 -> 0.0019350399 | ... L16: ='Data Sheet'!K27/'Data Sheet'!K$17 -> 0.0025523038
B17: ='Data Sheet'!A28 -> Profit before tax | C17: ='Data Sheet'!B28/'Data Sheet'!B$17 -> 0.30012332 | D17: ='Data Sheet'!C28/'Data Sheet'!C$17 -> 0.29132352 | E17: ='Data Sheet'!D28/'Data Sheet'!D$17 -> 0.28742804 | F17: ='Data Sheet'!E28/'Data Sheet'!E$17 -> 0.25450257 | G17: ='Data Sheet'!F28/'Data Sheet'!F$17 -> 0.24239187 | H17: ='Data Sheet'!G28/'Data Sheet'!G$17 -> 0.26502906 | I17: ='Data Sheet'!H28/'Data Sheet'!H$17 -> 0.24753167 | J17: ='Data Sheet'!I28/'Data Sheet'!I$17 -> 0.22704014 | ... L17: ='Data Sheet'!K28/'Data Sheet'!K$17 -> 0.23073808
... B20: ='Data Sheet'!A31 -> Dividend Amount | C20: ='Data Sheet'!B31/'Data Sheet'!B$17 -> 0.088858282 | D20: ='Data Sheet'!C31/'Data Sheet'!C$17 -> 0.086028853 | E20: ='Data Sheet'!D31/'Data Sheet'!D$17 -> 0.13422194 | F20: ='Data Sheet'!E31/'Data Sheet'!E$17 -> 0.11155125 | G20: ='Data Sheet'!F31/'Data Sheet'!F$17 -> 0.081803262 | H20: ='Data Sheet'!G31/'Data Sheet'!G$17 -> 0.11415718 | I20: ='Data Sheet'!H31/'Data Sheet'!H$17 -> 0.10693434 | J20: ='Data Sheet'!I31/'Data Sheet'!I$17 -> 0.095860786 | ... L20: ='Data Sheet'!K31/'Data Sheet'!K$17 -> 0.10937972
B21: ='Data Sheet'!A33 -> EBITDA | C21: ='Data Sheet'!B33/'Data Sheet'!B$17 -> 0.32348937 | D21: ='Data Sheet'!C33/'Data Sheet'!C$17 -> 0.31619064 | E21: ='Data Sheet'!D33/'Data Sheet'!D$17 -> 0.31384532 | F21: ='Data Sheet'!E33/'Data Sheet'!E$17 -> 0.27875416 | G21: ='Data Sheet'!F33/'Data Sheet'!F$17 -> 0.27563305 | H21: ='Data Sheet'!G33/'Data Sheet'!G$17 -> 0.29876981 | I21: ='Data Sheet'!H33/'Data Sheet'!H$17 -> 0.27745579 | J21: ='Data Sheet'!I33/'Data Sheet'!I$17 -> 0.25767373 | ... L21: ='Data Sheet'!K33/'Data Sheet'!K$17 -> 0.26258666
A23: # | B23: ="Common Size Balance Sheet"&" "&"- "&'Data Sheet'!$B$1 -> Common Size Balance Sheet - INFOSYS LTD
B25: Particulars | C25: ='Data Sheet'!B56 -> 42460 | D25: ='Data Sheet'!C56 -> 42825 | E25: ='Data Sheet'!D56 -> 43190 | F25: ='Data Sheet'!E56 -> 43555 | G25: ='Data Sheet'!F56 -> 43921 | H25: ='Data Sheet'!G56 -> 44286 | I25: ='Data Sheet'!H56 -> 44651 | J25: ='Data Sheet'!I56 -> 45016 | ... L25: ='Data Sheet'!K56 -> 45747
B27: Total Liabilities | C27: ='Data Sheet'!B61/'Data Sheet'!B$61 -> 1 | D27: ='Data Sheet'!C61/'Data Sheet'!C$61 -> 1 | E27: ='Data Sheet'!D61/'Data Sheet'!D$61 -> 1 | F27: ='Data Sheet'!E61/'Data Sheet'!E$61 -> 1 | G27: ='Data Sheet'!F61/'Data Sheet'!F$61 -> 1 | H27: ='Data Sheet'!G61/'Data Sheet'!G$61 -> 1 | I27: ='Data Sheet'!H61/'Data Sheet'!H$61 -> 1 | J27: ='Data Sheet'!I61/'Data Sheet'!I$61 -> 1 | ... L27: ='Data Sheet'!K61/'Data Sheet'!K$61 -> 1
B28: ='Data Sheet'!A57 -> Equity Share Capital | C28: ='Data Sheet'!B57/'Data Sheet'!B$61 -> 0.015233428 | D28: ='Data Sheet'!C57/'Data Sheet'!C$61 -> 0.013758599 | E28: ='Data Sheet'!D57/'Data Sheet'!D$61 -> 0.013711578 | F28: ='Data Sheet'!E57/'Data Sheet'!E$61 -> 0.025813052 | G28: ='Data Sheet'!F57/'Data Sheet'!F$61 -> 0.023115468 | H28: ='Data Sheet'!G57/'Data Sheet'!G$61 -> 0.019756118 | I28: ='Data Sheet'!H57/'Data Sheet'!H$61 -> 0.017973254 | J28: ='Data Sheet'!I57/'Data Sheet'!I$61 -> 0.01660567 | ... L28: ='Data Sheet'!K57/'Data Sheet'!K$61 -> 0.014026185
B29: ='Data Sheet'!A58 -> Reserves | C29: ='Data Sheet'!B58/'Data Sheet'!B$61 -> 0.80694559 | D29: ='Data Sheet'!C58/'Data Sheet'!C$61 -> 0.8158705 | E29: ='Data Sheet'!D58/'Data Sheet'!D$61 -> 0.80448399 | F29: ='Data Sheet'!E58/'Data Sheet'!E$61 -> 0.74677039 | G29: ='Data Sheet'!F58/'Data Sheet'!F$61 -> 0.68984749 | H29: ='Data Sheet'!G58/'Data Sheet'!G$61 -> 0.69041307 | I29: ='Data Sheet'!H58/'Data Sheet'!H$61 -> 0.627539 | J29: ='Data Sheet'!I58/'Data Sheet'!I$61 -> 0.58860638 | ... L29: ='Data Sheet'!K58/'Data Sheet'!K$61 -> 0.63429074
B30: ='Data Sheet'!A59 -> Borrowings | C30: ='Data Sheet'!B59/'Data Sheet'!B$61 -> 0 | D30: ='Data Sheet'!C59/'Data Sheet'!C$61 -> 0 | E30: ='Data Sheet'!D59/'Data Sheet'!D$61 -> 0 | F30: ='Data Sheet'!E59/'Data Sheet'!E$61 -> 0 | G30: ='Data Sheet'!F59/'Data Sheet'!F$61 -> 0.05046841 | H30: ='Data Sheet'!G59/'Data Sheet'!G$61 -> 0.049529816 | I30: ='Data Sheet'!H59/'Data Sheet'!H$61 -> 0.046894945 | J30: ='Data Sheet'!I59/'Data Sheet'!I$61 -> 0.066607275 | ... L30: ='Data Sheet'!K59/'Data Sheet'!K$61 -> 0.055664941
B31: ='Data Sheet'!A60 -> Other Liabilities | C31: ='Data Sheet'!B60/'Data Sheet'!B$61 -> 0.17782098 | D31: ='Data Sheet'!C60/'Data Sheet'!C$61 -> 0.1703709 | E31: ='Data Sheet'!D60/'Data Sheet'!D$61 -> 0.18180443 | F31: ='Data Sheet'!E60/'Data Sheet'!E$61 -> 0.22741655 | G31: ='Data Sheet'!F60/'Data Sheet'!F$61 -> 0.23656863 | H31: ='Data Sheet'!G60/'Data Sheet'!G$61 -> 0.24030099 | I31: ='Data Sheet'!H60/'Data Sheet'!H$61 -> 0.3075928 | J31: ='Data Sheet'!I60/'Data Sheet'!I$61 -> 0.32818068 | ... L31: ='Data Sheet'!K60/'Data Sheet'!K$61 -> 0.29601813
B33: Total Assets | C33: ='Data Sheet'!B76/'Data Sheet'!B$76 -> 1 | D33: ='Data Sheet'!C76/'Data Sheet'!C$76 -> 1 | E33: ='Data Sheet'!D76/'Data Sheet'!D$76 -> 1 | F33: ='Data Sheet'!E76/'Data Sheet'!E$76 -> 1 | G33: ='Data Sheet'!F76/'Data Sheet'!F$76 -> 1 | H33: ='Data Sheet'!G76/'Data Sheet'!G$76 -> 1 | I33: ='Data Sheet'!H76/'Data Sheet'!H$76 -> 1 | J33: ='Data Sheet'!I76/'Data Sheet'!I$76 -> 1 | ... L33: ='Data Sheet'!K76/'Data Sheet'!K$76 -> 1
B34: ='Data Sheet'!A62 -> Net Block | C34: ='Data Sheet'!B62/'Data Sheet'!B$76 -> 0.17824709 | D34: ='Data Sheet'!C62/'Data Sheet'!C$76 -> 0.17052725 | E34: ='Data Sheet'!D62/'Data Sheet'!D$76 -> 0.1584645 | F34: ='Data Sheet'!E62/'Data Sheet'!E$76 -> 0.18687698 | G34: ='Data Sheet'!F62/'Data Sheet'!F$76 -> 0.25913943 | H34: ='Data Sheet'!G62/'Data Sheet'!G$76 -> 0.23723154 | I34: ='Data Sheet'!H62/'Data Sheet'!H$76 -> 0.22102477 | J34: ='Data Sheet'!I62/'Data Sheet'!I$76 -> 0.23455809 | ... L34: ='Data Sheet'!K62/'Data Sheet'!K$76 -> 0.20948611
B35: ='Data Sheet'!A63 -> Capital Work in Progress | C35: ='Data Sheet'!B63/'Data Sheet'!B$76 -> 0.012783296 | D35: ='Data Sheet'!C63/'Data Sheet'!C$76 -> 0.01641651 | E35: ='Data Sheet'!D63/'Data Sheet'!D$76 -> 0.020239701 | F35: ='Data Sheet'!E63/'Data Sheet'!E$76 -> 0.016510837 | G35: ='Data Sheet'!F63/'Data Sheet'!F$76 -> 0.010392157 | H35: ='Data Sheet'!G63/'Data Sheet'!G$76 -> 0.0085758667 | I35: ='Data Sheet'!H63/'Data Sheet'!H$76 -> 0.0035638102 | J35: ='Data Sheet'!I63/'Data Sheet'!I$76 -> 0.0023114707 | ... L35: ='Data Sheet'!K63/'Data Sheet'!K$76 -> 0.0055076288
B36: ='Data Sheet'!A64 -> Investments | C36: ='Data Sheet'!B64/'Data Sheet'!B$76 -> 0.025193747 | D36: ='Data Sheet'!C64/'Data Sheet'!C$76 -> 0.19751527 | E36: ='Data Sheet'!D64/'Data Sheet'!D$76 -> 0.15328486 | F36: ='Data Sheet'!E64/'Data Sheet'!E$76 -> 0.13395427 | G36: ='Data Sheet'!F64/'Data Sheet'!F$76 -> 0.09577342 | H36: ='Data Sheet'!G64/'Data Sheet'!G$76 -> 0.13212602 | I36: ='Data Sheet'!H64/'Data Sheet'!H$76 -> 0.17411269 | J36: ='Data Sheet'!I64/'Data Sheet'!I$76 -> 0.15632926 | ... L36: ='Data Sheet'!K64/'Data Sheet'!K$76 -> 0.15928144
B37: ='Data Sheet'!A65 -> Other Assets | C37: ='Data Sheet'!B74/'Data Sheet'!B$76 -> 0.19751525 | D37: ='Data Sheet'!C74/'Data Sheet'!C$76 -> 0.19524222 | E37: ='Data Sheet'!D74/'Data Sheet'!D$76 -> 0.25263078 | F37: ='Data Sheet'!E74/'Data Sheet'!E$76 -> 0.2535151 | G37: ='Data Sheet'!F74/'Data Sheet'!F$76 -> 0.2301634 | H37: ='Data Sheet'!G74/'Data Sheet'!G$76 -> 0.21273172 | I37: ='Data Sheet'!H74/'Data Sheet'!H$76 -> 0.25716831 | J37: ='Data Sheet'!I74/'Data Sheet'!I$76 -> 0.30504992 | ... L37: ='Data Sheet'!K74/'Data Sheet'!K$76 -> 0.2494401
B38: ='Data Sheet'!A67 -> Receivables | C38: ='Data Sheet'!B67/'Data Sheet'!B$76 -> 0.15086953 | D38: ='Data Sheet'!C67/'Data Sheet'!C$76 -> 0.14819358 | E38: ='Data Sheet'!D67/'Data Sheet'!D$76 -> 0.16562276 | F38: ='Data Sheet'!E67/'Data Sheet'!E$76 -> 0.17637333 | G38: ='Data Sheet'!F67/'Data Sheet'!F$76 -> 0.20138344 | H38: ='Data Sheet'!G67/'Data Sheet'!G$76 -> 0.17946071 | I38: ='Data Sheet'!H67/'Data Sheet'!H$76 -> 0.19445039 | J38: ='Data Sheet'!I67/'Data Sheet'!I$76 -> 0.20405149 | ... L38: ='Data Sheet'!K67/'Data Sheet'!K$76 -> 0.21081904
B39: ='Data Sheet'!A68 -> Inventory | C39: ='Data Sheet'!B68/'Data Sheet'!B$76 -> 0 | D39: ='Data Sheet'!C68/'Data Sheet'!C$76 -> 0 | E39: ='Data Sheet'!D68/'Data Sheet'!D$76 -> 0 | F39: ='Data Sheet'!E68/'Data Sheet'!E$76 -> 0 | G39: ='Data Sheet'!F68/'Data Sheet'!F$76 -> 0 | H39: ='Data Sheet'!G68/'Data Sheet'!G$76 -> 0 | I39: ='Data Sheet'!H68/'Data Sheet'!H$76 -> 0 | J39: ='Data Sheet'!I68/'Data Sheet'!I$76 -> 0 | ... L39: ='Data Sheet'!K68/'Data Sheet'!K$76 -> 0
B40: ='Data Sheet'!A69 -> Cash & Bank | C40: ='Data Sheet'!B69/'Data Sheet'!B$76 -> 0.43539109 | D40: ='Data Sheet'!C69/'Data Sheet'!C$76 -> 0.27210516 | E40: ='Data Sheet'!D69/'Data Sheet'!D$76 -> 0.2497574 | F40: ='Data Sheet'!E69/'Data Sheet'!E$76 -> 0.23276949 | G40: ='Data Sheet'!F69/'Data Sheet'!F$76 -> 0.20314815 | H40: ='Data Sheet'!G69/'Data Sheet'!G$76 -> 0.22987415 | I40: ='Data Sheet'!H69/'Data Sheet'!H$76 -> 0.14968003 | J40: ='Data Sheet'!I69/'Data Sheet'!I$76 -> 0.097699766 | ... L40: ='Data Sheet'!K69/'Data Sheet'!K$76 -> 0.16546568

Sheet DCF>

Sheet WACC
B2: Weighted Average Cost of Capital
B4: All figures are in INR unless stated otherwise.
B6: Peer Companies
H7: Debt / | I7: Debt / | J7: Levered | K7: Unlevered
B8: Name of Companies | D8: Countary | E8: Total Debts | F8: Total Equity | G8: Tax Rate 1 | H8: Equity | I8: Capital | J8: Beta 2 | K8: Beta 3
B10: TCS | D10: India | E10: ='Beta Comps'!F3 -> 10932 | F10: ='Beta Comps'!E3 -> 1066286.6 | G10: 0.3 | H10: =E10/F10 -> 0.010252403 | I10: =E10/(F10+E10) -> 0.010148358 | J10: ='Bata - Regression'!AA18 -> -0.7250798 | K10: =J10/(1+(1-G10)*H10) -> -0.71991321
B11: Infosys | D11: India | E11: ='Beta Comps'!F4 -> 8796 | F11: ='Beta Comps'!E4 -> 607005.1 | G11: 0.3 | H11: =E11/F11 -> 0.014490817 | I11: =E11/(F11+E11) -> 0.014283833 | J11: ='Bata - Regression'!J18 -> -0.55864319 | K11: =J11/(1+(1-G11)*H11) -> -0.55303345
B12: HCL Technologies | D12: India | E12: ='Beta Comps'!F5 -> 6780 | F12: ='Beta Comps'!E5 -> 434403.52 | G12: 0.3 | H12: =E12/F12 -> 0.015607608 | I12: =E12/(F12+E12) -> 0.015367754 | J12: ='Bata - Regression'!AR18 -> -0.69639833 | K12: =J12/(1+(1-G12)*H12) -> -0.68887218
B13: Wipro | D13: India | E13: ='Beta Comps'!F6 -> 16163.7 | F13: ='Beta Comps'!E6 -> 241313.87 | G13: 0.3 | H13: =E13/F13 -> 0.06698206 | I13: =E13/(F13+E13) -> 0.062777119 | J13: ='Bata - Regression'!BI18 -> -0.36690988 | K13: =J13/(1+(1-G13)*H13) -> -0.35047691
B14: LTIMindtree | D14: India | E14: ='Beta Comps'!F7 -> 2382.6 | F14: ='Beta Comps'!E7 -> 166799.73 | G14: 0.3 | H14: =E14/F14 -> 0.014284196 | I14: =E14/(F14+E14) -> 0.014083031 | J14: ='Bata - Regression'!BZ18 -> -0.42203534 | K14: =J14/(1+(1-G14)*H14) -> -0.41785721
F16: Average | G16: =AVERAGE(G10:G14) -> 0.3 | H16: =AVERAGE(H10:H14) -> 0.024323417 | I16: =AVERAGE(I10:I14) -> 0.023332019 | J16: =AVERAGE(J10:J14) -> -0.55381331 | K16: =AVERAGE(K10:K14) -> -0.54603059
F17: Median | G17: =MEDIAN(G10:G14) -> 0.3 | H17: =MEDIAN(H10:H14) -> 0.014490817 | I17: =MEDIAN(I10:I14) -> 0.014283833 | J17: =MEDIAN(J10:J14) -> -0.55864319 | K17: =MEDIAN(K10:K14) -> -0.55303345
B20: Cost of Debt | G20: Cost of Equity
B22: Pre-Tax Cost of Debt | E22: =416/E11 -> 0.047294225 | G22: Risk Free Rate | K22: 0.07391
B23: Tax Rate | E23: =G17 -> 0.3 | G23: Equity Risk Premium | K23: =Rm!G7-WACC!K22 -> 0.077582308
B24: Post-Tax Cost of Debt | E24: =E22*(1-E23) -> 0.033105957 | G24: Levered Beta 4 | K24: =K33 -> -0.5622816
G25: Cost of Equity | K25: =K22+(K23*K24) -> 0.030286896
B28: Capital Structure | G28: Levered Beta
D30: Current | E30: Target | G30: Comps Median Unlevered Beta | K30: =K17 -> -0.55303345
B31: Total Debt | C31: =E11 -> 8796 | D31: =C31/$C$33 -> 0.014283833 | E31: =I16 -> 0.023332019 | G31: Target Debt /Equity | K31: =E35 -> 0.023889407
B32: Market Capitalization | C32: =F11 -> 607005.1 | D32: =C32/$C$33 -> 0.98571617 | E32: =E33-E31 -> 0.97666798 | G32: Tax Rate | K32: =E23 -> 0.3
B33: Total Capital | C33: =SUM(C31:C32) -> 615801.1 | D33: =C33/$C$33 -> 1 | E33: =D33 -> 1 | G33: Levered Beta | K33: =K30*(1+(1-K32)*K31) -> -0.5622816
B35: Debt/ Equity | D35: =D31/D32 -> 0.014490817 | E35: =E31/E32 -> 0.023889407 | G35: Weighted Average Cost of Capital
B37: Notes: | G37: Cost of Equity | K37: =K25 -> 0.030286896
B38: 1. Tax Rate considered as Marginal Tax Rate for the countary | G38: Equity Weight | K38: =E32 -> 0.97666798
B39: 2. Levered Beta is based on 5 year monthly data
B40: 3. Unlevered beta = Levered Beta/1+(1- Tax Rate)*Debt/ Equity) | G40: Cost of Debt | K40: =E24 -> 0.033105957
B41: 4. Levered beta = Unlevered Beta*1+(1- Tax Rate)*Debt/ Equity) | G41: Debt Weight | K41: =E31 -> 0.023332019
G43: WACC | K43: =(K37*K38)+(K40*K41) -> 0.03035267

Sheet Intrisic Growth
A2: # | B2: Calculation of Return on Investment and Capital | G2: ='Raw FS'!J3 -> 44256 | H2: ='Raw FS'!K3 -> 44621 | I2: ='Raw FS'!L3 -> 44986 | J2: ='Raw FS'!M3 -> 45352 | K2: ='Raw FS'!N3 -> 45717
B4: Current Asstes
B5: ='Raw FS'!B34 -> Trade receivables | G5: ='Raw FS'!J34 -> 19294 | H5: ='Raw FS'!K34 -> 22698 | I5: ='Raw FS'!L34 -> 25424 | J5: ='Raw FS'!M34 -> 30193 | K5: ='Raw FS'!N34 -> 31158
B6: ='Raw FS'!B36 -> Loans n Advances | G6: ='Raw FS'!J36 -> 1460 | H6: ='Raw FS'!K36 -> 2491 | I6: ='Raw FS'!L36 -> 3242 | J6: ='Raw FS'!M36 -> 10330 | K6: ='Raw FS'!N36 -> 6717
B7: ='Raw FS'!B37 -> Other asset items | G7: ='Raw FS'!J37 -> 21411 | H7: ='Raw FS'!K37 -> 27528 | I7: ='Raw FS'!L37 -> 34766 | J7: ='Raw FS'!M37 -> 29513 | K7: ='Raw FS'!N37 -> 30149
B8: Total Current Asstes | G8: =SUM(G5:G7) -> 42165 | H8: =SUM(H5:H7) -> 52717 | I8: =SUM(I5:I7) -> 63432 | J8: =SUM(J5:J7) -> 70036 | K8: =SUM(K5:K7) -> 68024
B10: Current Liabilities
B11: ='Raw FS'!B11 -> Trade Payables | G11: ='Raw FS'!J11 -> 2645 | H11: ='Raw FS'!K11 -> 4134 | I11: ='Raw FS'!L11 -> 3865 | J11: ='Raw FS'!M11 -> 3956 | K11: ='Raw FS'!N11 -> 4164
B12: ='Raw FS'!B12 -> Advance from Customers | G12: ='Raw FS'!J12 -> 0 | H12: ='Raw FS'!K12 -> 0 | I12: ='Raw FS'!L12 -> 0 | J12: ='Raw FS'!M12 -> 0 | K12: ='Raw FS'!N12 -> 0
B13: ='Raw FS'!B13 -> Other liability items | G13: ='Raw FS'!J13 -> 22759 | H13: ='Raw FS'!K13 -> 31385 | I13: ='Raw FS'!L13 -> 36637 | J13: ='Raw FS'!M13 -> 36584 | K13: ='Raw FS'!N13 -> 39201
B14: Total Current Liabilities | G14: =SUM(G11:G13) -> 25404 | H14: =SUM(H11:H13) -> 35519 | I14: =SUM(I11:I13) -> 40502 | J14: =SUM(J11:J13) -> 40540 | K14: =SUM(K11:K13) -> 43365
A16: # | B16: Net Working Capital | G16: =G8-G14 -> 16761 | H16: =H8-H14 -> 17198 | I16: =I8-I14 -> 22930 | J16: =J8-J14 -> 29496 | K16: =K8-K14 -> 24659
B18: Non Current Assets
B19: ='Raw FS'!B17 -> Land | G19: ='Raw FS'!J17 -> 2036 | H19: ='Raw FS'!K17 -> 2065 | I19: ='Raw FS'!L17 -> 2054 | J19: ='Raw FS'!M17 -> 2037 | K19: ='Raw FS'!N17 -> 2079
B20: ='Raw FS'!B18 -> Building | G20: ='Raw FS'!J18 -> 16328 | H20: ='Raw FS'!K18 -> 16761 | I20: ='Raw FS'!L18 -> 16903 | J20: ='Raw FS'!M18 -> 16515 | K20: ='Raw FS'!N18 -> 16376
B21: ='Raw FS'!B19 -> Plant Machinery | G21: ='Raw FS'!J19 -> 3296 | H21: ='Raw FS'!K19 -> 3210 | I21: ='Raw FS'!L19 -> 3302 | J21: ='Raw FS'!M19 -> 3428 | K21: ='Raw FS'!N19 -> 3461
B22: ='Raw FS'!B20 -> Equipments | G22: ='Raw FS'!J20 -> 1371 | H22: ='Raw FS'!K20 -> 1427 | I22: ='Raw FS'!L20 -> 1482 | J22: ='Raw FS'!M20 -> 1528 | K22: ='Raw FS'!N20 -> 1628
B23: ='Raw FS'!B21 -> Computers | G23: ='Raw FS'!J21 -> 8650 | H23: ='Raw FS'!K21 -> 9936 | I23: ='Raw FS'!L21 -> 11898 | J23: ='Raw FS'!M21 -> 12353 | K23: ='Raw FS'!N21 -> 12925
B24: ='Raw FS'!B22 -> Furniture n fittings | G24: ='Raw FS'!J22 -> 2149 | H24: ='Raw FS'!K22 -> 2279 | I24: ='Raw FS'!L22 -> 2303 | J24: ='Raw FS'!M22 -> 2326 | K24: ='Raw FS'!N22 -> 2340
B25: ='Raw FS'!B23 -> Vehicles | G25: ='Raw FS'!J23 -> 74 | H25: ='Raw FS'!K23 -> 71 | I25: ='Raw FS'!L23 -> 60 | J25: ='Raw FS'!M23 -> 62 | K25: ='Raw FS'!N23 -> 72
B26: ='Raw FS'!B24 -> Intangible Assets | G26: ='Raw FS'!J24 -> 6372 | H26: ='Raw FS'!K24 -> 6495 | I26: ='Raw FS'!L24 -> 7594 | J26: ='Raw FS'!M24 -> 7653 | K26: ='Raw FS'!N24 -> 10626
B27: ='Raw FS'!B25 -> Other fixed assets | G27: ='Raw FS'!J25 -> 2730 | H27: ='Raw FS'!K25 -> 2766 | I27: ='Raw FS'!L25 -> 3281 | J27: ='Raw FS'!M25 -> 3294 | K27: ='Raw FS'!N25 -> 5184
B28: Gross Block | G28: =SUM(G19:G27) -> 43006 | H28: =SUM(H19:H27) -> 45010 | I28: =SUM(I19:I27) -> 48877 | J28: =SUM(J19:J27) -> 49196 | K28: =SUM(K19:K27) -> 54691
B29: Accmulated Depreciation | G29: =-'Raw FS'!J27 -> -17501 | H29: =-'Raw FS'!K27 -> -19210 | I29: =-'Raw FS'!L27 -> -19652 | J29: =-'Raw FS'!M27 -> -21574 | K29: =-'Raw FS'!N27 -> -23730
A30: # | B30: Net Non Current Assets | G30: =SUM(G28:G29) -> 25505 | H30: =SUM(H28:H29) -> 25800 | I30: =SUM(I28:I29) -> 29225 | J30: =SUM(J28:J29) -> 27622 | K30: =SUM(K28:K29) -> 30961
A32: # | B32: Invested Capital | G32: =G30+G16 -> 42266 | H32: =H30+H16 -> 42998 | I32: =I30+I16 -> 52155 | J32: =J30+J16 -> 57118 | K32: =K30+K16 -> 55620
A33: # | B33: EBIT | G33: =(HistoricalFS!H27+HistoricalFS!H21) -> 24622 | H33: =(HistoricalFS!I27+HistoricalFS!I21) -> 28015 | I33: =(HistoricalFS!J27+HistoricalFS!J21) -> 30905 | J33: =(HistoricalFS!K27+HistoricalFS!K21) -> 31747 | K33: =(HistoricalFS!L27+HistoricalFS!L21) -> 34424
A35: # | B35: ROIC | G35: =G33/G32 -> 0.58254862 | H35: =H33/H32 -> 0.65154193 | I35: =I33/I32 -> 0.59256064 | J35: =J33/J32 -> 0.55581428 | K35: =K33/K32 -> 0.61891406
A38: # | B38: Calculation of Reinvestment Rate | G38: =G2 -> 44256 | H38: =H2 -> 44621 | I38: =I2 -> 44986 | J38: =J2 -> 45352 | K38: =K2 -> 45717
B40: Net Capex | G40: =-SUM('Raw FS'!J53:J54) -> 2107 | H40: =-SUM('Raw FS'!K53:K54) -> 2161 | I40: =-SUM('Raw FS'!L53:L54) -> 2579 | J40: =-SUM('Raw FS'!M53:M54) -> 2201 | K40: =-SUM('Raw FS'!N53:N54) -> 2237
B41: Change in Working Capital | H41: =H16-G16 -> 437 | I41: =I16-H16 -> 5732 | J41: =J16-I16 -> 6566 | K41: =K16-J16 -> -4837
B43: EBIT | G43: =G33 -> 24622 | H43: =H33 -> 28015 | I43: =I33 -> 30905 | J43: =J33 -> 31747 | K43: =K33 -> 34424
B44: Marginal Tax Rate | G44: 0.25 | H44: =G44 -> 0.25 | I44: =H44 -> 0.25 | J44: =I44 -> 0.25 | K44: =J44 -> 0.25
B45: EBIT(1-Tax) | G45: =G43*(1-G44) -> 18466.5 | H45: =H43*(1-H44) -> 21011.25 | I45: =I43*(1-I44) -> 23178.75 | J45: =J43*(1-J44) -> 23810.25 | K45: =K43*(1-K44) -> 25818
B47: Reinvestment | H47: =SUM(H40:H41) -> 2598 | I47: =SUM(I40:I41) -> 8311 | J47: =SUM(J40:J41) -> 8767 | K47: =SUM(K40:K41) -> -2600
B49: Reinvestment Rate | H49: =H47/H45 -> 0.12364805 | I49: =I47/I45 -> 0.35856118 | J49: =J47/J45 -> 0.36820277 | K49: =K47/K45 -> -0.10070493
J51: 4 Year Average | K51: =AVERAGE(H49:K49) -> 0.18742677
J52: 4 Year Median | K52: =MEDIAN(H49:K49) -> 0.24110461
A54: # | B54: Calculation of Growth Rate | G54: =G38 -> 44256 | H54: =H38 -> 44621 | I54: =I38 -> 44986 | J54: =J38 -> 45352 | K54: =K38 -> 45717
B56: Reinvestment Rate | H56: =H49 -> 0.12364805 | I56: =I49 -> 0.35856118 | J56: =J49 -> 0.36820277 | K56: =K49 -> -0.10070493
B57: ROIC | H57: =H35 -> 0.65154193 | I57: =I35 -> 0.59256064 | J57: =J35 -> 0.55581428 | K57: =K35 -> 0.61891406
B59: Intrisic Growth | H59: =H56*H57 -> 0.080561887 | I59: =I56*I57 -> 0.21246924 | J59: =J56*J57 -> 0.20465236 | K59: =K56*K57 -> -0.0623277
J61: 4 Year Average | K61: =AVERAGE(H59:K59) -> 0.10883895
J62: 4 Year Median | K62: =MEDIAN(H59:K59) -> 0.14260712

Sheet DCF
B2: Calculation of PV of FCFF | E2: ='Intrisic Growth'!K38 -> 45717 | F2: =E2+365 -> 46082 | G2: =F2+366 -> 46448 | H2: =G2+365 -> 46813 | I2: =H2+365 -> 47178 | J2: =I2+365 -> 47543
B4: EBIT | E4: ='Data Sheet'!K33-'Data Sheet'!K26 -> 37987 | F4: =E4*(1+$D$14) -> 41709.726 | G4: =F4*(1+$D$14) -> 45797.279 | H4: =G4*(1+$D$14) -> 50285.413 | I4: =H4*(1+$D$14) -> 55213.383 | J4: =I4*(1+$D$14) -> 60624.294
B5: Tax Rate | E5: 0.25 | F5: =E5 -> 0.25 | G5: =F5 -> 0.25 | H5: =G5 -> 0.25 | I5: =H5 -> 0.25 | J5: =I5 -> 0.25
B6: EBIT(1-Tax) | E6: =E4*(1-E5) -> 28490.25 | F6: =F4*(1-F5) -> 31282.295 | G6: =G4*(1-G5) -> 34347.959 | H6: =H4*(1-H5) -> 37714.059 | I6: =I4*(1-I5) -> 41410.037 | J6: =J4*(1-J5) -> 45468.221
B7: Less: Reinvestment Rate | E7: ='Intrisic Growth'!K52 -> 0.24110461 | F7: =E7+(($J$7-$E$7)/4) -> 0.27457846 | G7: =F7+(($J$7-$E$7)/4) -> 0.30805231 | H7: =G7+(($J$7-$E$7)/4) -> 0.34152615 | I7: =H7+(($J$7-$E$7)/4) -> 0.375 | J7: 0.375
B8: Free Cash Flow to Firm (FCFF) | E8: =E6*(1-E7) -> 21621.119 | F8: =F6*(1-F7) -> 22692.85 | G8: =G6*(1-G7) -> 23766.991 | H8: =H6*(1-H7) -> 24833.722 | I8: =I6*(1-I7) -> 25881.273 | J8: =J6*(1-J7) -> 28417.638
B9: Min Year Convention | F9: 0.5 | G9: =F9+1 -> 1.5 | H9: =G9+1 -> 2.5 | I9: =H9+1 -> 3.5 | J9: =I9+1 -> 4.5
B10: Discounting Factor | F10: =1/(1+$D$16)^F9 -> 0.98516063 | G10: =1/(1+$D$16)^G9 -> 0.95613925 | H10: =1/(1+$D$16)^H9 -> 0.9279728 | I10: =1/(1+$D$16)^I9 -> 0.90063609 | J10: =1/(1+$D$16)^J9 -> 0.87410468
B12: PV of FCFF | F12: =F8*F10 -> 22356.103 | G12: =G8*G10 -> 22724.553 | H12: =H8*H10 -> 23045.018 | I12: =I8*I10 -> 23309.609 | J12: =J8*J10 -> 24839.99
B14: Expected Growth | D14: 0.098
B15: Terminal Growth | D15: 0.0538
B16: WACC | D16: =WACC!K43 -> 0.03035267
B18: Calculation of Terminal Value
B20: FCFF (n+1) | D20: =J8*(1+D14) -> 31202.567
B21: WACC | D21: =D16 -> 0.03035267
B22: Terminal Growth Rate | D22: =D15 -> 0.0538
B24: Terminal Value | D24: =D20/(D21-D22) -> -1330751.4
B27: Calculation of Equity Value per Share
B29: PV of FCFF | D29: =SUM(F12:J12) -> 116275.27
B30: PV of Terminal Value | D30: =D24*J10 -> -1163216
B31: Value of Operating Assets | D31: =SUM(D29:D30) -> -1046940.7
B33: Add: Cash | D33: ='Data Sheet'!K69 -> 24455
B34: Less: Debt | D34: ='Raw FS'!N8 -> 8227
B35: Value of Equity | D35: =D31+D33-D34 -> -1030712.7
B36: No. of Shares | D36: ='Data Sheet'!B6 -> 405.46679
B38: Equity Value per Share | D38: =D35/D36 -> -2542.0398
B40: Share Price | D40: 1313
B41: Discount/Premium | D41: =D40/D38 -> -0.51651433

Sheet DCF Data>

Sheet Bata - Regression
A2: # | B2: Regression Beta - 5 Years Monthly
B4: Infosys Monthly Return | F4: NIFTY Monthly Return | I4: Beta Drifting | S4: TCS Monthly Return | W4: NIFTY Monthly Return | Z4: Beta Drifting | AJ4: HCL Technologies Monthly Return | AN4: NIFTY Monthly Return | AQ4: Beta Drifting | BA4: Wipro Monthly Return | BE4: NIFTY Monthly Return | BH4: Beta Drifting | BR4: LTIMindtree Monthly Return | BV4: NIFTY Monthly Return | BY4: Beta Drifting
B6: Date | C6: Closing Price | D6: Return | F6: Closing Price | G6: Return | I6: Levered Raw Beta | J6: =J18 -> -0.55864319 | S6: Date | T6: Closing Price | U6: Return | W6: Closing Price | X6: Return | Z6: Levered Raw Beta | AA6: =AA18 -> -0.7250798 | AJ6: Date | AK6: Closing Price | AL6: Return | AN6: Closing Price | AO6: Return | AQ6: Levered Raw Beta | AR6: =AR18 -> -0.69639833 | BA6: Date | BB6: Closing Price | BC6: Return | BE6: Closing Price | BF6: Return | BH6: Levered Raw Beta | BI6: =BI18 -> -0.36690988 | BR6: Date | BS6: Closing Price | BT6: Return | BV6: Closing Price | BW6: Return | BY6: Levered Raw Beta | BZ6: =BZ18 -> -0.42203534
B7: 44256 | C7: 1204.32 | F7: 282.93 | I7: Raw Beta Weight | J7: 0.75 | S7: 44256 | T7: 2793.57 | W7: 282.93 | Z7: Raw Beta Weight | AA7: 0.75 | AJ7: 44256 | AK7: 803.33 | AN7: 282.93 | AQ7: Raw Beta Weight | AR7: 0.75 | BA7: 44256 | BB7: 191.32 | BE7: 282.93 | BH7: Raw Beta Weight | BI7: 0.75 | BR7: 44256 | BS7: 3820.59 | BV7: 282.93 | BY7: Raw Beta Weight | BZ7: 0.75
B8: 44287 | C8: 1192.26 | D8: =C8/C7-1 -> -0.01001395 | F8: 279.32 | G8: =F8/F7-1 -> -0.01275934 | S8: 44287 | T8: 2668.57 | U8: =T8/T7-1 -> -0.044745612 | W8: 279.32 | X8: =W8/W7-1 -> -0.01275934 | AJ8: 44287 | AK8: 747.86 | AL8: =AK8/AK7-1 -> -0.069050079 | AN8: 279.32 | AO8: =AN8/AN7-1 -> -0.01275934 | BA8: 44287 | BB8: 227.63 | BC8: =BB8/BB7-1 -> 0.18978674 | BE8: 279.32 | BF8: =BE8/BE7-1 -> -0.01275934 | BR8: 44287 | BS8: 3666 | BT8: =BS8/BS7-1 -> -0.040462337 | BV8: 279.32 | BW8: =BV8/BV7-1 -> -0.01275934
B9: 44317 | C9: 1240.19 | D9: =C9/C8-1 -> 0.040200963 | F9: 287.88 | G9: =F9/F8-1 -> 0.030645854 | I9: Market Beta | J9: 1 | S9: 44317 | T9: 2790.72 | U9: =T9/T8-1 -> 0.045773579 | W9: 287.88 | X9: =W9/W8-1 -> 0.030645854 | Z9: Market Beta | AA9: 1 | AJ9: 44317 | AK9: 786.34 | AL9: =AK9/AK8-1 -> 0.051453481 | AN9: 287.88 | AO9: =AN9/AN8-1 -> 0.030645854 | AQ9: Market Beta | AR9: 1 | BA9: 44317 | BB9: 249.01 | BC9: =BB9/BB8-1 -> 0.093924351 | BE9: 287.88 | BF9: =BE9/BE8-1 -> 0.030645854 | BH9: Market Beta | BI9: 1 | BR9: 44317 | BS9: 3715.14 | BT9: =BS9/BS8-1 -> 0.013404255 | BV9: 287.88 | BW9: =BV9/BV8-1 -> 0.030645854 | BY9: Market Beta | BZ9: 1
B10: 44348 | C10: 1406.63 | D10: =C10/C9-1 -> 0.13420524 | F10: 288.64 | G10: =F10/F9-1 -> 0.0026399889 | I10: Market Beta Weight | J10: 0.25 | S10: 44348 | T10: 2955.56 | U10: =T10/T9-1 -> 0.059067194 | W10: 288.64 | X10: =W10/W9-1 -> 0.0026399889 | Z10: Market Beta Weight | AA10: 0.25 | AJ10: 44348 | AK10: 818.2 | AL10: =AK10/AK9-1 -> 0.040516825 | AN10: 288.64 | AO10: =AN10/AN9-1 -> 0.0026399889 | AQ10: Market Beta Weight | AR10: 0.25 | BA10: 44348 | BB10: 252.06 | BC10: =BB10/BB9-1 -> 0.012248504 | BE10: 288.64 | BF10: =BE10/BE9-1 -> 0.0026399889 | BH10: Market Beta Weight | BI10: 0.25 | BR10: 44348 | BS10: 3836.61 | BT10: =BS10/BS9-1 -> 0.032695941 | BV10: 288.64 | BW10: =BV10/BV9-1 -> 0.0026399889 | BY10: Market Beta Weight | BZ10: 0.25
B11: 44378 | C11: 1433.05 | D11: =C11/C10-1 -> 0.01878248 | F11: 283.22 | G11: =F11/F10-1 -> -0.018777716 | S11: 44378 | T11: 2804.16 | U11: =T11/T10-1 -> -0.051225487 | W11: 283.22 | X11: =W11/W10-1 -> -0.018777716 | AJ11: 44378 | AK11: 857.83 | AL11: =AK11/AK10-1 -> 0.04843559 | AN11: 283.22 | AO11: =AN11/AN10-1 -> -0.018777716 | BA11: 44378 | BB11: 271.23 | BC11: =BB11/BB10-1 -> 0.076053321 | BE11: 283.22 | BF11: =BE11/BE10-1 -> -0.018777716 | BR11: 44378 | BS11: 4451.19 | BT11: =BS11/BS10-1 -> 0.16018829 | BV11: 283.22 | BW11: =BV11/BV10-1 -> -0.018777716
B12: 44409 | C12: 1518.43 | D12: =C12/C11-1 -> 0.059579219 | F12: 270.2 | G12: =F12/F11-1 -> -0.04597133 | I12: Adjusted Beta | J12: =(J6*J7)+(J9*J10) -> -0.16898239 | S12: 44409 | T12: 3352.16 | U12: =T12/T11-1 -> 0.19542394 | W12: 270.2 | X12: =W12/W11-1 -> -0.04597133 | Z12: Adjusted Beta | AA12: =(AA6*AA7)+(AA9*AA10) -> -0.29380985 | AJ12: 44409 | AK12: 989.52 | AL12: =AK12/AK11-1 -> 0.15351527 | AN12: 270.2 | AO12: =AN12/AN11-1 -> -0.04597133 | AQ12: Adjusted Beta | AR12: =(AR6*AR7)+(AR9*AR10) -> -0.27229875 | BA12: 44409 | BB12: 296.09 | BC12: =BB12/BB11-1 -> 0.091656528 | BE12: 270.2 | BF12: =BE12/BE11-1 -> -0.04597133 | BH12: Adjusted Beta | BI12: =(BI6*BI7)+(BI9*BI10) -> -0.025182407 | BR12: 44409 | BS12: 5048.03 | BT12: =BS12/BS11-1 -> 0.13408549 | BV12: 270.2 | BW12: =BV12/BV11-1 -> -0.04597133 | BY12: Adjusted Beta | BZ12: =(BZ6*BZ7)+(BZ9*BZ10) -> -0.066526502
B13: 44440 | C13: 1490.63 | D13: =C13/C12-1 -> -0.018308384 | F13: 268.67 | G13: =F13/F12-1 -> -0.0056624722 | S13: 44440 | T13: 3342.51 | U13: =T13/T12-1 -> -0.0028787409 | W13: 268.67 | X13: =W13/W12-1 -> -0.0056624722 | AJ13: 44440 | AK13: 1070.91 | AL13: =AK13/AK12-1 -> 0.082252001 | AN13: 268.67 | AO13: =AN13/AN12-1 -> -0.0056624722 | BA13: 44440 | BB13: 292.92 | BC13: =BB13/BB12-1 -> -0.010706204 | BE13: 268.67 | BF13: =BE13/BE12-1 -> -0.0056624722 | BR13: 44440 | BS13: 5478.2 | BT13: =BS13/BS12-1 -> 0.085215421 | BV13: 268.67 | BW13: =BV13/BV12-1 -> -0.0056624722
B14: 44470 | C14: 1497.15 | D14: =C14/C13-1 -> 0.0043739895 | F14: 272.04 | G14: =F14/F13-1 -> 0.012543269 | S14: 44470 | T14: 3013.82 | U14: =T14/T13-1 -> -0.09833628 | W14: 272.04 | X14: =W14/W13-1 -> 0.012543269 | AJ14: 44470 | AK14: 965.08 | AL14: =AK14/AK13-1 -> -0.098822497 | AN14: 272.04 | AO14: =AN14/AN13-1 -> 0.012543269 | BA14: 44470 | BB14: 298.77 | BC14: =BB14/BB13-1 -> 0.019971323 | BE14: 272.04 | BF14: =BE14/BE13-1 -> 0.012543269 | BR14: 44470 | BS14: 6364.29 | BT14: =BS14/BS13-1 -> 0.16174838 | BV14: 272.04 | BW14: =BV14/BV13-1 -> 0.012543269
B15: 44501 | C15: 1537.46 | D15: =C15/C14-1 -> 0.02692449 | F15: 279.35 | G15: =F15/F14-1 -> 0.026871048 | I15: Beta 1 | J15: =SLOPE(D8:D66,G8:G66) -> -0.55864319 | S15: 44501 | T15: 3130.37 | U15: =T15/T14-1 -> 0.038671852 | W15: 279.35 | X15: =W15/W14-1 -> 0.026871048 | Z15: Beta 1 | AA15: =SLOPE(U8:U66,X8:X66) -> -0.7250798 | AJ15: 44501 | AK15: 960.78 | AL15: =AK15/AK14-1 -> -0.0044555892 | AN15: 279.35 | AO15: =AN15/AN14-1 -> 0.026871048 | AQ15: Beta 1 | AR15: =SLOPE(AL8:AL66,AO8:AO66) -> -0.69639833 | BA15: 44501 | BB15: 294.38 | BC15: =BB15/BB14-1 -> -0.014693577 | BE15: 279.35 | BF15: =BE15/BE14-1 -> 0.026871048 | BH15: Beta 1 | BI15: =SLOPE(BC8:BC66,BF8:BF66) -> -0.36690988 | BR15: 44501 | BS15: 6485.62 | BT15: =BS15/BS14-1 -> 0.019064185 | BV15: 279.35 | BW15: =BV15/BV14-1 -> 0.026871048 | BY15: Beta 1 | BZ15: =SLOPE(BT8:BT66,BW8:BW66) -> -0.42203534
B16: 44531 | C16: 1694.64 | D16: =C16/C15-1 -> 0.10223355 | F16: 270.53 | G16: =F16/F15-1 -> -0.031573295 | I16: Beta 2 | J16: =_xlfn.COVARIANCE.S(D7:D66,G7:G66)/_xlfn.VAR.S(G7:G66) -> -0.55864319 | S16: 44531 | T16: 3315.93 | U16: =T16/T15-1 -> 0.059277338 | W16: 270.53 | X16: =W16/W15-1 -> -0.031573295 | Z16: Beta 2 | AA16: =_xlfn.COVARIANCE.S(U7:U66,X7:X66)/_xlfn.VAR.S(X7:X66) -> -0.7250798 | AJ16: 44531 | AK16: 1113.04 | AL16: =AK16/AK15-1 -> 0.15847541 | AN16: 270.53 | AO16: =AN16/AN15-1 -> -0.031573295 | AQ16: Beta 2 | AR16: =_xlfn.COVARIANCE.S(AL7:AL66,AO7:AO66)/_xlfn.VAR.S(AO7:AO66) -> -0.69639833 | BA16: 44531 | BB16: 330.46 | BC16: =BB16/BB15-1 -> 0.12256267 | BE16: 270.53 | BF16: =BE16/BE15-1 -> -0.031573295 | BH16: Beta 2 | BI16: =_xlfn.COVARIANCE.S(BC7:BC66,BF7:BF66)/_xlfn.VAR.S(BF7:BF66) -> -0.36690988 | BR16: 44531 | BS16: 6983.07 | BT16: =BS16/BS15-1 -> 0.076700454 | BV16: 270.53 | BW16: =BV16/BV15-1 -> -0.031573295 | BY16: Beta 2 | BZ16: =_xlfn.COVARIANCE.S(BT7:BT66,BW7:BW66)/_xlfn.VAR.S(BW7:BW66) -> -0.42203534
B17: 44562 | C17: 1558.6 | D17: =C17/C16-1 -> -0.080276637 | F17: 265.19 | G17: =F17/F16-1 -> -0.019739031 | S17: 44562 | T17: 3319.89 | U17: =T17/T16-1 -> 0.0011942351 | W17: 265.19 | X17: =W17/W16-1 -> -0.019739031 | AJ17: 44562 | AK17: 935.46 | AL17: =AK17/AK16-1 -> -0.15954503 | AN17: 265.19 | AO17: =AN17/AN16-1 -> -0.019739031 | BA17: 44562 | BB17: 264.94 | BC17: =BB17/BB16-1 -> -0.19826908 | BE17: 265.19 | BF17: =BE17/BE16-1 -> -0.019739031 | BR17: 44562 | BS17: 5971.94 | BT17: =BS17/BS16-1 -> -0.14479735 | BV17: 265.19 | BW17: =BV17/BV16-1 -> -0.019739031
B18: 44593 | C18: 1540.1 | D18: =C18/C17-1 -> -0.011869627 | F18: 255.89 | G18: =F18/F17-1 -> -0.035069196 | I18: Beta 3 | J18: =J37 -> -0.55864319 | S18: 44593 | T18: 3158.13 | U18: =T18/T17-1 -> -0.048724506 | W18: 255.89 | X18: =W18/W17-1 -> -0.035069196 | Z18: Beta 3 | AA18: =AA37 -> -0.7250798 | AJ18: 44593 | AK18: 958.9 | AL18: =AK18/AK17-1 -> 0.025057191 | AN18: 255.89 | AO18: =AN18/AN17-1 -> -0.035069196 | AQ18: Beta 3 | AR18: =AR37 -> -0.69639833 | BA18: 44593 | BB18: 257.17 | BC18: =BB18/BB17-1 -> -0.029327395 | BE18: 255.89 | BF18: =BE18/BE17-1 -> -0.035069196 | BH18: Beta 3 | BI18: =BI37 -> -0.36690988 | BR18: 44593 | BS18: 5571.41 | BT18: =BS18/BS17-1 -> -0.067068658 | BV18: 255.89 | BW18: =BV18/BV17-1 -> -0.035069196 | BY18: Beta 3 | BZ18: =BZ37 -> -0.42203534
B19: 44621 | C19: 1711.79 | D19: =C19/C18-1 -> 0.11147977 | F19: 241.9 | G19: =F19/F18-1 -> -0.054671929 | S19: 44621 | T19: 3323.18 | U19: =T19/T18-1 -> 0.05226194 | W19: 241.9 | X19: =W19/W18-1 -> -0.054671929 | AJ19: 44621 | AK19: 990.22 | AL19: =AK19/AK18-1 -> 0.032662426 | AN19: 241.9 | AO19: =AN19/AN18-1 -> -0.054671929 | BA19: 44621 | BB19: 273.87 | BC19: =BB19/BB18-1 -> 0.06493759 | BE19: 241.9 | BF19: =BE19/BE18-1 -> -0.054671929 | BR19: 44621 | BS19: 5862.46 | BT19: =BS19/BS18-1 -> 0.052239918 | BV19: 241.9 | BW19: =BV19/BV18-1 -> -0.054671929
B20: 44652 | C20: 1407.2 | D20: =C20/C19-1 -> -0.17793655 | F20: 256.28 | G20: =F20/F19-1 -> 0.059446052 | I20: SUMMARY OUTPUT | S20: 44652 | T20: 3151.46 | U20: =T20/T19-1 -> -0.051673397 | W20: 256.28 | X20: =W20/W19-1 -> 0.059446052 | Z20: SUMMARY OUTPUT | AJ20: 44652 | AK20: 933.66 | AL20: =AK20/AK19-1 -> -0.05711862 | AN20: 256.28 | AO20: =AN20/AN19-1 -> 0.059446052 | AQ20: SUMMARY OUTPUT | BA20: 44652 | BB20: 237.38 | BC20: =BB20/BB19-1 -> -0.1332384 | BE20: 256.28 | BF20: =BE20/BE19-1 -> 0.059446052 | BH20: SUMMARY OUTPUT | BR20: 44652 | BS20: 4608.76 | BT20: =BS20/BS19-1 -> -0.21385221 | BV20: 256.28 | BW20: =BV20/BV19-1 -> 0.059446052 | BY20: SUMMARY OUTPUT
B21: 44682 | C21: 1364.09 | D21: =C21/C20-1 -> -0.030635304 | F21: 257.45 | G21: =F21/F20-1 -> 0.0045653192 | S21: 44682 | T21: 3009.57 | U21: =T21/T20-1 -> -0.045023576 | W21: 257.45 | X21: =W21/W20-1 -> 0.0045653192 | AJ21: 44682 | AK21: 900.35 | AL21: =AK21/AK20-1 -> -0.035676799 | AN21: 257.45 | AO21: =AN21/AN20-1 -> 0.0045653192 | BA21: 44682 | BB21: 223.04 | BC21: =BB21/BB20-1 -> -0.06040947 | BE21: 257.45 | BF21: =BE21/BE20-1 -> 0.0045653192 | BR21: 44682 | BS21: 4051.27 | BT21: =BS21/BS20-1 -> -0.12096312 | BV21: 257.45 | BW21: =BV21/BV20-1 -> 0.0045653192
B22: 44713 | C22: 1326.25 | D22: =C22/C21-1 -> -0.027740105 | F22: 262.32 | G22: =F22/F21-1 -> 0.018916294 | I22: Regression Statistics | S22: 44713 | T22: 2922.58 | U22: =T22/T21-1 -> -0.028904461 | W22: 262.32 | X22: =W22/W21-1 -> 0.018916294 | Z22: Regression Statistics | AJ22: 44713 | AK22: 841.96 | AL22: =AK22/AK21-1 -> -0.064852557 | AN22: 262.32 | AO22: =AN22/AN21-1 -> 0.018916294 | AQ22: Regression Statistics | BA22: 44713 | BB22: 194.11 | BC22: =BB22/BB21-1 -> -0.12970768 | BE22: 262.32 | BF22: =BE22/BE21-1 -> 0.018916294 | BH22: Regression Statistics | BR22: 44713 | BS22: 3814.26 | BT22: =BS22/BS21-1 -> -0.058502642 | BV22: 262.32 | BW22: =BV22/BV21-1 -> 0.018916294 | BY22: Regression Statistics
B23: 44743 | C23: 1405.91 | D23: =C23/C22-1 -> 0.06006409 | F23: 263.58 | G23: =F23/F22-1 -> 0.0048032937 | I23: Multiple R | J23: 0.28644176 | S23: 44743 | T23: 2961.5 | U23: =T23/T22-1 -> 0.013317001 | W23: 263.58 | X23: =W23/W22-1 -> 0.0048032937 | Z23: Multiple R | AA23: 0.41410329 | AJ23: 44743 | AK23: 829.67 | AL23: =AK23/AK22-1 -> -0.014596893 | AN23: 263.58 | AO23: =AN23/AN22-1 -> 0.0048032937 | AQ23: Multiple R | AR23: 0.32848051 | BA23: 44743 | BB23: 197.68 | BC23: =BB23/BB22-1 -> 0.018391634 | BE23: 263.58 | BF23: =BE23/BE22-1 -> 0.0048032937 | BH23: Multiple R | BI23: 0.17274207 | BR23: 44743 | BS23: 4538.93 | BT23: =BS23/BS22-1 -> 0.18998967 | BV23: 263.58 | BW23: =BV23/BV22-1 -> 0.0048032937 | BY23: Multiple R | BZ23: 0.16180832
B24: 44774 | C24: 1354.42 | D24: =C24/C23-1 -> -0.036623966 | F24: 280.6 | G24: =F24/F23-1 -> 0.064572426 | I24: R Square | J24: 0.082048883 | S24: 44774 | T24: 2880.11 | U24: =T24/T23-1 -> -0.027482695 | W24: 280.6 | X24: =W24/W23-1 -> 0.064572426 | Z24: R Square | AA24: 0.17148154 | AJ24: 44774 | AK24: 821.41 | AL24: =AK24/AK23-1 -> -0.0099557655 | AN24: 280.6 | AO24: =AN24/AN23-1 -> 0.064572426 | AQ24: R Square | AR24: 0.10789944 | BA24: 44774 | BB24: 192.94 | BC24: =BB24/BB23-1 -> -0.023978146 | BE24: 280.6 | BF24: =BE24/BE23-1 -> 0.064572426 | BH24: R Square | BI24: 0.029839823 | BR24: 44774 | BS24: 4453.49 | BT24: =BS24/BS23-1 -> -0.01882382 | BV24: 280.6 | BW24: =BV24/BV23-1 -> 0.064572426 | BY24: R Square | BZ24: 0.026181933
B25: 44805 | C25: 1282.3 | D25: =C25/C24-1 -> -0.053247885 | F25: 273.81 | G25: =F25/F24-1 -> -0.024198147 | I25: Adjusted R Square | J25: 0.065944477 | S25: 44805 | T25: 2694.81 | U25: =T25/T24-1 -> -0.06433782 | W25: 273.81 | X25: =W25/W24-1 -> -0.024198147 | Z25: Adjusted R Square | AA25: 0.15694612 | AJ25: 44805 | AK25: 815.63 | AL25: =AK25/AK24-1 -> -0.0070366808 | AN25: 273.81 | AO25: =AN25/AN24-1 -> -0.024198147 | AQ25: Adjusted R Square | AR25: 0.092248558 | BA25: 44805 | BB25: 183.94 | BC25: =BB25/BB24-1 -> -0.046646626 | BE25: 273.81 | BF25: =BE25/BE24-1 -> -0.024198147 | BH25: Adjusted R Square | BI25: 0.012819469 | BR25: 44805 | BS25: 4277.1 | BT25: =BS25/BS24-1 -> -0.03960714 | BV25: 273.81 | BW25: =BV25/BV24-1 -> -0.024198147 | BY25: Adjusted R Square | BZ25: 0.0090974059
B26: 44835 | C26: 1410.22 | D26: =C26/C25-1 -> 0.099758247 | F26: 270.26 | G26: =F26/F25-1 -> -0.012965195 | I26: Standard Error | J26: 0.064228958 | S26: 44835 | T26: 2871.38 | U26: =T26/T25-1 -> 0.065522245 | W26: 270.26 | X26: =W26/W25-1 -> -0.012965195 | Z26: Standard Error | AA26: 0.054783673 | AJ26: 44835 | AK26: 919.93 | AL26: =AK26/AK25-1 -> 0.12787661 | AN26: 270.26 | AO26: =AN26/AN25-1 -> -0.012965195 | AQ26: Standard Error | AR26: 0.068830029 | BA26: 44835 | BB26: 180.35 | BC26: =BB26/BB25-1 -> -0.019517234 | BE26: 270.26 | BF26: =BE26/BE25-1 -> -0.012965195 | BH26: Standard Error | BI26: 0.071912756 | BR26: 44835 | BS26: 4547.66 | BT26: =BS26/BS25-1 -> 0.063257815 | BV26: 270.26 | BW26: =BV26/BV25-1 -> -0.012965195 | BY26: Standard Error | BZ26: 0.088472806
B27: 44866 | C27: 1499.46 | D27: =C27/C26-1 -> 0.063280907 | F27: 260.3 | G27: =F27/F26-1 -> -0.0368534 | I27: Observations | J27: 59 | S27: 44866 | T27: 3049.11 | U27: =T27/T26-1 -> 0.061897067 | W27: 260.3 | X27: =W27/W26-1 -> -0.0368534 | Z27: Observations | AA27: 59 | AJ27: 44866 | AK27: 990.31 | AL27: =AK27/AK26-1 -> 0.076505821 | AN27: 260.3 | AO27: =AN27/AN26-1 -> -0.0368534 | AQ27: Observations | AR27: 59 | BA27: 44866 | BB27: 189.84 | BC27: =BB27/BB26-1 -> 0.052619906 | BE27: 260.3 | BF27: =BE27/BE26-1 -> -0.0368534 | BH27: Observations | BI27: 59 | BR27: 44866 | BS27: 4642.36 | BT27: =BS27/BS26-1 -> 0.020823896 | BV27: 260.3 | BW27: =BV27/BV26-1 -> -0.0368534 | BY27: Observations | BZ27: 59
B28: 44896 | C28: 1383.21 | D28: =C28/C27-1 -> -0.07752791 | F28: 243.73 | G28: =F28/F27-1 -> -0.063657318 | S28: 44896 | T28: 2928.52 | U28: =T28/T27-1 -> -0.039549246 | W28: 243.73 | X28: =W28/W27-1 -> -0.063657318 | AJ28: 44896 | AK28: 918.29 | AL28: =AK28/AK27-1 -> -0.072724702 | AN28: 243.73 | AO28: =AN28/AN27-1 -> -0.063657318 | BA28: 44896 | BB28: 183.24 | BC28: =BB28/BB27-1 -> -0.034766119 | BE28: 243.73 | BF28: =BE28/BE27-1 -> -0.063657318 | BR28: 44896 | BS28: 4188.39 | BT28: =BS28/BS27-1 -> -0.097788625 | BV28: 243.73 | BW28: =BV28/BV27-1 -> -0.063657318
B29: 44927 | C29: 1406.64 | D29: =C29/C28-1 -> 0.01693886 | F29: 243.52 | G29: =F29/F28-1 -> -0.00086160916 | I29: ANOVA | S29: 44927 | T29: 3088.9 | U29: =T29/T28-1 -> 0.054764864 | W29: 243.52 | X29: =W29/W28-1 -> -0.00086160916 | Z29: ANOVA | AJ29: 44927 | AK29: 1000.51 | AL29: =AK29/AK28-1 -> 0.089535985 | AN29: 243.52 | AO29: =AN29/AN28-1 -> -0.00086160916 | AQ29: ANOVA | BA29: 44927 | BB29: 186.54 | BC29: =BB29/BB28-1 -> 0.018009168 | BE29: 243.52 | BF29: =BE29/BE28-1 -> -0.00086160916 | BH29: ANOVA | BR29: 44927 | BS29: 4210.34 | BT29: =BS29/BS28-1 -> 0.0052406772 | BV29: 243.52 | BW29: =BV29/BV28-1 -> -0.00086160916 | BY29: ANOVA
B30: 44958 | C30: 1364.27 | D30: =C30/C29-1 -> -0.030121424 | F30: 240.7 | G30: =F30/F29-1 -> -0.011580158 | J30: df | K30: SS | L30: MS | M30: F | N30: Significance F | S30: 44958 | T30: 3046.73 | U30: =T30/T29-1 -> -0.013652109 | W30: 240.7 | X30: =W30/W29-1 -> -0.011580158 | AA30: df | AB30: SS | AC30: MS | AD30: F | AE30: Significance F | AJ30: 44958 | AK30: 960.75 | AL30: =AK30/AK29-1 -> -0.039739733 | AN30: 240.7 | AO30: =AN30/AN29-1 -> -0.011580158 | AR30: df | AS30: SS | AT30: MS | AU30: F | AV30: Significance F | BA30: 44958 | BB30: 181.02 | BC30: =BB30/BB29-1 -> -0.029591509 | BE30: 240.7 | BF30: =BE30/BE29-1 -> -0.011580158 | BI30: df | BJ30: SS | BK30: MS | BL30: F | BM30: Significance F | BR30: 44958 | BS30: 4551.04 | BT30: =BS30/BS29-1 -> 0.080919831 | BV30: 240.7 | BW30: =BV30/BV29-1 -> -0.011580158 | BZ30: df | CA30: SS | CB30: MS | CC30: F | CD30: Significance F
B31: 44986 | C31: 1309.61 | D31: =C31/C30-1 -> -0.040065383 | F31: 236.83 | G31: =F31/F30-1 -> -0.016078106 | I31: Regression | J31: 1 | K31: 0.02101792 | L31: 0.02101792 | M31: 5.0948098 | N31: 0.02784685 | S31: 44986 | T31: 2948.37 | U31: =T31/T30-1 -> -0.032283793 | W31: 236.83 | X31: =W31/W30-1 -> -0.016078106 | Z31: Regression | AA31: 1 | AB31: 0.035407261 | AC31: 0.035407261 | AD31: 11.797501 | AE31: 0.0011124049 | AJ31: 44986 | AK31: 967.57 | AL31: =AK31/AK30-1 -> 0.0070986209 | AN31: 236.83 | AO31: =AN31/AN30-1 -> -0.016078106 | AQ31: Regression | AR31: 1 | AS31: 0.032661502 | AT31: 0.032661502 | AU31: 6.8941425 | AV31: 0.011084227 | BA31: 44986 | BB31: 170.83 | BC31: =BB31/BB30-1 -> -0.056292122 | BE31: 236.83 | BF31: =BE31/BE30-1 -> -0.016078106 | BH31: Regression | BI31: 1 | BJ31: 0.0090664969 | BK31: 0.0090664969 | BL31: 1.7531846 | BM31: 0.19076219 | BR31: 44986 | BS31: 4587.28 | BT31: =BS31/BS30-1 -> 0.007963015 | BV31: 236.83 | BW31: =BV31/BV30-1 -> -0.016078106 | BY31: Regression | BZ31: 1 | CA31: 0.0119955 | CB31: 0.0119955 | CC31: 1.5324939 | CD31: 0.2208134
B32: 45017 | C32: 1148.93 | D32: =C32/C31-1 -> -0.12269302 | F32: 233.18 | G32: =F32/F31-1 -> -0.015411899 | I32: Residual | J32: 57 | K32: 0.23514547 | L32: 0.0041253591 | S32: 45017 | T32: 2960.65 | U32: =T32/T31-1 -> 0.0041650132 | W32: 233.18 | X32: =W32/W31-1 -> -0.015411899 | Z32: Residual | AA32: 57 | AB32: 0.1710713 | AC32: 0.0030012509 | AJ32: 45017 | AK32: 964.93 | AL32: =AK32/AK31-1 -> -0.0027284848 | AN32: 233.18 | AO32: =AN32/AN31-1 -> -0.015411899 | AQ32: Residual | AR32: 57 | AS32: 0.27004165 | AT32: 0.0047375729 | BA32: 45017 | BB32: 180.07 | BC32: =BB32/BB31-1 -> 0.05408886 | BE32: 233.18 | BF32: =BE32/BE31-1 -> -0.015411899 | BH32: Residual | BI32: 57 | BJ32: 0.29477233 | BK32: 0.0051714444 | BR32: 45017 | BS32: 4259.4 | BT32: =BS32/BS31-1 -> -0.071475907 | BV32: 233.18 | BW32: =BV32/BV31-1 -> -0.015411899 | BY32: Residual | BZ32: 57 | CA32: 0.44616393 | CB32: 0.0078274374
B33: 45047 | C33: 1209.05 | D33: =C33/C32-1 -> 0.052326948 | F33: 235.26 | G33: =F33/F32-1 -> 0.0089201475 | I33: Total | J33: 58 | K33: 0.25616339 | S33: 45047 | T33: 3025.25 | U33: =T33/T32-1 -> 0.021819533 | W33: 235.26 | X33: =W33/W32-1 -> 0.0089201475 | Z33: Total | AA33: 58 | AB33: 0.20647856 | AJ33: 45047 | AK33: 1038.38 | AL33: =AK33/AK32-1 -> 0.076119511 | AN33: 235.26 | AO33: =AN33/AN32-1 -> 0.0089201475 | AQ33: Total | AR33: 58 | AS33: 0.30270316 | BA33: 45047 | BB33: 188.79 | BC33: =BB33/BB32-1 -> 0.048425612 | BE33: 235.26 | BF33: =BE33/BE32-1 -> 0.0089201475 | BH33: Total | BI33: 58 | BJ33: 0.30383883 | BR33: 45047 | BS33: 4817.38 | BT33: =BS33/BS32-1 -> 0.13099967 | BV33: 235.26 | BW33: =BV33/BV32-1 -> 0.0089201475 | BY33: Total | BZ33: 58 | CA33: 0.45815943
B34: 45078 | C34: 1241.29 | D34: =C34/C33-1 -> 0.026665564 | F34: 216.48 | G34: =F34/F33-1 -> -0.079826575 | S34: 45078 | T34: 3059.57 | U34: =T34/T33-1 -> 0.011344517 | W34: 216.48 | X34: =W34/W33-1 -> -0.079826575 | AJ34: 45078 | AK34: 1077.24 | AL34: =AK34/AK33-1 -> 0.037423679 | AN34: 216.48 | AO34: =AN34/AN33-1 -> -0.079826575 | BA34: 45078 | BB34: 182.01 | BC34: =BB34/BB33-1 -> -0.035912919 | BE34: 216.48 | BF34: =BE34/BE33-1 -> -0.079826575 | BR34: 45078 | BS34: 5008.98 | BT34: =BS34/BS33-1 -> 0.039772657 | BV34: 216.48 | BW34: =BV34/BV33-1 -> -0.079826575
B35: 45108 | C35: 1260.06 | D35: =C35/C34-1 -> 0.015121366 | F35: 205.29 | G35: =F35/F34-1 -> -0.051690687 | J35: Coefficients | K35: Standard Error | L35: t Stat | M35: P-value | N35: Lower 95% | O35: Upper 95% | P35: Lower 95.0% | Q35: Upper 95.0% | S35: 45108 | T35: 3178.25 | U35: =T35/T34-1 -> 0.038789765 | W35: 205.29 | X35: =W35/W34-1 -> -0.051690687 | AA35: Coefficients | AB35: Standard Error | AC35: t Stat | AD35: P-value | AE35: Lower 95% | AF35: Upper 95% | AG35: Lower 95.0% | AH35: Upper 95.0% | AJ35: 45108 | AK35: 1021.36 | AL35: =AK35/AK34-1 -> -0.051873306 | AN35: 205.29 | AO35: =AN35/AN34-1 -> -0.051690687 | AR35: Coefficients | AS35: Standard Error | AT35: t Stat | AU35: P-value | AV35: Lower 95% | AW35: Upper 95% | AX35: Lower 95.0% | AY35: Upper 95.0% | BA35: 45108 | BB35: 189.44 | BC35: =BB35/BB34-1 -> 0.040821933 | BE35: 205.29 | BF35: =BE35/BE34-1 -> -0.051690687 | BI35: Coefficients | BJ35: Standard Error | BK35: t Stat | BL35: P-value | BM35: Lower 95% | BN35: Upper 95% | BO35: Lower 95.0% | BP35: Upper 95.0% | BR35: 45108 | BS35: 4751.66 | BT35: =BS35/BS34-1 -> -0.051371736 | BV35: 205.29 | BW35: =BV35/BV34-1 -> -0.051690687 | BZ35: Coefficients | CA35: Standard Error | CB35: t Stat | CC35: P-value | CD35: Lower 95% | CE35: Upper 95% | CF35: Lower 95.0% | CG35: Upper 95.0%
B36: 45139 | C36: 1334.19 | D36: =C36/C35-1 -> 0.058830532 | F36: 210.94 | G36: =F36/F35-1 -> 0.027522042 | I36: Intercept | J36: 0.002107374 | K36: 0.0087069438 | L36: 0.24203373 | M36: 0.80962273 | N36: -0.01532798 | O36: 0.019542728 | P36: -0.01532798 | Q36: 0.019542728 | S36: 45139 | T36: 3118.2 | U36: =T36/T35-1 -> -0.018894045 | W36: 210.94 | X36: =W36/W35-1 -> 0.027522042 | Z36: Intercept | AA36: -0.0029308755 | AB36: 0.0074265312 | AC36: -0.39464932 | AD36: 0.69457456 | AE36: -0.017802248 | AF36: 0.011940497 | AG36: -0.017802248 | AH36: 0.011940497 | AJ36: 45139 | AK36: 1072.08 | AL36: =AK36/AK35-1 -> 0.049659278 | AN36: 210.94 | AO36: =AN36/AN35-1 -> 0.027522042 | AQ36: Intercept | AR36: 0.0072012004 | AS36: 0.0093306696 | AT36: 0.77177745 | AU36: 0.44343426 | AV36: -0.011483143 | AW36: 0.025885544 | AX36: -0.011483143 | AY36: 0.025885544 | BA36: 45139 | BB36: 191.01 | BC36: =BB36/BB35-1 -> 0.0082875845 | BE36: 210.94 | BF36: =BE36/BE35-1 -> 0.027522042 | BH36: Intercept | BI36: 0.0022172971 | BJ36: 0.0097485672 | BK36: 0.22744851 | BL36: 0.82088886 | BM36: -0.017303872 | BN36: 0.021738466 | BO36: -0.017303872 | BP36: 0.021738466 | BR36: 45139 | BS36: 5044.78 | BT36: =BS36/BS35-1 -> 0.061687915 | BV36: 210.94 | BW36: =BV36/BV35-1 -> 0.027522042 | BY36: Intercept | BZ36: 0.0064938933 | CA36: 0.011993465 | CB36: 0.54145265 | CC36: 0.59030579 | CD36: -0.017522606 | CE36: 0.030510392 | CF36: -0.017522606 | CG36: 0.030510392
B37: 45170 | C37: 1334.19 | D37: =C37/C36-1 -> 0 | F37: 207.56 | G37: =F37/F36-1 -> -0.016023514 | I37: X Variable 1 | J37: -0.55864319 | K37: 0.24749733 | L37: -2.2571685 | M37: 0.02784685 | N37: -1.054248 | O37: -0.063038329 | P37: -1.054248 | Q37: -0.063038329 | S37: 45170 | T37: 3277.78 | U37: =T37/T36-1 -> 0.051176961 | W37: 207.56 | X37: =W37/W36-1 -> -0.016023514 | Z37: X Variable 1 | AA37: -0.7250798 | AB37: 0.21110124 | AC37: -3.4347491 | AD37: 0.0011124049 | AE37: -1.1478028 | AF37: -0.30235685 | AG37: -1.1478028 | AH37: -0.30235685 | AJ37: 45170 | AK37: 1129.38 | AL37: =AK37/AK36-1 -> 0.053447504 | AN37: 207.56 | AO37: =AN37/AN36-1 -> -0.016023514 | AQ37: X Variable 1 | AR37: -0.69639833 | AS37: 0.26522692 | AT37: -2.6256699 | AU37: 0.011084227 | AV37: -1.2275061 | AW37: -0.16529059 | AX37: -1.2275061 | AY37: -0.16529059 | BA37: 45170 | BB37: 189.91 | BC37: =BB37/BB36-1 -> -0.0057588608 | BE37: 207.56 | BF37: =BE37/BE36-1 -> -0.016023514 | BH37: X Variable 1 | BI37: -0.36690988 | BJ37: 0.27710577 | BK37: -1.3240788 | BL37: 0.19076219 | BM37: -0.92180462 | BN37: 0.18798486 | BO37: -0.92180462 | BP37: 0.18798486 | BR37: 45170 | BS37: 5060.76 | BT37: =BS37/BS36-1 -> 0.0031676307 | BV37: 207.56 | BW37: =BV37/BV36-1 -> -0.016023514 | BY37: X Variable 1 | BZ37: -0.42203534 | CA37: 0.34091762 | CB37: -1.2379394 | CC37: 0.2208134 | CD37: -1.1047111 | CE37: 0.26064042 | CF37: -1.1047111 | CG37: 0.26064042
B38: 45200 | C38: 1288.33 | D38: =C38/C37-1 -> -0.034372915 | F38: 211.24 | G38: =F38/F37-1 -> 0.017729813 | S38: 45200 | T38: 3137.39 | U38: =T38/T37-1 -> -0.042830818 | W38: 211.24 | X38: =W38/W37-1 -> 0.017729813 | AJ38: 45200 | AK38: 1178.22 | AL38: =AK38/AK37-1 -> 0.043244966 | AN38: 211.24 | AO38: =AN38/AN37-1 -> 0.017729813 | BA38: 45200 | BB38: 178.57 | BC38: =BB38/BB37-1 -> -0.059712495 | BE38: 211.24 | BF38: =BE38/BE37-1 -> 0.017729813 | BR38: 45200 | BS38: 4934.67 | BT38: =BS38/BS37-1 -> -0.02491523 | BV38: 211.24 | BW38: =BV38/BV37-1 -> 0.017729813
B39: 45231 | C39: 1370 | D39: =C39/C38-1 -> 0.063392143 | F39: 205 | G39: =F39/F38-1 -> -0.02953986 | S39: 45231 | T39: 3248.08 | U39: =T39/T38-1 -> 0.035280918 | W39: 205 | X39: =W39/W38-1 -> -0.02953986 | AJ39: 45231 | AK39: 1238.14 | AL39: =AK39/AK38-1 -> 0.050856377 | AN39: 205 | AO39: =AN39/AN38-1 -> -0.02953986 | BA39: 45231 | BB39: 193.18 | BC39: =BB39/BB38-1 -> 0.081816655 | BE39: 205 | BF39: =BE39/BE38-1 -> -0.02953986 | BR39: 45231 | BS39: 5399.14 | BT39: =BS39/BS38-1 -> 0.094123822 | BV39: 205 | BW39: =BV39/BV38-1 -> -0.02953986
B40: 45261 | C40: 1452.62 | D40: =C40/C39-1 -> 0.060306569 | F40: 198.07 | G40: =F40/F39-1 -> -0.033804878 | S40: 45261 | T40: 3532.88 | U40: =T40/T39-1 -> 0.087682569 | W40: 198.07 | X40: =W40/W39-1 -> -0.033804878 | AJ40: 45261 | AK40: 1353.75 | AL40: =AK40/AK39-1 -> 0.093373932 | AN40: 198.07 | AO40: =AN40/AN39-1 -> -0.033804878 | BA40: 45261 | BB40: 220.43 | BC40: =BB40/BB39-1 -> 0.14106015 | BE40: 198.07 | BF40: =BE40/BE39-1 -> -0.033804878 | BR40: 45261 | BS40: 6138.55 | BT40: =BS40/BS39-1 -> 0.13694959 | BV40: 198.07 | BW40: =BV40/BV39-1 -> -0.033804878
B41: 45292 | C41: 1563.71 | D41: =C41/C40-1 -> 0.07647561 | F41: 191.86 | G41: =F41/F40-1 -> -0.031352552 | S41: 45292 | T41: 3578.64 | U41: =T41/T40-1 -> 0.012952605 | W41: 191.86 | X41: =W41/W40-1 -> -0.031352552 | AJ41: 45292 | AK41: 1466.46 | AL41: =AK41/AK40-1 -> 0.083257618 | AN41: 191.86 | AO41: =AN41/AN40-1 -> -0.031352552 | BA41: 45292 | BB41: 224.11 | BC41: =BB41/BB40-1 -> 0.016694642 | BE41: 191.86 | BF41: =BE41/BE40-1 -> -0.031352552 | BR41: 45292 | BS41: 5313.18 | BT41: =BS41/BS40-1 -> -0.13445683 | BV41: 191.86 | BW41: =BV41/BV40-1 -> -0.031352552
B42: 45323 | C42: 1575.95 | D42: =C42/C41-1 -> 0.0078275384 | F42: 184.47 | G42: =F42/F41-1 -> -0.038517669 | S42: 45323 | T42: 3840.43 | U42: =T42/T41-1 -> 0.073153488 | W42: 184.47 | X42: =W42/W41-1 -> -0.038517669 | AJ42: 45323 | AK42: 1548.2 | AL42: =AK42/AK41-1 -> 0.055739672 | AN42: 184.47 | AO42: =AN42/AN41-1 -> -0.038517669 | BA42: 45323 | BB42: 243.07 | BC42: =BB42/BB41-1 -> 0.084601312 | BE42: 184.47 | BF42: =BE42/BE41-1 -> -0.038517669 | BR42: 45323 | BS42: 5169.15 | BT42: =BS42/BS41-1 -> -0.02710806 | BV42: 184.47 | BW42: =BV42/BV41-1 -> -0.038517669
B43: 45352 | C43: 1410.39 | D43: =C43/C42-1 -> -0.10505409 | F43: 184.67 | G43: =F43/F42-1 -> 0.0010841871 | S43: 45352 | T43: 3635.24 | U43: =T43/T42-1 -> -0.053428913 | W43: 184.67 | X43: =W43/W42-1 -> 0.0010841871 | AJ43: 45352 | AK43: 1436.26 | AL43: =AK43/AK42-1 -> -0.07230332 | AN43: 184.67 | AO43: =AN43/AN42-1 -> 0.0010841871 | BA43: 45352 | BB43: 225.02 | BC43: =BB43/BB42-1 -> -0.074258444 | BE43: 184.67 | BF43: =BE43/BE42-1 -> 0.0010841871 | BR43: 45352 | BS43: 4815.7 | BT43: =BS43/BS42-1 -> -0.068376812 | BV43: 184.67 | BW43: =BV43/BV42-1 -> 0.0010841871
B44: 45383 | C44: 1337.43 | D44: =C44/C43-1 -> -0.051730372 | F44: 188.91 | G44: =F44/F43-1 -> 0.022959874 | S44: 45383 | T44: 3583.05 | U44: =T44/T43-1 -> -0.014356686 | W44: 188.91 | X44: =W44/W43-1 -> 0.022959874 | AJ44: 45383 | AK44: 1271.61 | AL44: =AK44/AK43-1 -> -0.11463802 | AN44: 188.91 | AO44: =AN44/AN43-1 -> 0.022959874 | BA44: 45383 | BB44: 216.73 | BC44: =BB44/BB43-1 -> -0.03684117 | BE44: 188.91 | BF44: =BE44/BE43-1 -> 0.022959874 | BR44: 45383 | BS44: 4589.47 | BT44: =BS44/BS43-1 -> -0.046977594 | BV44: 188.91 | BW44: =BV44/BV43-1 -> 0.022959874
B45: 45413 | C45: 1351.08 | D45: =C45/C44-1 -> 0.010206142 | F45: 193.04 | G45: =F45/F44-1 -> 0.021862262 | S45: 45413 | T45: 3467.68 | U45: =T45/T44-1 -> -0.032198825 | W45: 193.04 | X45: =W45/W44-1 -> 0.021862262 | AJ45: 45413 | AK45: 1248.6 | AL45: =AK45/AK44-1 -> -0.018095171 | AN45: 193.04 | AO45: =AN45/AN44-1 -> 0.021862262 | BA45: 45413 | BB45: 205.38 | BC45: =BB45/BB44-1 -> -0.052369307 | BE45: 193.04 | BF45: =BE45/BE44-1 -> 0.021862262 | BR45: 45413 | BS45: 4585.08 | BT45: =BS45/BS44-1 -> -0.00095653747 | BV45: 193.04 | BW45: =BV45/BV44-1 -> 0.021862262
B46: 45444 | C46: 1504.58 | D46: =C46/C45-1 -> 0.11361281 | F46: 199.95 | G46: =F46/F45-1 -> 0.03579569 | S46: 45444 | T46: 3687.96 | U46: =T46/T45-1 -> 0.063523739 | W46: 199.95 | X46: =W46/W45-1 -> 0.03579569 | AJ46: 45444 | AK46: 1376.38 | AL46: =AK46/AK45-1 -> 0.10233862 | AN46: 199.95 | AO46: =AN46/AN45-1 -> 0.03579569 | BA46: 45444 | BB46: 241.31 | BC46: =BB46/BB45-1 -> 0.17494401 | BE46: 199.95 | BF46: =BE46/BE45-1 -> 0.03579569 | BR46: 45444 | BS46: 5298.1 | BT46: =BS46/BS45-1 -> 0.15550874 | BV46: 199.95 | BW46: =BV46/BV45-1 -> 0.03579569
B47: 45474 | C47: 1794.12 | D47: =C47/C46-1 -> 0.19243909 | F47: 191.01 | G47: =F47/F46-1 -> -0.044711178 | S47: 45474 | T47: 4152.14 | U47: =T47/T46-1 -> 0.12586362 | W47: 191.01 | X47: =W47/W46-1 -> -0.044711178 | AJ47: 45474 | AK47: 1560.82 | AL47: =AK47/AK46-1 -> 0.13400369 | AN47: 191.01 | AO47: =AN47/AN46-1 -> -0.044711178 | BA47: 45474 | BB47: 244.66 | BC47: =BB47/BB46-1 -> 0.013882558 | BE47: 191.01 | BF47: =BE47/BE46-1 -> -0.044711178 | BR47: 45474 | BS47: 5566.79 | BT47: =BS47/BS46-1 -> 0.050714407 | BV47: 191.01 | BW47: =BV47/BV46-1 -> -0.044711178
B48: 45505 | C48: 1866.58 | D48: =C48/C47-1 -> 0.040387488 | F48: 181.89 | G48: =F48/F47-1 -> -0.047746191 | S48: 45505 | T48: 4311.58 | U48: =T48/T47-1 -> 0.038399476 | W48: 181.89 | X48: =W48/W47-1 -> -0.047746191 | AJ48: 45505 | AK48: 1665.96 | AL48: =AK48/AK47-1 -> 0.067362028 | AN48: 181.89 | AO48: =AN48/AN47-1 -> -0.047746191 | BA48: 45505 | BB48: 252.35 | BC48: =BB48/BB47-1 -> 0.031431374 | BE48: 181.89 | BF48: =BE48/BE47-1 -> -0.047746191 | BR48: 45505 | BS48: 6056.65 | BT48: =BS48/BS47-1 -> 0.087996853 | BV48: 181.89 | BW48: =BV48/BV47-1 -> -0.047746191
B49: 45536 | C49: 1801.18 | D49: =C49/C48-1 -> -0.035037341 | F49: 188.56 | G49: =F49/F48-1 -> 0.036670515 | S49: 45536 | T49: 4041.5 | U49: =T49/T48-1 -> -0.06264061 | W49: 188.56 | X49: =W49/W48-1 -> 0.036670515 | AJ49: 45536 | AK49: 1706.68 | AL49: =AK49/AK48-1 -> 0.024442364 | AN49: 188.56 | AO49: =AN49/AN48-1 -> 0.036670515 | BA49: 45536 | BB49: 253.78 | BC49: =BB49/BB48-1 -> 0.0056667327 | BE49: 188.56 | BF49: =BE49/BE48-1 -> 0.036670515 | BR49: 45536 | BS49: 6143.52 | BT49: =BS49/BS48-1 -> 0.014342912 | BV49: 188.56 | BW49: =BV49/BV48-1 -> 0.036670515
... B66: 46054 | C66: 1656 | D66: =C66/C65-1 -> 0.0091407678 | F66: 152.85 | G66: =F66/F65-1 -> -0.00117624 | S66: 46054 | T66: 3225.3 | U66: =T66/T65-1 -> 0.032459426 | W66: 152.85 | X66: =W66/W65-1 -> -0.00117624 | AJ66: 46054 | AK66: 1573.1 | AL66: =AK66/AK65-1 -> -0.072245813 | AN66: 152.85 | AO66: =AN66/AN65-1 -> -0.00117624 | BA66: 46054 | BB66: 231.47 | BC66: =BB66/BB65-1 -> -0.022921064 | BE66: 152.85 | BF66: =BE66/BE65-1 -> -0.00117624 | BR66: 46054 | BS66: 5662 | BT66: =BS66/BS65-1 -> -0.052305632 | BV66: 152.85 | BW66: =BV66/BV65-1 -> -0.00117624

Sheet Rm
B2: Return on Markets
B4: Year | C4: Annual
B5: 2000 | C5: -0.1465 | E5: Average Return | G5: =AVERAGE(C5:C30) -> 0.15149231
B6: 2001 | C6: -0.1618 | E6: Divident Yield | G6: 1.28% 1
B7: 2002 | C7: 0.0325 | E7: Total Market Return | G7: =SUM(G5:G6) -> 0.15149231
B8: 2003 | C8: 0.719
B9: 2004 | C9: 0.1068
B10: 2005 | C10: 0.3634
B11: 2006 | C11: 0.3983
B12: 2007 | C12: 0.5477
B13: 2008 | C13: -0.5179
B14: 2009 | C14: 0.7576
B15: 2010 | C15: 0.1795
B16: 2011 | C16: -0.2462
B17: 2012 | C17: 0.277
B18: 2013 | C18: 0.0676
B19: 2014 | C19: 0.3139
... B30: 2025 | C30: 0.1051

Sheet Beta Comps
B2: S.No. | C2: Name | D2: CMP Rs. | E2: Mar Cap Rs.Cr. | F2: Debt Rs.Cr. | G2: Debt / Eq
B3: 1 | C3: TCS | D3: 2947.1 | E3: 1066286.6 | F3: 10932 | G3: 0.1
B4: 2 | C4: Infosys | D4: 1497.05 | E4: 607005.1 | F4: 8796 | G4: 0.11
B5: 3 | C5: HCL Technologies | D5: 1600.8 | E5: 434403.52 | F5: 6780 | G5: 0.1
B6: 4 | C6: Wipro | D6: 230.1 | E6: 241313.87 | F6: 16163.7 | G6: 0.19
B7: 5 | C7: LTIMindtree | D7: 5625.75 | E7: 166799.73 | F7: 2382.6 | G7: 0.1

Sheet Data DCF
B2: Infosys Data | F2: NIFTY Data | J2: TSC Data | N2: HCL Technologies Data | R2: Wipro Data | V2: LTIMindtree Data
B3: Date | C3: Adj. Close | F3: Date | G3: Adj. Close | J3: Date | K3: Adj. Close | N3: Date | O3: Adj. Close | R3: Date | S3: Adj. Close | V3: Date | W3: Adj. Close
B4: 46054 | C4: 1656 | F4: 46054 | G4: 282.93 | J4: 46054 | K4: 2793.57 | N4: 46054 | O4: 1573.1 | R4: 46054 | S4: 231.47 | V4: 46054 | W4: 5662
B5: 46023 | C5: 1641 | F5: 46023 | G5: 279.32 | J5: 46023 | K5: 2668.57 | N5: 46023 | O5: 1695.6 | R5: 46023 | S5: 236.9 | V5: 46023 | W5: 5974.5
B6: 45992 | C6: 1615.4 | F6: 45992 | G6: 287.88 | J6: 45992 | K6: 2790.72 | N6: 45992 | O6: 1611.63 | R6: 45992 | S6: 256.65 | V6: 45992 | W6: 6063.5
B7: 45962 | C7: 1560.1 | F7: 45962 | G7: 288.64 | J7: 45962 | K7: 2955.56 | N7: 45962 | O7: 1612.52 | R7: 45962 | S7: 243.25 | V7: 45962 | W7: 6096.5
B8: 45931 | C8: 1482.3 | F8: 45931 | G8: 283.22 | J8: 45931 | K8: 2804.16 | N8: 45931 | O8: 1530.41 | R8: 45931 | S8: 234.61 | V8: 45931 | W8: 5684.5
B9: 45901 | C9: 1420.06 | F9: 45901 | G9: 270.2 | J9: 45901 | K9: 3352.16 | N9: 45901 | O9: 1364.25 | R9: 45901 | S9: 233.35 | V9: 45901 | W9: 5137.3
B10: 45870 | C10: 1447.44 | F10: 45870 | G10: 268.67 | J10: 45870 | K10: 3342.51 | N10: 45870 | O10: 1432.9 | R10: 45870 | S10: 243.13 | V10: 45870 | W10: 5113.39
B11: 45839 | C11: 1486.25 | F11: 45839 | G11: 272.04 | J11: 45839 | K11: 3013.82 | N11: 45839 | O11: 1445.8 | R11: 45839 | S11: 242.05 | V11: 45839 | W11: 5086
B12: 45809 | C12: 1577.65 | F12: 45809 | G12: 279.35 | J12: 45809 | K12: 3130.37 | N12: 45809 | O12: 1689.34 | R12: 45809 | S12: 254.28 | V12: 45809 | W12: 5296.18
B13: 45778 | C13: 1539.14 | F13: 45778 | G13: 270.53 | J13: 45778 | K13: 3315.93 | N13: 45778 | O13: 1599.43 | R13: 45778 | S13: 238.69 | V13: 45778 | W13: 5049.05
B14: 45748 | C14: 1456.98 | F14: 45748 | G14: 265.19 | J14: 45748 | K14: 3319.89 | N14: 45748 | O14: 1531.9 | R14: 45748 | S14: 230.88 | V14: 45748 | W14: 4527.61
B15: 45717 | C15: 1525.5 | F15: 45717 | G15: 255.89 | J15: 45717 | K15: 3158.13 | N15: 45717 | O15: 1538.58 | R15: 45717 | S15: 250.72 | V15: 45717 | W15: 4433.68
... B63: 44256 | C63: 1204.32 | F63: 44256 | G63: 152.85 | J63: 44256 | K63: 3225.3 | N63: 44256 | O63: 803.33 | R63: 44256 | S63: 191.32 | V63: 44256 | W63: 3820.59

Sheet Cash Flow Data
B3: Praticulars | C3: 41699 | D3: 42064 | E3: 42430 | F3: 42795 | G3: 43160 | H3: 43525 | I3: 43891 | J3: 44256 | K3: 44621 | L3: 44986 | M3: 45352 | N3: 45717
B4: Cash from Operating Activity - | C4: 9825 | D4: 8353 | E4: 10028 | F4: 11531 | G4: 13218 | H4: 14841 | I4: 17003 | J4: 23224 | K4: 23885 | L4: 22467 | M4: 25210 | N4: 35694
B5: Profit from operations | C5: 14172 | D5: 15946 | E5: 17839 | F5: 19340 | G5: 19963 | H5: 22126 | I5: 23920 | J5: 28845 | K5: 32921 | L5: 37605 | M5: 39523 | N5: 41591
B6: Receivables | C6: -1406 | D6: -1475 | E6: -1654 | F6: -1743 | G6: -1523 | H6: -2881 | I6: -3861 | J6: -1835 | K6: -7937 | L6: -7076 | M6: -2667 | N6: -1769
B7: Payables | C7: 0 | D7: 0 | E7: 242 | F7: -19 | G7: 328 | H7: 916 | I7: -373 | J7: -245 | K7: 1489 | L7: -279 | M7: 91 | N7: 176
B8: Loans Advances | C8: -1060 | D8: -221 | E8: -1134 | F8: 0 | G8: 0 | H8: 0 | I8: 0 | J8: -534 | K8: -1914 | L8: -3108 | M8: -1172 | N8: -1024
B9: Other WC items | C9: 1993 | D9: 854 | E9: 600 | F9: -394 | G9: 1279 | H9: 1512 | I9: 1867 | J9: 3382 | K9: 6938 | L9: 4119 | M9: -1334 | N9: 2322
B10: Working capital changes | C10: -473 | D10: -842 | E10: -1946 | F10: -2156 | G10: 84 | H10: -453 | I10: -2367 | J10: 768 | K10: -1424 | L10: -6344 | M10: -5082 | N10: -295
B11: Direct taxes | C11: -3874 | D11: -6751 | E11: -5865 | F11: -5653 | G11: -6829 | H11: -6832 | I11: -4550 | J11: -6389 | K11: -7612 | L11: -8794 | M11: -9231 | N11: -5602
B12: Cash from Investing Activity - | C12: -2563 | D12: 999 | E12: -885 | F12: -14664 | G12: 4533 | H12: -632 | I12: -331 | J12: -7373 | K12: -6485 | L12: -1071 | M12: -5093 | N12: -1864
B13: Fixed assets purchased | C13: -2748 | D13: -2247 | E13: -2723 | F13: -2760 | G13: -1998 | H13: -2445 | I13: -3307 | J13: -2107 | K13: -2161 | L13: -2579 | M13: -2201 | N13: -2237
B14: Fixed assets sold | C14: 3 | D14: 0 | E14: 0 | F14: 0 | G14: 0 | H14: 0 | I14: 0 | J14: 0 | K14: 0 | L14: 0 | M14: 0 | N14: 0
... B28: Net Cash Flow | C28: 4118 | D28: 4417 | E28: 2330 | F28: -10072 | G28: -2754 | H28: -303 | I28: -919 | J28: 6065 | K28: -7242 | L28: -5299 | M28: 2613 | N28: 9669

Sheet Raw FS
A3: # | B3: Particulars | C3: 41699 | D3: 42064 | E3: 42430 | F3: 42795 | G3: 43160 | H3: 43525 | I3: 43891 | J3: 44256 | K3: 44621 | L3: 44986 | M3: 45352 | N3: 45717
B5: Equity Capital | C5: 286 | D5: 572 | E5: 1144 | F5: 1144 | G5: 1088 | H5: 2170 | I5: 2122 | J5: 2124 | K5: 2098 | L5: 2069 | M5: 2071 | N5: 2073
B6: Reserves | C6: 44244 | D6: 50164 | E6: 60600 | F6: 67838 | G6: 63835 | H6: 62778 | I6: 63328 | J6: 74227 | K6: 73252 | L6: 73338 | M6: 86045 | N6: 93745
B7: Borrowings -
B8: Lease Liabilities | C8: 0 | D8: 0 | E8: 0 | F8: 0 | G8: 0 | H8: 0 | I8: 4633 | J8: 5325 | K8: 5474 | L8: 8299 | M8: 8359 | N8: 8227
B9: Other Liabilities -
B10: Non controlling int | C10: 0 | D10: 0 | E10: 0 | F10: 0 | G10: 1 | H10: 58 | I10: 394 | J10: 431 | K10: 386 | L10: 388 | M10: 345 | N10: 385
B11: Trade Payables | C11: 173 | D11: 140 | E11: 386 | F11: 367 | G11: 694 | H11: 1655 | I11: 2852 | J11: 2645 | K11: 4134 | L11: 3865 | M11: 3956 | N11: 4164
B12: Advance from Customers | C12: 40 | D12: 27 | E12: 28 | F12: 0 | G12: 0 | H12: 0 | I12: 0 | J12: 0 | K12: 0 | L12: 0 | M12: 0 | N12: 0
B13: Other liability items | C13: 12223 | D13: 15386 | E13: 12940 | F13: 13799 | G13: 13731 | H13: 17405 | I13: 18471 | J13: 22759 | K13: 31385 | L13: 36637 | M13: 36584 | N13: 39201
B14: Total Liabilities | C14: 56966 | D14: 66289 | E14: 75098 | F14: 83148 | G14: 79349 | H14: 84066 | I14: 91800 | J14: 107511 | K14: 116729 | L14: 124596 | M14: 137360 | N14: 147795
B16: Fixed Assets -
B17: Land | C17: 1142 | D17: 1564 | E17: 1622 | F17: 1095 | G17: 1229 | H17: 1307 | I17: 1950 | J17: 2036 | K17: 2065 | L17: 2054 | M17: 2037 | N17: 2079
B18: Building | C18: 5238 | D18: 6102 | E18: 6325 | F18: 8419 | G18: 9334 | H18: 10270 | I18: 15104 | J18: 16328 | K18: 16761 | L18: 16903 | M18: 16515 | N18: 16376
B19: Plant Machinery | C19: 1150 | D19: 1427 | E19: 1759 | F19: 2048 | G19: 2306 | H19: 2709 | I19: 3185 | J19: 3296 | K19: 3210 | L19: 3302 | M19: 3428 | N19: 3461
B20: Equipments | C20: 551 | D20: 676 | E20: 839 | F20: 922 | G20: 1002 | H20: 1101 | I20: 1265 | J20: 1371 | K20: 1427 | L20: 1482 | M20: 1528 | N20: 1628
B21: Computers | C21: 2659 | D21: 3347 | E21: 4486 | F21: 4945 | G21: 4903 | H21: 6287 | I21: 7423 | J21: 8650 | K21: 9936 | L21: 11898 | M21: 12353 | N21: 12925
B22: Furniture n fittings | C22: 805 | D22: 958 | E22: 1444 | F22: 1277 | G22: 1393 | H22: 1620 | I22: 2073 | J22: 2149 | K22: 2279 | L22: 2303 | M22: 2326 | N22: 2340
B23: Vehicles | C23: 35 | D23: 34 | E23: 29 | F23: 31 | G23: 31 | H23: 38 | I23: 69 | J23: 74 | K23: 71 | L23: 60 | M23: 62 | N23: 72
B24: Intangible Assets | C24: 2244 | D24: 3637 | E24: 3858 | F24: 3743 | G24: 2237 | H24: 3640 | I24: 5527 | J24: 6372 | K24: 6495 | L24: 7594 | M24: 7653 | N24: 10626
B25: Other fixed assets | C25: 126 | D25: 71 | E25: 931 | F25: 899 | G25: 545 | H25: 1093 | I25: 2289 | J25: 2730 | K25: 2766 | L25: 3281 | M25: 3294 | N25: 5184
B26: Gross Block | C26: 13950 | D26: 17816 | E26: 21293 | F26: 23379 | G26: 22980 | H26: 28065 | I26: 38885 | J26: 43006 | K26: 45010 | L26: 48877 | M26: 49196 | N26: 54691
B27: Accumulated Depreciation | C27: 5572 | D27: 6470 | E27: 7907 | F27: 9200 | G27: 10406 | H27: 12355 | I27: 15096 | J27: 17501 | K27: 19210 | L27: 19652 | M27: 21574 | N27: 23730
B28: Net Block | C28: =C26-C27 -> 8378 | D28: =D26-D27 -> 11346 | E28: =E26-E27 -> 13386 | F28: =F26-F27 -> 14179 | G28: =G26-G27 -> 12574 | H28: =H26-H27 -> 15710 | I28: =I26-I27 -> 23789 | J28: =J26-J27 -> 25505 | ... N28: =N26-N27 -> 30961
B30: CWIP | C30: 961 | D30: 776 | E30: 960 | F30: 1365 | G30: 1606 | H30: 1388 | I30: 954 | J30: 922 | K30: 416 | L30: 288 | M30: 293 | N30: 814
B31: Investments | C31: 4331 | D31: 2270 | E31: 1892 | F31: 16423 | G31: 12163 | H31: 11261 | I31: 8792 | J31: 14205 | K31: 20324 | L31: 19478 | M31: 24623 | N31: 23541
B33: Other Assets -
B34: Trade receivables | C34: 8351 | D34: 9713 | E34: 11330 | F34: 12322 | G34: 13142 | H34: 14827 | I34: 18487 | J34: 19294 | K34: 22698 | L34: 25424 | M34: 30193 | N34: 31158
B35: Cash Equivalents | C35: 25950 | D35: 30367 | E35: 32697 | F35: 22625 | G35: 19818 | H35: 19568 | I35: 18649 | J35: 24714 | K35: 17472 | L35: 12173 | M35: 14786 | N35: 24455
B36: Loans n Advances | C36: 1484 | D36: 399 | E36: 614 | F36: 844 | G36: 830 | H36: 1524 | I36: 1359 | J36: 1460 | K36: 2491 | L36: 3242 | M36: 10330 | N36: 6717
B37: Other asset items | C37: 7511 | D37: 11418 | E37: 14219 | F37: 15390 | G37: 19216 | H37: 19788 | I37: 19770 | J37: 21411 | K37: 27528 | L37: 34766 | M37: 29513 | N37: 30149
B38: Total Assets | C38: 56966 | D38: 66289 | E38: 75098 | F38: 83148 | G38: 79349 | H38: 84066 | I38: 91800 | J38: 107511 | K38: 116729 | L38: 124596 | M38: 137360 | N38: 147795
A41: # | B41: Particulars | C41: 41699 | D41: 42064 | E41: 42430 | F41: 42795 | G41: 43160 | H41: 43525 | I41: 43891 | J41: 44256 | K41: 44621 | L41: 44986 | M41: 45352 | N41: 45717
B43: Cash from Operating Activity -
B44: Profit from operations | C44: 14172 | D44: 15946 | E44: 17839 | F44: 19340 | G44: 19963 | H44: 22126 | I44: 23920 | J44: 28845 | K44: 32921 | L44: 37605 | M44: 39523 | N44: 41591
B45: Receivables | C45: -1406 | D45: -1475 | E45: -1654 | F45: -1743 | G45: -1523 | H45: -2881 | I45: -3861 | J45: -1835 | K45: -7937 | L45: -7076 | M45: -2667 | N45: -1769
B46: Payables | C46: 0 | D46: 0 | E46: 242 | F46: -19 | G46: 328 | H46: 916 | I46: -373 | J46: -245 | K46: 1489 | L46: -279 | M46: 91 | N46: 176
B47: Loans Advances | C47: -1060 | D47: -221 | E47: -1134 | F47: 0 | G47: 0 | H47: 0 | I47: 0 | J47: -534 | K47: -1914 | L47: -3108 | M47: -1172 | N47: -1024
B48: Other WC items | C48: 1993 | D48: 854 | E48: 600 | F48: -394 | G48: 1279 | H48: 1512 | I48: 1867 | J48: 3382 | K48: 6938 | L48: 4119 | M48: -1334 | N48: 2322
B49: Working capital changes | C49: -473 | D49: -842 | E49: -1946 | F49: -2156 | G49: 84 | H49: -453 | I49: -2367 | J49: 768 | K49: -1424 | L49: -6344 | M49: -5082 | N49: -295
B50: Direct taxes | C50: -3874 | D50: -6751 | E50: -5865 | F50: -5653 | G50: -6829 | H50: -6832 | I50: -4550 | J50: -6389 | K50: -7612 | L50: -8794 | M50: -9231 | N50: -5602
B52: Cash from Investing Activity -
B53: Fixed assets purchased | C53: -2748 | D53: -2247 | E53: -2723 | F53: -2760 | G53: -1998 | H53: -2445 | I53: -3307 | J53: -2107 | K53: -2161 | L53: -2579 | M53: -2201 | N53: -2237
B54: Fixed assets sold | C54: 3 | D54: 0 | E54: 0 | F54: 0 | G54: 0 | H54: 0 | I54: 0 | J54: 0 | K54: 0 | L54: 0 | M54: 0 | N54: 0
B55: Investments purchased | C55: -25046 | D55: -23923 | E55: -24577 | F55: -66410 | G55: -69159 | H55: -79410 | I55: -37482 | J55: -46738 | K55: -59951 | L55: -75800 | M55: -78118 | N55: -82753
B56: Investments sold | C56: 22385 | D56: 25253 | E56: 24980 | F56: 52048 | G56: 74003 | H56: 78098 | I56: 38861 | J56: 40381 | K56: 57356 | L56: 76722 | M56: 72956 | N56: 84888
B57: Interest received | C57: 2379 | D57: 2551 | E57: 2383 | F57: 0 | G57: 0 | H57: 0 | I57: 0 | J57: 0 | K57: 0 | L57: 0 | M57: 0 | N57: 0
B58: Dividends received | C58: 0 | D58: 0 | E58: 0 | F58: 2753 | G58: 1768 | H58: 1557 | I58: 1929 | J58: 1418 | K58: 1898 | L58: 1525 | M58: 1768 | N58: 2040
B59: Acquisition of companies | C59: 0 | D59: -1376 | E59: -747 | F59: 0 | G59: 0 | H59: 0 | I59: 0 | J59: 0 | K59: 0 | L59: 0 | M59: 0 | N59: 0
B60: Inter corporate deposits | C60: 0 | D60: 0 | E60: -142 | F60: -164 | G60: -130 | H60: -24 | I60: -108 | J60: 0 | K60: 0 | L60: 0 | M60: 0 | N60: 0
B61: Other investing items | C61: 464 | D61: 741 | E61: -59 | F61: -131 | G61: 49 | H61: 1592 | I61: -224 | J61: -327 | K61: -3627 | L61: -939 | M61: 502 | N61: -3802
B63: Cash from Financing Activity -
B64: Proceeds from shares | C64: 0 | D64: 0 | E64: 0 | F64: 0 | G64: 5 | H64: 6 | I64: 6 | J64: 15 | K64: 21 | L64: 35 | M64: 5 | N64: 6
B65: Repayment of borrowings | C65: 0 | D65: 0 | E65: 0 | F65: 0 | G65: 0 | H65: 0 | I65: 0 | J65: 0 | K65: 0 | L65: 0 | M65: 0 | N65: -985
B66: Dividends paid | C66: -3144 | D66: -4935 | E66: -6813 | F66: -6939 | G66: -7464 | H66: -13705 | I66: -9548 | J66: -9137 | K66: -12731 | L66: -13653 | M66: -14731 | N66: -20289
B67: Financial liabilities | C67: 0 | D67: 0 | E67: 0 | F67: 0 | G67: 0 | H67: 0 | I67: -571 | J67: -698 | K67: -915 | L67: -1231 | M67: -2024 | N67: -2355
B68: Other financing items | C68: 0 | D68: 0 | E68: 0 | F68: 0 | G68: -13046 | H68: -813 | I68: -7478 | J68: 34 | K68: -11017 | L68: -11846 | M68: -754 | N68: -538
B69: Net Cash Flow | C69: 4118 | D69: 4417 | E69: 2330 | F69: -10072 | G69: -2754 | H69: -303 | I69: -919 | J69: 6065 | K69: -7242 | L69: -5299 | M69: 2613 | N69: 9669

Sheet Data Room>

Sheet Data Sheet
A1: COMPANY NAME | B1: INFOSYS LTD | E1: =IF(B2<>B3, "A NEW VERSION OF THE WORKSHEET IS AVAILABLE", "")
A2: LATEST VERSION | B2: 2.1 | E2: PLEASE DO NOT MAKE ANY CHANGES TO THIS SHEET
A3: CURRENT VERSION | B3: 2.1
A5: META
A6: Number of shares | B6: =IF(B9>0, B9/B8, 0) -> 405.46679
A7: Face Value | B7: 5
A8: Current Price | B8: 1599.8
A9: Market Capitalization | B9: 648665.77
A15: PROFIT & LOSS
A16: Report Date | B16: 42460 | C16: 42825 | D16: 43190 | E16: 43555 | F16: 43921 | G16: 44286 | H16: 44651 | I16: 45016 | J16: 45382 | K16: 45747
A17: Sales | B17: 62441 | C17: 68484 | D17: 70522 | E17: 82675 | F17: 90791 | G17: 100472 | H17: 121641 | I17: 146767 | J17: 153670 | K17: 162990
A18: Raw Material Cost
A19: Change in Inventory
A20: Power and Fuel | B20: 217 | C20: 228 | D20: 207 | E20: 221 | F20: 229 | G20: 143 | H20: 132 | I20: 176 | J20: 199 | K20: 222
A21: Other Mfr. Exp | B21: 5860 | C21: 6712 | D21: 7286 | E21: 9902 | F21: 11086 | G21: 12800 | H21: 20690 | I21: 26330 | J21: 27195 | K21: 30395
A22: Employee Cost | B22: 34415 | C22: 37669 | D22: 38902 | E22: 45323 | F22: 50895 | G22: 55547 | H22: 63997 | I22: 78374 | J22: 82636 | K22: 85968
A23: Selling and admin | B23: 4441 | C23: 4584 | D23: 4585 | E23: 5553 | F23: 5375 | G23: 3194 | H23: 4305 | I23: 5300 | J23: 5705 | K23: 6039
A24: Other Expenses | B24: 429 | C24: 687 | D24: 720 | E24: 1506 | F24: 939 | G24: 899 | H24: 1026 | I24: 1457 | J24: 1510 | K24: 1130
A25: Other Income | B25: 3120 | C25: 3050 | D25: 3311 | E25: 2882 | F25: 2803 | G25: 2201 | H25: 2295 | I25: 2701 | J25: 4711 | K25: 3600
A26: Depreciation | B26: 1459 | C26: 1703 | D26: 1863 | E26: 2011 | F26: 2893 | G26: 3267 | H26: 3476 | I26: 4225 | J26: 4678 | K26: 4812
A27: Interest | F27: 170 | G27: 195 | H27: 200 | I27: 284 | J27: 470 | K27: 416
A28: Profit before tax | B28: 18740 | C28: 19951 | D28: 20270 | E28: 21041 | F28: 22007 | G28: 26628 | H28: 30110 | I28: 33322 | J28: 35988 | K28: 37608
A29: Tax | B29: 5251 | C29: 5598 | D29: 4241 | E29: 5631 | F29: 5368 | G29: 7205 | H29: 7964 | I29: 9214 | J29: 9740 | K29: 10858
A30: Net profit | B30: 13489 | C30: 14353 | D30: 16029 | E30: 15404 | F30: 16594 | G30: 19351 | H30: 22110 | I30: 24095 | J30: 26233 | K30: 26713
A31: Dividend Amount | B31: 5548.4 | C31: 5891.6 | D31: 9465.6 | E31: 9222.5 | F31: 7427 | G31: 11469.6 | H31: 13007.6 | I31: 14069.2 | J31: 19053.2 | K31: 17827.8
A33: EBITDA | B33: =B30+B29+B27+B26 -> 20199 | C33: =C30+C29+C27+C26 -> 21654 | D33: =D30+D29+D27+D26 -> 22133 | E33: =E30+E29+E27+E26 -> 23046 | F33: =F30+F29+F27+F26 -> 25025 | G33: =G30+G29+G27+G26 -> 30018 | H33: =H30+H29+H27+H26 -> 33750 | I33: =I30+I29+I27+I26 -> 37818 | ... K33: =K30+K29+K27+K26 -> 42799
A40: Quarters
A41: Report Date | B41: 45199 | C41: 45291 | D41: 45382 | E41: 45473 | F41: 45565 | G41: 45657 | H41: 45747 | I41: 45838 | J41: 45930 | K41: 46022
A42: Sales | B42: 38994 | C42: 38821 | D42: 37923 | E42: 39315 | F42: 40986 | G42: 41764 | H42: 40925 | I42: 42279 | J42: 44490 | K42: 45479
A43: Expenses | B43: 29554 | C43: 29684 | D43: 29139 | E43: 29878 | F43: 31177 | G43: 31649 | H43: 31051 | I43: 32336 | J43: 33955 | K43: 34845
A44: Other Income | B44: 632 | C44: 789 | D44: 2729 | E44: 838 | F44: 712 | G44: 859 | H44: 1190 | I44: 1042 | J44: 982 | K44: -150
A45: Depreciation | B45: 1166 | C45: 1176 | D45: 1163 | E45: 1149 | F45: 1160 | G45: 1203 | H45: 1299 | I45: 1140 | J45: 1182 | K45: 1155
A46: Interest | B46: 138 | C46: 131 | D46: 110 | E46: 105 | F46: 108 | G46: 101 | H46: 102 | I46: 105 | J46: 106 | K46: 100
A47: Profit before tax | B47: 8768 | C47: 8619 | D47: 10240 | E47: 9021 | F47: 9253 | G47: 9670 | H47: 9663 | I47: 9740 | J47: 10229 | K47: 9229
A48: Tax | B48: 2553 | C48: 2506 | D48: 2265 | E48: 2647 | F48: 2737 | G48: 2848 | H48: 2625 | I48: 2816 | J48: 2854 | K48: 2563
A49: Net profit | B49: 6212 | C49: 6106 | D49: 7969 | E49: 6368 | F49: 6506 | G49: 6806 | H49: 7033 | I49: 6921 | J49: 7364 | K49: 6654
A50: Operating Profit | B50: 9440 | C50: 9137 | D50: 8784 | E50: 9437 | F50: 9809 | G50: 10115 | H50: 9874 | I50: 9943 | J50: 10535 | K50: 10634
A55: BALANCE SHEET
A56: Report Date | B56: 42460 | C56: 42825 | D56: 43190 | E56: 43555 | F56: 43921 | G56: 44286 | H56: 44651 | I56: 45016 | J56: 45382 | K56: 45747
A57: Equity Share Capital | B57: 1144 | C57: 1144 | D57: 1088 | E57: 2170 | F57: 2122 | G57: 2124 | H57: 2098 | I57: 2069 | J57: 2071 | K57: 2073
A58: Reserves | B58: 60600 | C58: 67838 | D58: 63835 | E58: 62778 | F58: 63328 | G58: 74227 | H58: 73252 | I58: 73338 | J58: 86045 | K58: 93745
A59: Borrowings | F59: 4633 | G59: 5325 | H59: 5474 | I59: 8299 | J59: 8359 | K59: 8227
A60: Other Liabilities | B60: 13354 | C60: 14166 | D60: 14426 | E60: 19118 | F60: 21717 | G60: 25835 | H60: 35905 | I60: 40890 | J60: 40885 | K60: 43750
A61: Total | B61: 75098 | C61: 83148 | D61: 79349 | E61: 84066 | F61: 91800 | G61: 107511 | H61: 116729 | I61: 124596 | J61: 137360 | K61: 147795
A62: Net Block | B62: 13386 | C62: 14179 | D62: 12574 | E62: 15710 | F62: 23789 | G62: 25505 | H62: 25800 | I62: 29225 | J62: 27622 | K62: 30961
A63: Capital Work in Progress | B63: 960 | C63: 1365 | D63: 1606 | E63: 1388 | F63: 954 | G63: 922 | H63: 416 | I63: 288 | J63: 293 | K63: 814
A64: Investments | B64: 1892 | C64: 16423 | D64: 12163 | E64: 11261 | F64: 8792 | G64: 14205 | H64: 20324 | I64: 19478 | J64: 24623 | K64: 23541
A65: Other Assets | B65: 58860 | C65: 51181 | D65: 53006 | E65: 55707 | F65: 58265 | G65: 66879 | H65: 70189 | I65: 75605 | J65: 84822 | K65: 92479
A66: Total | B66: 75098 | C66: 83148 | D66: 79349 | E66: 84066 | F66: 91800 | G66: 107511 | H66: 116729 | I66: 124596 | J66: 137360 | K66: 147795
A67: Receivables | B67: 11330 | C67: 12322 | D67: 13142 | E67: 14827 | F67: 18487 | G67: 19294 | H67: 22698 | I67: 25424 | J67: 30193 | K67: 31158
A68: Inventory
A69: Cash & Bank | B69: 32697 | C69: 22625 | D69: 19818 | E69: 19568 | F69: 18649 | G69: 24714 | H69: 17472 | I69: 12173 | J69: 14786 | K69: 24455
A70: No. of Equity Shares | B70: 2285621088 | C70: 2285655150 | D70: 2173312301 | E70: 4335954462 | F70: 4240753210 | G70: 4245146114 | H70: 4193012929 | I70: 4136387925 | J70: 4139950635 | K70: 4143607528
A71: New Bonus Shares | B71: 1148472332 | E71: 2184191490
A72: Face value | B72: 5 | C72: 5 | D72: 5 | E72: 5 | F72: 5 | G72: 5 | H72: 5 | I72: 5 | J72: 5 | K72: 5
A74: Other Assets | B74: =B65-SUM(B67:B69) -> 14833 | C74: =C65-SUM(C67:C69) -> 16234 | D74: =D65-SUM(D67:D69) -> 20046 | E74: =E65-SUM(E67:E69) -> 21312 | F74: =F65-SUM(F67:F69) -> 21129 | G74: =G65-SUM(G67:G69) -> 22871 | H74: =H65-SUM(H67:H69) -> 30019 | I74: =I65-SUM(I67:I69) -> 38008 | ... K74: =K65-SUM(K67:K69) -> 36866
A76: Total Assets | B76: =B61 -> 75098 | C76: =C61 -> 83148 | D76: =D61 -> 79349 | E76: =E61 -> 84066 | F76: =F61 -> 91800 | G76: =G61 -> 107511 | H76: =H61 -> 116729 | I76: =I61 -> 124596 | ... K76: =K61 -> 147795
A82: CASH FLOW:
A83: Report Date | B83: 42460 | C83: 42825 | D83: 43190 | E83: 43555 | F83: 43921 | G83: 44286 | H83: 44651 | I83: 45016 | J83: 45382 | K83: 45747
A84: Cash from Operating Activity | B84: 10028 | C84: 11531 | D84: 13218 | E84: 14841 | F84: 17003 | G84: 23224 | H84: 23885 | I84: 22467 | J84: 25210 | K84: 35694
A85: Cash from Investing Activity | B85: -885 | C85: -14664 | D85: 4533 | E85: -632 | F85: -331 | G85: -7373 | H85: -6485 | I85: -1071 | J85: -5093 | K85: -1864
A86: Cash from Financing Activity | B86: -6813 | C86: -6939 | D86: -20505 | E86: -14512 | F86: -17591 | G86: -9786 | H86: -24642 | I86: -26695 | J86: -17504 | K86: -24161
A87: Net Cash Flow | B87: 2330 | C87: -10072 | D87: -2754 | E87: -303 | F87: -919 | G87: 6065 | H87: -7242 | I87: -5299 | J87: 2613 | K87: 9669
A92: PRICE: | B92: 609.15 | C92: 511.13 | D92: 565.9 | E92: 743.85 | F92: 641.5 | G92: 1368.05 | H92: 1906.85 | I92: 1427.95 | J92: 1498.05 | K92: 1570.65
A94: DERIVED:
A95: Adjusted Equity Shares in Cr | B95: 459.39 | C95: 459.39 | D95: 436.82 | E95: 436.89 | F95: 425.9 | G95: 426.07 | H95: 420.67 | I95: 414.86 | J95: 415.09 | K95: 415.33
